Workbook

Sheet Summary
A1: Hisab-Kitab AI — Testing Report v2: Employee, Customer, Supplier, Expense, Family, Stock, Purchase, Report, Correction, Router (before vs after fixes) + holdout on unseen data
A2: Model gpt-4o-mini · test dates 2026-10-04 to 2026-10-08 · every number below is a live formula over the bundle sheets. After-fix numbers are Hinglish; Hindi and English after-fix runs are planned once all bundles are fixed.
A3: z (95%) | B3: 1.96 | C3: Wilson interval z-value (input).
A4: Final result on unseen data (Holdout round 2, 135 statements): | E4: ='Holdout Summary'!G16 -> 0.75301205 | F4: strict accuracy | G4: ='Holdout Summary'!K16 -> 0.096385542 | H4: silent-error rate (see 'Holdout Summary')
A5: 1. Before vs after — all categories
A6: Bundle / run | B6: Rows | C6: Strict accuracy | D6: 95% CI low | E6: 95% CI high | F6: Safe rate | G6: Silent-error rate
A7: Employee — before (v1), Hinglish | B7: =B40 -> 64 | C7: =G40 -> 0.421875 | D7: =H40 -> 0.30869594 | E7: =I40 -> 0.54390188 | F7: =J40 -> 0.46875 | G7: =K40 -> 0.234375
A8: Employee — after fixes (full run 5 Oct 13:49), Hinglish | B8: =B50 -> 66 | C8: =G50 -> 0.89393939 | D8: =H50 -> 0.79687474 | E8: =I50 -> 0.94766719 | F8: =J50 -> 0.90909091 | G8: =K50 -> 0.075757576
A9: Customer — before (v1), Hinglish | B9: =B60 -> 72 | C9: =G60 -> 0.54166667 | D9: =H60 -> 0.42739664 | E9: =I60 -> 0.65171561 | F9: =J60 -> 0.54166667 | G9: =K60 -> 0.16666667
A10: Customer — after fixes (full run 5 Oct 22:14), Hinglish | B10: =B70 -> 67 | C10: =G70 -> 0.95522388 | D10: =H70 -> 0.87641967 | E10: =I70 -> 0.9846563 | F10: =J70 -> 0.98507463 | G10: =K70 -> 0.014925373
A11: Supplier — before (baseline), Hinglish | B11: =B80 -> 86 | C11: =G80 -> 0.51162791 | D11: =H80 -> 0.40776537 | E11: =I80 -> 0.61449603 | F11: =J80 -> 0.58139535 | G11: =K80 -> 0.15116279
A12: Supplier — after fixes (full run 6 Oct 15:27), Hinglish | B12: =B90 -> 82 | C12: =G90 -> 0.85365854 | D12: =H90 -> 0.76140386 | E12: =I90 -> 0.91425922 | F12: =J90 -> 0.8902439 | G12: =K90 -> 0.085365854
A13: Expense — before (baseline), Hinglish | B13: =B100 -> 109 | C13: =G100 -> 0.47706422 | D13: =H100 -> 0.38568353 | E13: =I100 -> 0.57000657 | F13: =J100 -> 0.55963303 | G13: =K100 -> 0.10091743
A14: Expense — after fixes (full run 6 Oct 17:42), Hinglish | B14: =B110 -> 105 | C14: =G110 -> 0.96190476 | D14: =H110 -> 0.90611558 | E14: =I110 -> 0.98508778 | F14: =J110 -> 0.99047619 | G14: =K110 -> 0
A15: Family — before (baseline), Hinglish | B15: =B120 -> 75 | C15: =G120 -> 0.54666667 | D15: =H120 -> 0.43448174 | E15: =I120 -> 0.65430388 | F15: =J120 -> 0.65333333 | G15: =K120 -> 0.16
A16: Family — after fixes (full run 7 Oct 12:15), Hinglish | B16: =B130 -> 69 | C16: =G130 -> 0.97101449 | D16: =H130 -> 0.90033227 | E16: =I130 -> 0.99201496 | F16: =J130 -> 0.98550725 | G16: =K130 -> 0.014492754
A17: Stock — before (baseline), Hinglish | B17: =B140 -> 67 | C17: =G140 -> 0.62686567 | D17: =H140 -> 0.50715186 | E17: =I140 -> 0.73282013 | F17: =J140 -> 0.64179104 | G17: =K140 -> 0.059701493
A18: Stock — after fixes (full run 8 Oct 07:07), Hinglish | B18: =B150 -> 64 | C18: =G150 -> 0.96875 | D18: =H150 -> 0.89302506 | E18: =I150 -> 0.99138804 | F18: =J150 -> 0.96875 | G18: =K150 -> 0
A19: Purchase — before (baseline), Hinglish | B19: =B160 -> 74 | C19: =G160 -> 0.75675676 | D19: =H160 -> 0.64793456 | E19: =I160 -> 0.84023629 | F19: =J160 -> 0.75675676 | G19: =K160 -> 0.10810811
A20: Purchase — after fixes (full run 8 Oct 13:17), Hinglish | B20: =B170 -> 72 | C20: =G170 -> 0.88888889 | D20: =H170 -> 0.79576856 | E20: =I170 -> 0.94261249 | F20: =J170 -> 0.88888889 | G20: =K170 -> 0.027777778
A21: Report — before (baseline), Hinglish | B21: =B179 -> 20 | C21: =G179 -> 0.7 | D21: =H179 -> 0.48102322 | E21: =I179 -> 0.85452473 | F21: =J179 -> 0.7 | G21: =K179 -> 0.25
A22: Report — after fixes (full run 8 Oct 11:16), Hinglish | B22: =B189 -> 20 | C22: =G189 -> 1 | D22: =H189 -> 0.83886987 | E22: =I189 -> 1 | F22: =J189 -> 1 | G22: =K189 -> 0
A23: Correction — before (baseline), Hinglish | B23: =B199 -> 25 | C23: =G199 -> 0.76 | D23: =H199 -> 0.5656994 | E23: =I199 -> 0.88503842 | F23: =J199 -> 0.76 | G23: =K199 -> 0.24
A24: Correction — after fixes (latest per test: 11:28 full + 11:57 re-run), Hinglish | B24: =B209 -> 25 | C24: =G209 -> 0.96 | D24: =H209 -> 0.80455528 | E24: =I209 -> 0.99290395 | F24: =J209 -> 0.96 | G24: =K209 -> 0.04
A25: Router — single full run (12:27), Hinglish | B25: =B219 -> 30 | C25: =G219 -> 1 | D25: =H219 -> 0.88648291 | E25: =I219 -> 1 | F25: =J219 -> 1 | G25: =K219 -> 0
A26: Employee — before (v1), Hindi | B26: =B230 -> 64 | C26: =G230 -> 0.4375 | D26: =H230 -> 0.32293817 | E26: =I230 -> 0.55914008 | F26: =J230 -> 0.53125 | G26: =K230 -> 0.140625
A27: Employee — before (v1), English | B27: =B240 -> 66 | C27: =G240 -> 0.48484848 | D27: =H240 -> 0.36846762 | E27: =I240 -> 0.60289615 | F27: =J240 -> 0.53030303 | G27: =K240 -> 0.16666667
A28: Employee F — fields correct (latest per test, not a full run) | B28: =COUNTA('Employee F'!$G$5:$G$63) -> 59 | C28: =IF(B28=0,"",COUNTIF('Employee F'!$G$5:$G$63,"Y")/B28) -> 0.86440678
A29: After = the last FULL run of each bundle (every test in one run; run file named in the row). Exceptions, marked in the row: Correction and Employee F (latest result per test).
A30: Supplier fixes changed shared steps (extraction, grouping, dates, amounts). Customer and Employee were re-checked on ~40 selected tests (all passed), not re-run in full — see Known issues.
A33: 2. Employee — before (v1), Hinglish
A34: Category | B34: Rows | C34: Correct | D34: Safe ask | E34: Silent wrong | F34: Missed | G34: Strict accuracy | H34: 95% CI low | I34: 95% CI high | J34: Safe rate | K34: Silent-error rate
A35: A - Daily | B35: =COUNTIFS(Employee!$M$5:$M$72,"<>",Employee!$B$5:$B$72,"A - Daily") -> 10 | C35: =COUNTIFS(Employee!$M$5:$M$72,"Correct",Employee!$B$5:$B$72,"A - Daily") -> 4 | D35: =COUNTIFS(Employee!$M$5:$M$72,"Safe ask",Employee!$B$5:$B$72,"A - Daily") -> 0 | E35: =COUNTIFS(Employee!$M$5:$M$72,"Silent wrong",Employee!$B$5:$B$72,"A - Daily") -> 1 | F35: =COUNTIFS(Employee!$M$5:$M$72,"Missed",Employee!$B$5:$B$72,"A - Daily") -> 5 | G35: =IF(B35=0,"",C35/B35) -> 0.4 | H35: =IF(B35=0,"",(((C35/B35)+$B$3^2/(2*B35))-($B$3*SQRT((C35/B35)*(1-(C35/B35))/B35+$B$3^2/(4*B35^2))))/(1+$B$3^2/B35)) -> 0.16817758 | I35: =IF(B35=0,"",(((C35/B35)+$B$3^2/(2*B35))+($B$3*SQRT((C35/B35)*(1-(C35/B35))/B35+$B$3^2/(4*B35^2))))/(1+$B$3^2/B35)) -> 0.68733045 | J35: =IF(B35=0,"",(C35+D35)/B35) -> 0.4 | K35: =IF(B35=0,"",E35/B35) -> 0.1
A36: B - Tricky | B36: =COUNTIFS(Employee!$M$5:$M$72,"<>",Employee!$B$5:$B$72,"B - Tricky") -> 10 | C36: =COUNTIFS(Employee!$M$5:$M$72,"Correct",Employee!$B$5:$B$72,"B - Tricky") -> 5 | D36: =COUNTIFS(Employee!$M$5:$M$72,"Safe ask",Employee!$B$5:$B$72,"B - Tricky") -> 0 | E36: =COUNTIFS(Employee!$M$5:$M$72,"Silent wrong",Employee!$B$5:$B$72,"B - Tricky") -> 4 | F36: =COUNTIFS(Employee!$M$5:$M$72,"Missed",Employee!$B$5:$B$72,"B - Tricky") -> 1 | G36: =IF(B36=0,"",C36/B36) -> 0.5 | H36: =IF(B36=0,"",(((C36/B36)+$B$3^2/(2*B36))-($B$3*SQRT((C36/B36)*(1-(C36/B36))/B36+$B$3^2/(4*B36^2))))/(1+$B$3^2/B36)) -> 0.23658959 | I36: =IF(B36=0,"",(((C36/B36)+$B$3^2/(2*B36))+($B$3*SQRT((C36/B36)*(1-(C36/B36))/B36+$B$3^2/(4*B36^2))))/(1+$B$3^2/B36)) -> 0.76341041 | J36: =IF(B36=0,"",(C36+D36)/B36) -> 0.5 | K36: =IF(B36=0,"",E36/B36) -> 0.4
A37: C - Edge | B37: =COUNTIFS(Employee!$M$5:$M$72,"<>",Employee!$B$5:$B$72,"C - Edge") -> 10 | C37: =COUNTIFS(Employee!$M$5:$M$72,"Correct",Employee!$B$5:$B$72,"C - Edge") -> 3 | D37: =COUNTIFS(Employee!$M$5:$M$72,"Safe ask",Employee!$B$5:$B$72,"C - Edge") -> 2 | E37: =COUNTIFS(Employee!$M$5:$M$72,"Silent wrong",Employee!$B$5:$B$72,"C - Edge") -> 3 | F37: =COUNTIFS(Employee!$M$5:$M$72,"Missed",Employee!$B$5:$B$72,"C - Edge") -> 2 | G37: =IF(B37=0,"",C37/B37) -> 0.3 | H37: =IF(B37=0,"",(((C37/B37)+$B$3^2/(2*B37))-($B$3*SQRT((C37/B37)*(1-(C37/B37))/B37+$B$3^2/(4*B37^2))))/(1+$B$3^2/B37)) -> 0.10778929 | I37: =IF(B37=0,"",(((C37/B37)+$B$3^2/(2*B37))+($B$3*SQRT((C37/B37)*(1-(C37/B37))/B37+$B$3^2/(4*B37^2))))/(1+$B$3^2/B37)) -> 0.60322678 | J37: =IF(B37=0,"",(C37+D37)/B37) -> 0.5 | K37: =IF(B37=0,"",E37/B37) -> 0.3
A38: D - Other business | B38: =COUNTIFS(Employee!$M$5:$M$72,"<>",Employee!$B$5:$B$72,"D - Other business") -> 10 | C38: =COUNTIFS(Employee!$M$5:$M$72,"Correct",Employee!$B$5:$B$72,"D - Other business") -> 3 | D38: =COUNTIFS(Employee!$M$5:$M$72,"Safe ask",Employee!$B$5:$B$72,"D - Other business") -> 1 | E38: =COUNTIFS(Employee!$M$5:$M$72,"Silent wrong",Employee!$B$5:$B$72,"D - Other business") -> 5 | F38: =COUNTIFS(Employee!$M$5:$M$72,"Missed",Employee!$B$5:$B$72,"D - Other business") -> 1 | G38: =IF(B38=0,"",C38/B38) -> 0.3 | H38: =IF(B38=0,"",(((C38/B38)+$B$3^2/(2*B38))-($B$3*SQRT((C38/B38)*(1-(C38/B38))/B38+$B$3^2/(4*B38^2))))/(1+$B$3^2/B38)) -> 0.10778929 | I38: =IF(B38=0,"",(((C38/B38)+$B$3^2/(2*B38))+($B$3*SQRT((C38/B38)*(1-(C38/B38))/B38+$B$3^2/(4*B38^2))))/(1+$B$3^2/B38)) -> 0.60322678 | J38: =IF(B38=0,"",(C38+D38)/B38) -> 0.4 | K38: =IF(B38=0,"",E38/B38) -> 0.5
A39: E - Mixed | B39: =COUNTIFS(Employee!$M$5:$M$72,"<>",Employee!$B$5:$B$72,"E - Mixed") -> 24 | C39: =COUNTIFS(Employee!$M$5:$M$72,"Correct",Employee!$B$5:$B$72,"E - Mixed") -> 12 | D39: =COUNTIFS(Employee!$M$5:$M$72,"Safe ask",Employee!$B$5:$B$72,"E - Mixed") -> 0 | E39: =COUNTIFS(Employee!$M$5:$M$72,"Silent wrong",Employee!$B$5:$B$72,"E - Mixed") -> 2 | F39: =COUNTIFS(Employee!$M$5:$M$72,"Missed",Employee!$B$5:$B$72,"E - Mixed") -> 10 | G39: =IF(B39=0,"",C39/B39) -> 0.5 | H39: =IF(B39=0,"",(((C39/B39)+$B$3^2/(2*B39))-($B$3*SQRT((C39/B39)*(1-(C39/B39))/B39+$B$3^2/(4*B39^2))))/(1+$B$3^2/B39)) -> 0.31427132 | I39: =IF(B39=0,"",(((C39/B39)+$B$3^2/(2*B39))+($B$3*SQRT((C39/B39)*(1-(C39/B39))/B39+$B$3^2/(4*B39^2))))/(1+$B$3^2/B39)) -> 0.68572868 | J39: =IF(B39=0,"",(C39+D39)/B39) -> 0.5 | K39: =IF(B39=0,"",E39/B39) -> 0.083333333
A40: All categories | B40: =COUNTIFS(Employee!$M$5:$M$72,"<>") -> 64 | C40: =COUNTIFS(Employee!$M$5:$M$72,"Correct") -> 27 | D40: =COUNTIFS(Employee!$M$5:$M$72,"Safe ask") -> 3 | E40: =COUNTIFS(Employee!$M$5:$M$72,"Silent wrong") -> 15 | F40: =COUNTIFS(Employee!$M$5:$M$72,"Missed") -> 19 | G40: =IF(B40=0,"",C40/B40) -> 0.421875 | H40: =IF(B40=0,"",(((C40/B40)+$B$3^2/(2*B40))-($B$3*SQRT((C40/B40)*(1-(C40/B40))/B40+$B$3^2/(4*B40^2))))/(1+$B$3^2/B40)) -> 0.30869594 | I40: =IF(B40=0,"",(((C40/B40)+$B$3^2/(2*B40))+($B$3*SQRT((C40/B40)*(1-(C40/B40))/B40+$B$3^2/(4*B40^2))))/(1+$B$3^2/B40)) -> 0.54390188 | J40: =IF(B40=0,"",(C40+D40)/B40) -> 0.46875 | K40: =IF(B40=0,"",E40/B40) -> 0.234375
A43: 3. Employee — after fixes (full run 5 Oct 13:49), Hinglish
A44: Category | B44: Rows | C44: Correct | D44: Safe ask | E44: Silent wrong | F44: Missed | G44: Strict accuracy | H44: 95% CI low | I44: 95% CI high | J44: Safe rate | K44: Silent-error rate
A45: A - Daily | B45: =COUNTIFS(Employee!$R$5:$R$72,"<>",Employee!$B$5:$B$72,"A - Daily") -> 10 | C45: =COUNTIFS(Employee!$R$5:$R$72,"Correct",Employee!$B$5:$B$72,"A - Daily") -> 10 | D45: =COUNTIFS(Employee!$R$5:$R$72,"Safe ask",Employee!$B$5:$B$72,"A - Daily") -> 0 | E45: =COUNTIFS(Employee!$R$5:$R$72,"Silent wrong",Employee!$B$5:$B$72,"A - Daily") -> 0 | F45: =COUNTIFS(Employee!$R$5:$R$72,"Missed",Employee!$B$5:$B$72,"A - Daily") -> 0 | G45: =IF(B45=0,"",C45/B45) -> 1 | H45: =IF(B45=0,"",(((C45/B45)+$B$3^2/(2*B45))-($B$3*SQRT((C45/B45)*(1-(C45/B45))/B45+$B$3^2/(4*B45^2))))/(1+$B$3^2/B45)) -> 0.72245983 | I45: =IF(B45=0,"",(((C45/B45)+$B$3^2/(2*B45))+($B$3*SQRT((C45/B45)*(1-(C45/B45))/B45+$B$3^2/(4*B45^2))))/(1+$B$3^2/B45)) -> 1 | J45: =IF(B45=0,"",(C45+D45)/B45) -> 1 | K45: =IF(B45=0,"",E45/B45) -> 0
A46: B - Tricky | B46: =COUNTIFS(Employee!$R$5:$R$72,"<>",Employee!$B$5:$B$72,"B - Tricky") -> 11 | C46: =COUNTIFS(Employee!$R$5:$R$72,"Correct",Employee!$B$5:$B$72,"B - Tricky") -> 10 | D46: =COUNTIFS(Employee!$R$5:$R$72,"Safe ask",Employee!$B$5:$B$72,"B - Tricky") -> 0 | E46: =COUNTIFS(Employee!$R$5:$R$72,"Silent wrong",Employee!$B$5:$B$72,"B - Tricky") -> 1 | F46: =COUNTIFS(Employee!$R$5:$R$72,"Missed",Employee!$B$5:$B$72,"B - Tricky") -> 0 | G46: =IF(B46=0,"",C46/B46) -> 0.90909091 | H46: =IF(B46=0,"",(((C46/B46)+$B$3^2/(2*B46))-($B$3*SQRT((C46/B46)*(1-(C46/B46))/B46+$B$3^2/(4*B46^2))))/(1+$B$3^2/B46)) -> 0.62263537 | I46: =IF(B46=0,"",(((C46/B46)+$B$3^2/(2*B46))+($B$3*SQRT((C46/B46)*(1-(C46/B46))/B46+$B$3^2/(4*B46^2))))/(1+$B$3^2/B46)) -> 0.98376825 | J46: =IF(B46=0,"",(C46+D46)/B46) -> 0.90909091 | K46: =IF(B46=0,"",E46/B46) -> 0.090909091
A47: C - Edge | B47: =COUNTIFS(Employee!$R$5:$R$72,"<>",Employee!$B$5:$B$72,"C - Edge") -> 10 | C47: =COUNTIFS(Employee!$R$5:$R$72,"Correct",Employee!$B$5:$B$72,"C - Edge") -> 6 | D47: =COUNTIFS(Employee!$R$5:$R$72,"Safe ask",Employee!$B$5:$B$72,"C - Edge") -> 1 | E47: =COUNTIFS(Employee!$R$5:$R$72,"Silent wrong",Employee!$B$5:$B$72,"C - Edge") -> 3 | F47: =COUNTIFS(Employee!$R$5:$R$72,"Missed",Employee!$B$5:$B$72,"C - Edge") -> 0 | G47: =IF(B47=0,"",C47/B47) -> 0.6 | H47: =IF(B47=0,"",(((C47/B47)+$B$3^2/(2*B47))-($B$3*SQRT((C47/B47)*(1-(C47/B47))/B47+$B$3^2/(4*B47^2))))/(1+$B$3^2/B47)) -> 0.31266955 | I47: =IF(B47=0,"",(((C47/B47)+$B$3^2/(2*B47))+($B$3*SQRT((C47/B47)*(1-(C47/B47))/B47+$B$3^2/(4*B47^2))))/(1+$B$3^2/B47)) -> 0.83182242 | J47: =IF(B47=0,"",(C47+D47)/B47) -> 0.7 | K47: =IF(B47=0,"",E47/B47) -> 0.3
A48: D - Other business | B48: =COUNTIFS(Employee!$R$5:$R$72,"<>",Employee!$B$5:$B$72,"D - Other business") -> 11 | C48: =COUNTIFS(Employee!$R$5:$R$72,"Correct",Employee!$B$5:$B$72,"D - Other business") -> 9 | D48: =COUNTIFS(Employee!$R$5:$R$72,"Safe ask",Employee!$B$5:$B$72,"D - Other business") -> 0 | E48: =COUNTIFS(Employee!$R$5:$R$72,"Silent wrong",Employee!$B$5:$B$72,"D - Other business") -> 1 | F48: =COUNTIFS(Employee!$R$5:$R$72,"Missed",Employee!$B$5:$B$72,"D - Other business") -> 1 | G48: =IF(B48=0,"",C48/B48) -> 0.81818182 | H48: =IF(B48=0,"",(((C48/B48)+$B$3^2/(2*B48))-($B$3*SQRT((C48/B48)*(1-(C48/B48))/B48+$B$3^2/(4*B48^2))))/(1+$B$3^2/B48)) -> 0.52301386 | I48: =IF(B48=0,"",(((C48/B48)+$B$3^2/(2*B48))+($B$3*SQRT((C48/B48)*(1-(C48/B48))/B48+$B$3^2/(4*B48^2))))/(1+$B$3^2/B48)) -> 0.9486334 | J48: =IF(B48=0,"",(C48+D48)/B48) -> 0.81818182 | K48: =IF(B48=0,"",E48/B48) -> 0.090909091
A49: E - Mixed | B49: =COUNTIFS(Employee!$R$5:$R$72,"<>",Employee!$B$5:$B$72,"E - Mixed") -> 24 | C49: =COUNTIFS(Employee!$R$5:$R$72,"Correct",Employee!$B$5:$B$72,"E - Mixed") -> 24 | D49: =COUNTIFS(Employee!$R$5:$R$72,"Safe ask",Employee!$B$5:$B$72,"E - Mixed") -> 0 | E49: =COUNTIFS(Employee!$R$5:$R$72,"Silent wrong",Employee!$B$5:$B$72,"E - Mixed") -> 0 | F49: =COUNTIFS(Employee!$R$5:$R$72,"Missed",Employee!$B$5:$B$72,"E - Mixed") -> 0 | G49: =IF(B49=0,"",C49/B49) -> 1 | H49: =IF(B49=0,"",(((C49/B49)+$B$3^2/(2*B49))-($B$3*SQRT((C49/B49)*(1-(C49/B49))/B49+$B$3^2/(4*B49^2))))/(1+$B$3^2/B49)) -> 0.86201942 | I49: =IF(B49=0,"",(((C49/B49)+$B$3^2/(2*B49))+($B$3*SQRT((C49/B49)*(1-(C49/B49))/B49+$B$3^2/(4*B49^2))))/(1+$B$3^2/B49)) -> 1 | J49: =IF(B49=0,"",(C49+D49)/B49) -> 1 | K49: =IF(B49=0,"",E49/B49) -> 0
A50: All categories | B50: =COUNTIFS(Employee!$R$5:$R$72,"<>") -> 66 | C50: =COUNTIFS(Employee!$R$5:$R$72,"Correct") -> 59 | D50: =COUNTIFS(Employee!$R$5:$R$72,"Safe ask") -> 1 | E50: =COUNTIFS(Employee!$R$5:$R$72,"Silent wrong") -> 5 | F50: =COUNTIFS(Employee!$R$5:$R$72,"Missed") -> 1 | G50: =IF(B50=0,"",C50/B50) -> 0.89393939 | H50: =IF(B50=0,"",(((C50/B50)+$B$3^2/(2*B50))-($B$3*SQRT((C50/B50)*(1-(C50/B50))/B50+$B$3^2/(4*B50^2))))/(1+$B$3^2/B50)) -> 0.79687474 | I50: =IF(B50=0,"",(((C50/B50)+$B$3^2/(2*B50))+($B$3*SQRT((C50/B50)*(1-(C50/B50))/B50+$B$3^2/(4*B50^2))))/(1+$B$3^2/B50)) -> 0.94766719 | J50: =IF(B50=0,"",(C50+D50)/B50) -> 0.90909091 | K50: =IF(B50=0,"",E50/B50) -> 0.075757576
A53: 4. Customer — before (v1), Hinglish
A54: Category | B54: Rows | C54: Correct | D54: Safe ask | E54: Silent wrong | F54: Missed | G54: Strict accuracy | H54: 95% CI low | I54: 95% CI high | J54: Safe rate | K54: Silent-error rate
A55: A - Daily | B55: =COUNTIFS(Customer!$M$5:$M$76,"<>",Customer!$B$5:$B$76,"A - Daily") -> 12 | C55: =COUNTIFS(Customer!$M$5:$M$76,"Correct",Customer!$B$5:$B$76,"A - Daily") -> 9 | D55: =COUNTIFS(Customer!$M$5:$M$76,"Safe ask",Customer!$B$5:$B$76,"A - Daily") -> 0 | E55: =COUNTIFS(Customer!$M$5:$M$76,"Silent wrong",Customer!$B$5:$B$76,"A - Daily") -> 1 | F55: =COUNTIFS(Customer!$M$5:$M$76,"Missed",Customer!$B$5:$B$76,"A - Daily") -> 2 | G55: =IF(B55=0,"",C55/B55) -> 0.75 | H55: =IF(B55=0,"",(((C55/B55)+$B$3^2/(2*B55))-($B$3*SQRT((C55/B55)*(1-(C55/B55))/B55+$B$3^2/(4*B55^2))))/(1+$B$3^2/B55)) -> 0.46768966 | I55: =IF(B55=0,"",(((C55/B55)+$B$3^2/(2*B55))+($B$3*SQRT((C55/B55)*(1-(C55/B55))/B55+$B$3^2/(4*B55^2))))/(1+$B$3^2/B55)) -> 0.91105996 | J55: =IF(B55=0,"",(C55+D55)/B55) -> 0.75 | K55: =IF(B55=0,"",E55/B55) -> 0.083333333
A56: B - Tricky | B56: =COUNTIFS(Customer!$M$5:$M$76,"<>",Customer!$B$5:$B$76,"B - Tricky") -> 10 | C56: =COUNTIFS(Customer!$M$5:$M$76,"Correct",Customer!$B$5:$B$76,"B - Tricky") -> 5 | D56: =COUNTIFS(Customer!$M$5:$M$76,"Safe ask",Customer!$B$5:$B$76,"B - Tricky") -> 0 | E56: =COUNTIFS(Customer!$M$5:$M$76,"Silent wrong",Customer!$B$5:$B$76,"B - Tricky") -> 1 | F56: =COUNTIFS(Customer!$M$5:$M$76,"Missed",Customer!$B$5:$B$76,"B - Tricky") -> 4 | G56: =IF(B56=0,"",C56/B56) -> 0.5 | H56: =IF(B56=0,"",(((C56/B56)+$B$3^2/(2*B56))-($B$3*SQRT((C56/B56)*(1-(C56/B56))/B56+$B$3^2/(4*B56^2))))/(1+$B$3^2/B56)) -> 0.23658959 | I56: =IF(B56=0,"",(((C56/B56)+$B$3^2/(2*B56))+($B$3*SQRT((C56/B56)*(1-(C56/B56))/B56+$B$3^2/(4*B56^2))))/(1+$B$3^2/B56)) -> 0.76341041 | J56: =IF(B56=0,"",(C56+D56)/B56) -> 0.5 | K56: =IF(B56=0,"",E56/B56) -> 0.1
A57: C - Edge | B57: =COUNTIFS(Customer!$M$5:$M$76,"<>",Customer!$B$5:$B$76,"C - Edge") -> 11 | C57: =COUNTIFS(Customer!$M$5:$M$76,"Correct",Customer!$B$5:$B$76,"C - Edge") -> 7 | D57: =COUNTIFS(Customer!$M$5:$M$76,"Safe ask",Customer!$B$5:$B$76,"C - Edge") -> 0 | E57: =COUNTIFS(Customer!$M$5:$M$76,"Silent wrong",Customer!$B$5:$B$76,"C - Edge") -> 3 | F57: =COUNTIFS(Customer!$M$5:$M$76,"Missed",Customer!$B$5:$B$76,"C - Edge") -> 1 | G57: =IF(B57=0,"",C57/B57) -> 0.63636364 | H57: =IF(B57=0,"",(((C57/B57)+$B$3^2/(2*B57))-($B$3*SQRT((C57/B57)*(1-(C57/B57))/B57+$B$3^2/(4*B57^2))))/(1+$B$3^2/B57)) -> 0.35379678 | I57: =IF(B57=0,"",(((C57/B57)+$B$3^2/(2*B57))+($B$3*SQRT((C57/B57)*(1-(C57/B57))/B57+$B$3^2/(4*B57^2))))/(1+$B$3^2/B57)) -> 0.84833776 | J57: =IF(B57=0,"",(C57+D57)/B57) -> 0.63636364 | K57: =IF(B57=0,"",E57/B57) -> 0.27272727
A58: D - Other business | B58: =COUNTIFS(Customer!$M$5:$M$76,"<>",Customer!$B$5:$B$76,"D - Other business") -> 15 | C58: =COUNTIFS(Customer!$M$5:$M$76,"Correct",Customer!$B$5:$B$76,"D - Other business") -> 4 | D58: =COUNTIFS(Customer!$M$5:$M$76,"Safe ask",Customer!$B$5:$B$76,"D - Other business") -> 0 | E58: =COUNTIFS(Customer!$M$5:$M$76,"Silent wrong",Customer!$B$5:$B$76,"D - Other business") -> 1 | F58: =COUNTIFS(Customer!$M$5:$M$76,"Missed",Customer!$B$5:$B$76,"D - Other business") -> 10 | G58: =IF(B58=0,"",C58/B58) -> 0.26666667 | H58: =IF(B58=0,"",(((C58/B58)+$B$3^2/(2*B58))-($B$3*SQRT((C58/B58)*(1-(C58/B58))/B58+$B$3^2/(4*B58^2))))/(1+$B$3^2/B58)) -> 0.10897276 | I58: =IF(B58=0,"",(((C58/B58)+$B$3^2/(2*B58))+($B$3*SQRT((C58/B58)*(1-(C58/B58))/B58+$B$3^2/(4*B58^2))))/(1+$B$3^2/B58)) -> 0.5195089 | J58: =IF(B58=0,"",(C58+D58)/B58) -> 0.26666667 | K58: =IF(B58=0,"",E58/B58) -> 0.066666667
A59: E - Mixed | B59: =COUNTIFS(Customer!$M$5:$M$76,"<>",Customer!$B$5:$B$76,"E - Mixed") -> 24 | C59: =COUNTIFS(Customer!$M$5:$M$76,"Correct",Customer!$B$5:$B$76,"E - Mixed") -> 14 | D59: =COUNTIFS(Customer!$M$5:$M$76,"Safe ask",Customer!$B$5:$B$76,"E - Mixed") -> 0 | E59: =COUNTIFS(Customer!$M$5:$M$76,"Silent wrong",Customer!$B$5:$B$76,"E - Mixed") -> 6 | F59: =COUNTIFS(Customer!$M$5:$M$76,"Missed",Customer!$B$5:$B$76,"E - Mixed") -> 4 | G59: =IF(B59=0,"",C59/B59) -> 0.58333333 | H59: =IF(B59=0,"",(((C59/B59)+$B$3^2/(2*B59))-($B$3*SQRT((C59/B59)*(1-(C59/B59))/B59+$B$3^2/(4*B59^2))))/(1+$B$3^2/B59)) -> 0.38834338 | I59: =IF(B59=0,"",(((C59/B59)+$B$3^2/(2*B59))+($B$3*SQRT((C59/B59)*(1-(C59/B59))/B59+$B$3^2/(4*B59^2))))/(1+$B$3^2/B59)) -> 0.75532653 | J59: =IF(B59=0,"",(C59+D59)/B59) -> 0.58333333 | K59: =IF(B59=0,"",E59/B59) -> 0.25
A60: All categories | B60: =COUNTIFS(Customer!$M$5:$M$76,"<>") -> 72 | C60: =COUNTIFS(Customer!$M$5:$M$76,"Correct") -> 39 | D60: =COUNTIFS(Customer!$M$5:$M$76,"Safe ask") -> 0 | E60: =COUNTIFS(Customer!$M$5:$M$76,"Silent wrong") -> 12 | F60: =COUNTIFS(Customer!$M$5:$M$76,"Missed") -> 21 | G60: =IF(B60=0,"",C60/B60) -> 0.54166667 | H60: =IF(B60=0,"",(((C60/B60)+$B$3^2/(2*B60))-($B$3*SQRT((C60/B60)*(1-(C60/B60))/B60+$B$3^2/(4*B60^2))))/(1+$B$3^2/B60)) -> 0.42739664 | I60: =IF(B60=0,"",(((C60/B60)+$B$3^2/(2*B60))+($B$3*SQRT((C60/B60)*(1-(C60/B60))/B60+$B$3^2/(4*B60^2))))/(1+$B$3^2/B60)) -> 0.65171561 | J60: =IF(B60=0,"",(C60+D60)/B60) -> 0.54166667 | K60: =IF(B60=0,"",E60/B60) -> 0.16666667
A63: 5. Customer — after fixes (full run 5 Oct 22:14), Hinglish
A64: Category | B64: Rows | C64: Correct | D64: Safe ask | E64: Silent wrong | F64: Missed | G64: Strict accuracy | H64: 95% CI low | I64: 95% CI high | J64: Safe rate | K64: Silent-error rate
A65: A - Daily | B65: =COUNTIFS(Customer!$P$5:$P$76,"<>",Customer!$B$5:$B$76,"A - Daily") -> 12 | C65: =COUNTIFS(Customer!$P$5:$P$76,"Correct",Customer!$B$5:$B$76,"A - Daily") -> 12 | D65: =COUNTIFS(Customer!$P$5:$P$76,"Safe ask",Customer!$B$5:$B$76,"A - Daily") -> 0 | E65: =COUNTIFS(Customer!$P$5:$P$76,"Silent wrong",Customer!$B$5:$B$76,"A - Daily") -> 0 | F65: =COUNTIFS(Customer!$P$5:$P$76,"Missed",Customer!$B$5:$B$76,"A - Daily") -> 0 | G65: =IF(B65=0,"",C65/B65) -> 1 | H65: =IF(B65=0,"",(((C65/B65)+$B$3^2/(2*B65))-($B$3*SQRT((C65/B65)*(1-(C65/B65))/B65+$B$3^2/(4*B65^2))))/(1+$B$3^2/B65)) -> 0.75749924 | I65: =IF(B65=0,"",(((C65/B65)+$B$3^2/(2*B65))+($B$3*SQRT((C65/B65)*(1-(C65/B65))/B65+$B$3^2/(4*B65^2))))/(1+$B$3^2/B65)) -> 1 | J65: =IF(B65=0,"",(C65+D65)/B65) -> 1 | K65: =IF(B65=0,"",E65/B65) -> 0
A66: B - Tricky | B66: =COUNTIFS(Customer!$P$5:$P$76,"<>",Customer!$B$5:$B$76,"B - Tricky") -> 10 | C66: =COUNTIFS(Customer!$P$5:$P$76,"Correct",Customer!$B$5:$B$76,"B - Tricky") -> 10 | D66: =COUNTIFS(Customer!$P$5:$P$76,"Safe ask",Customer!$B$5:$B$76,"B - Tricky") -> 0 | E66: =COUNTIFS(Customer!$P$5:$P$76,"Silent wrong",Customer!$B$5:$B$76,"B - Tricky") -> 0 | F66: =COUNTIFS(Customer!$P$5:$P$76,"Missed",Customer!$B$5:$B$76,"B - Tricky") -> 0 | G66: =IF(B66=0,"",C66/B66) -> 1 | H66: =IF(B66=0,"",(((C66/B66)+$B$3^2/(2*B66))-($B$3*SQRT((C66/B66)*(1-(C66/B66))/B66+$B$3^2/(4*B66^2))))/(1+$B$3^2/B66)) -> 0.72245983 | I66: =IF(B66=0,"",(((C66/B66)+$B$3^2/(2*B66))+($B$3*SQRT((C66/B66)*(1-(C66/B66))/B66+$B$3^2/(4*B66^2))))/(1+$B$3^2/B66)) -> 1 | J66: =IF(B66=0,"",(C66+D66)/B66) -> 1 | K66: =IF(B66=0,"",E66/B66) -> 0
A67: C - Edge | B67: =COUNTIFS(Customer!$P$5:$P$76,"<>",Customer!$B$5:$B$76,"C - Edge") -> 11 | C67: =COUNTIFS(Customer!$P$5:$P$76,"Correct",Customer!$B$5:$B$76,"C - Edge") -> 11 | D67: =COUNTIFS(Customer!$P$5:$P$76,"Safe ask",Customer!$B$5:$B$76,"C - Edge") -> 0 | E67: =COUNTIFS(Customer!$P$5:$P$76,"Silent wrong",Customer!$B$5:$B$76,"C - Edge") -> 0 | F67: =COUNTIFS(Customer!$P$5:$P$76,"Missed",Customer!$B$5:$B$76,"C - Edge") -> 0 | G67: =IF(B67=0,"",C67/B67) -> 1 | H67: =IF(B67=0,"",(((C67/B67)+$B$3^2/(2*B67))-($B$3*SQRT((C67/B67)*(1-(C67/B67))/B67+$B$3^2/(4*B67^2))))/(1+$B$3^2/B67)) -> 0.74115998 | I67: =IF(B67=0,"",(((C67/B67)+$B$3^2/(2*B67))+($B$3*SQRT((C67/B67)*(1-(C67/B67))/B67+$B$3^2/(4*B67^2))))/(1+$B$3^2/B67)) -> 1 | J67: =IF(B67=0,"",(C67+D67)/B67) -> 1 | K67: =IF(B67=0,"",E67/B67) -> 0
A68: D - Other business | B68: =COUNTIFS(Customer!$P$5:$P$76,"<>",Customer!$B$5:$B$76,"D - Other business") -> 14 | C68: =COUNTIFS(Customer!$P$5:$P$76,"Correct",Customer!$B$5:$B$76,"D - Other business") -> 14 | D68: =COUNTIFS(Customer!$P$5:$P$76,"Safe ask",Customer!$B$5:$B$76,"D - Other business") -> 0 | E68: =COUNTIFS(Customer!$P$5:$P$76,"Silent wrong",Customer!$B$5:$B$76,"D - Other business") -> 0 | F68: =COUNTIFS(Customer!$P$5:$P$76,"Missed",Customer!$B$5:$B$76,"D - Other business") -> 0 | G68: =IF(B68=0,"",C68/B68) -> 1 | H68: =IF(B68=0,"",(((C68/B68)+$B$3^2/(2*B68))-($B$3*SQRT((C68/B68)*(1-(C68/B68))/B68+$B$3^2/(4*B68^2))))/(1+$B$3^2/B68)) -> 0.78468299 | I68: =IF(B68=0,"",(((C68/B68)+$B$3^2/(2*B68))+($B$3*SQRT((C68/B68)*(1-(C68/B68))/B68+$B$3^2/(4*B68^2))))/(1+$B$3^2/B68)) -> 1 | J68: =IF(B68=0,"",(C68+D68)/B68) -> 1 | K68: =IF(B68=0,"",E68/B68) -> 0
A69: E - Mixed | B69: =COUNTIFS(Customer!$P$5:$P$76,"<>",Customer!$B$5:$B$76,"E - Mixed") -> 20 | C69: =COUNTIFS(Customer!$P$5:$P$76,"Correct",Customer!$B$5:$B$76,"E - Mixed") -> 17 | D69: =COUNTIFS(Customer!$P$5:$P$76,"Safe ask",Customer!$B$5:$B$76,"E - Mixed") -> 2 | E69: =COUNTIFS(Customer!$P$5:$P$76,"Silent wrong",Customer!$B$5:$B$76,"E - Mixed") -> 1 | F69: =COUNTIFS(Customer!$P$5:$P$76,"Missed",Customer!$B$5:$B$76,"E - Mixed") -> 0 | G69: =IF(B69=0,"",C69/B69) -> 0.85 | H69: =IF(B69=0,"",(((C69/B69)+$B$3^2/(2*B69))-($B$3*SQRT((C69/B69)*(1-(C69/B69))/B69+$B$3^2/(4*B69^2))))/(1+$B$3^2/B69)) -> 0.6395767 | I69: =IF(B69=0,"",(((C69/B69)+$B$3^2/(2*B69))+($B$3*SQRT((C69/B69)*(1-(C69/B69))/B69+$B$3^2/(4*B69^2))))/(1+$B$3^2/B69)) -> 0.94763221 | J69: =IF(B69=0,"",(C69+D69)/B69) -> 0.95 | K69: =IF(B69=0,"",E69/B69) -> 0.05
A70: All categories | B70: =COUNTIFS(Customer!$P$5:$P$76,"<>") -> 67 | C70: =COUNTIFS(Customer!$P$5:$P$76,"Correct") -> 64 | D70: =COUNTIFS(Customer!$P$5:$P$76,"Safe ask") -> 2 | E70: =COUNTIFS(Customer!$P$5:$P$76,"Silent wrong") -> 1 | F70: =COUNTIFS(Customer!$P$5:$P$76,"Missed") -> 0 | G70: =IF(B70=0,"",C70/B70) -> 0.95522388 | H70: =IF(B70=0,"",(((C70/B70)+$B$3^2/(2*B70))-($B$3*SQRT((C70/B70)*(1-(C70/B70))/B70+$B$3^2/(4*B70^2))))/(1+$B$3^2/B70)) -> 0.87641967 | I70: =IF(B70=0,"",(((C70/B70)+$B$3^2/(2*B70))+($B$3*SQRT((C70/B70)*(1-(C70/B70))/B70+$B$3^2/(4*B70^2))))/(1+$B$3^2/B70)) -> 0.9846563 | J70: =IF(B70=0,"",(C70+D70)/B70) -> 0.98507463 | K70: =IF(B70=0,"",E70/B70) -> 0.014925373
A73: 6. Supplier — before (baseline), Hinglish
A74: Category | B74: Rows | C74: Correct | D74: Safe ask | E74: Silent wrong | F74: Missed | G74: Strict accuracy | H74: 95% CI low | I74: 95% CI high | J74: Safe rate | K74: Silent-error rate
A75: A - Daily | B75: =COUNTIFS(Supplier!$M$5:$M$91,"<>",Supplier!$B$5:$B$91,"A - Daily") -> 22 | C75: =COUNTIFS(Supplier!$M$5:$M$91,"Correct",Supplier!$B$5:$B$91,"A - Daily") -> 14 | D75: =COUNTIFS(Supplier!$M$5:$M$91,"Safe ask",Supplier!$B$5:$B$91,"A - Daily") -> 0 | E75: =COUNTIFS(Supplier!$M$5:$M$91,"Silent wrong",Supplier!$B$5:$B$91,"A - Daily") -> 2 | F75: =COUNTIFS(Supplier!$M$5:$M$91,"Missed",Supplier!$B$5:$B$91,"A - Daily") -> 6 | G75: =IF(B75=0,"",C75/B75) -> 0.63636364 | H75: =IF(B75=0,"",(((C75/B75)+$B$3^2/(2*B75))-($B$3*SQRT((C75/B75)*(1-(C75/B75))/B75+$B$3^2/(4*B75^2))))/(1+$B$3^2/B75)) -> 0.42951349 | I75: =IF(B75=0,"",(((C75/B75)+$B$3^2/(2*B75))+($B$3*SQRT((C75/B75)*(1-(C75/B75))/B75+$B$3^2/(4*B75^2))))/(1+$B$3^2/B75)) -> 0.80267027 | J75: =IF(B75=0,"",(C75+D75)/B75) -> 0.63636364 | K75: =IF(B75=0,"",E75/B75) -> 0.090909091
A76: B - Tricky | B76: =COUNTIFS(Supplier!$M$5:$M$91,"<>",Supplier!$B$5:$B$91,"B - Tricky") -> 17 | C76: =COUNTIFS(Supplier!$M$5:$M$91,"Correct",Supplier!$B$5:$B$91,"B - Tricky") -> 10 | D76: =COUNTIFS(Supplier!$M$5:$M$91,"Safe ask",Supplier!$B$5:$B$91,"B - Tricky") -> 0 | E76: =COUNTIFS(Supplier!$M$5:$M$91,"Silent wrong",Supplier!$B$5:$B$91,"B - Tricky") -> 3 | F76: =COUNTIFS(Supplier!$M$5:$M$91,"Missed",Supplier!$B$5:$B$91,"B - Tricky") -> 4 | G76: =IF(B76=0,"",C76/B76) -> 0.58823529 | H76: =IF(B76=0,"",(((C76/B76)+$B$3^2/(2*B76))-($B$3*SQRT((C76/B76)*(1-(C76/B76))/B76+$B$3^2/(4*B76^2))))/(1+$B$3^2/B76)) -> 0.36005074 | I76: =IF(B76=0,"",(((C76/B76)+$B$3^2/(2*B76))+($B$3*SQRT((C76/B76)*(1-(C76/B76))/B76+$B$3^2/(4*B76^2))))/(1+$B$3^2/B76)) -> 0.78389214 | J76: =IF(B76=0,"",(C76+D76)/B76) -> 0.58823529 | K76: =IF(B76=0,"",E76/B76) -> 0.17647059
A77: C - Edge | B77: =COUNTIFS(Supplier!$M$5:$M$91,"<>",Supplier!$B$5:$B$91,"C - Edge") -> 11 | C77: =COUNTIFS(Supplier!$M$5:$M$91,"Correct",Supplier!$B$5:$B$91,"C - Edge") -> 4 | D77: =COUNTIFS(Supplier!$M$5:$M$91,"Safe ask",Supplier!$B$5:$B$91,"C - Edge") -> 0 | E77: =COUNTIFS(Supplier!$M$5:$M$91,"Silent wrong",Supplier!$B$5:$B$91,"C - Edge") -> 2 | F77: =COUNTIFS(Supplier!$M$5:$M$91,"Missed",Supplier!$B$5:$B$91,"C - Edge") -> 5 | G77: =IF(B77=0,"",C77/B77) -> 0.36363636 | H77: =IF(B77=0,"",(((C77/B77)+$B$3^2/(2*B77))-($B$3*SQRT((C77/B77)*(1-(C77/B77))/B77+$B$3^2/(4*B77^2))))/(1+$B$3^2/B77)) -> 0.15166224 | I77: =IF(B77=0,"",(((C77/B77)+$B$3^2/(2*B77))+($B$3*SQRT((C77/B77)*(1-(C77/B77))/B77+$B$3^2/(4*B77^2))))/(1+$B$3^2/B77)) -> 0.64620322 | J77: =IF(B77=0,"",(C77+D77)/B77) -> 0.36363636 | K77: =IF(B77=0,"",E77/B77) -> 0.18181818
A78: D - Other business | B78: =COUNTIFS(Supplier!$M$5:$M$91,"<>",Supplier!$B$5:$B$91,"D - Other business") -> 12 | C78: =COUNTIFS(Supplier!$M$5:$M$91,"Correct",Supplier!$B$5:$B$91,"D - Other business") -> 1 | D78: =COUNTIFS(Supplier!$M$5:$M$91,"Safe ask",Supplier!$B$5:$B$91,"D - Other business") -> 2 | E78: =COUNTIFS(Supplier!$M$5:$M$91,"Silent wrong",Supplier!$B$5:$B$91,"D - Other business") -> 3 | F78: =COUNTIFS(Supplier!$M$5:$M$91,"Missed",Supplier!$B$5:$B$91,"D - Other business") -> 6 | G78: =IF(B78=0,"",C78/B78) -> 0.083333333 | H78: =IF(B78=0,"",(((C78/B78)+$B$3^2/(2*B78))-($B$3*SQRT((C78/B78)*(1-(C78/B78))/B78+$B$3^2/(4*B78^2))))/(1+$B$3^2/B78)) -> 0.014864709 | I78: =IF(B78=0,"",(((C78/B78)+$B$3^2/(2*B78))+($B$3*SQRT((C78/B78)*(1-(C78/B78))/B78+$B$3^2/(4*B78^2))))/(1+$B$3^2/B78)) -> 0.35388592 | J78: =IF(B78=0,"",(C78+D78)/B78) -> 0.25 | K78: =IF(B78=0,"",E78/B78) -> 0.25
A79: E - Mixed | B79: =COUNTIFS(Supplier!$M$5:$M$91,"<>",Supplier!$B$5:$B$91,"E - Mixed") -> 24 | C79: =COUNTIFS(Supplier!$M$5:$M$91,"Correct",Supplier!$B$5:$B$91,"E - Mixed") -> 15 | D79: =COUNTIFS(Supplier!$M$5:$M$91,"Safe ask",Supplier!$B$5:$B$91,"E - Mixed") -> 4 | E79: =COUNTIFS(Supplier!$M$5:$M$91,"Silent wrong",Supplier!$B$5:$B$91,"E - Mixed") -> 3 | F79: =COUNTIFS(Supplier!$M$5:$M$91,"Missed",Supplier!$B$5:$B$91,"E - Mixed") -> 2 | G79: =IF(B79=0,"",C79/B79) -> 0.625 | H79: =IF(B79=0,"",(((C79/B79)+$B$3^2/(2*B79))-($B$3*SQRT((C79/B79)*(1-(C79/B79))/B79+$B$3^2/(4*B79^2))))/(1+$B$3^2/B79)) -> 0.42709619 | I79: =IF(B79=0,"",(((C79/B79)+$B$3^2/(2*B79))+($B$3*SQRT((C79/B79)*(1-(C79/B79))/B79+$B$3^2/(4*B79^2))))/(1+$B$3^2/B79)) -> 0.78840867 | J79: =IF(B79=0,"",(C79+D79)/B79) -> 0.79166667 | K79: =IF(B79=0,"",E79/B79) -> 0.125
A80: All categories | B80: =COUNTIFS(Supplier!$M$5:$M$91,"<>") -> 86 | C80: =COUNTIFS(Supplier!$M$5:$M$91,"Correct") -> 44 | D80: =COUNTIFS(Supplier!$M$5:$M$91,"Safe ask") -> 6 | E80: =COUNTIFS(Supplier!$M$5:$M$91,"Silent wrong") -> 13 | F80: =COUNTIFS(Supplier!$M$5:$M$91,"Missed") -> 23 | G80: =IF(B80=0,"",C80/B80) -> 0.51162791 | H80: =IF(B80=0,"",(((C80/B80)+$B$3^2/(2*B80))-($B$3*SQRT((C80/B80)*(1-(C80/B80))/B80+$B$3^2/(4*B80^2))))/(1+$B$3^2/B80)) -> 0.40776537 | I80: =IF(B80=0,"",(((C80/B80)+$B$3^2/(2*B80))+($B$3*SQRT((C80/B80)*(1-(C80/B80))/B80+$B$3^2/(4*B80^2))))/(1+$B$3^2/B80)) -> 0.61449603 | J80: =IF(B80=0,"",(C80+D80)/B80) -> 0.58139535 | K80: =IF(B80=0,"",E80/B80) -> 0.15116279
A83: 7. Supplier — after fixes (full run 6 Oct 15:27), Hinglish
A84: Category | B84: Rows | C84: Correct | D84: Safe ask | E84: Silent wrong | F84: Missed | G84: Strict accuracy | H84: 95% CI low | I84: 95% CI high | J84: Safe rate | K84: Silent-error rate
A85: A - Daily | B85: =COUNTIFS(Supplier!$P$5:$P$91,"<>",Supplier!$B$5:$B$91,"A - Daily") -> 21 | C85: =COUNTIFS(Supplier!$P$5:$P$91,"Correct",Supplier!$B$5:$B$91,"A - Daily") -> 20 | D85: =COUNTIFS(Supplier!$P$5:$P$91,"Safe ask",Supplier!$B$5:$B$91,"A - Daily") -> 0 | E85: =COUNTIFS(Supplier!$P$5:$P$91,"Silent wrong",Supplier!$B$5:$B$91,"A - Daily") -> 1 | F85: =COUNTIFS(Supplier!$P$5:$P$91,"Missed",Supplier!$B$5:$B$91,"A - Daily") -> 0 | G85: =IF(B85=0,"",C85/B85) -> 0.95238095 | H85: =IF(B85=0,"",(((C85/B85)+$B$3^2/(2*B85))-($B$3*SQRT((C85/B85)*(1-(C85/B85))/B85+$B$3^2/(4*B85^2))))/(1+$B$3^2/B85)) -> 0.77330183 | I85: =IF(B85=0,"",(((C85/B85)+$B$3^2/(2*B85))+($B$3*SQRT((C85/B85)*(1-(C85/B85))/B85+$B$3^2/(4*B85^2))))/(1+$B$3^2/B85)) -> 0.99154423 | J85: =IF(B85=0,"",(C85+D85)/B85) -> 0.95238095 | K85: =IF(B85=0,"",E85/B85) -> 0.047619048
A86: B - Tricky | B86: =COUNTIFS(Supplier!$P$5:$P$91,"<>",Supplier!$B$5:$B$91,"B - Tricky") -> 15 | C86: =COUNTIFS(Supplier!$P$5:$P$91,"Correct",Supplier!$B$5:$B$91,"B - Tricky") -> 11 | D86: =COUNTIFS(Supplier!$P$5:$P$91,"Safe ask",Supplier!$B$5:$B$91,"B - Tricky") -> 0 | E86: =COUNTIFS(Supplier!$P$5:$P$91,"Silent wrong",Supplier!$B$5:$B$91,"B - Tricky") -> 3 | F86: =COUNTIFS(Supplier!$P$5:$P$91,"Missed",Supplier!$B$5:$B$91,"B - Tricky") -> 1 | G86: =IF(B86=0,"",C86/B86) -> 0.73333333 | H86: =IF(B86=0,"",(((C86/B86)+$B$3^2/(2*B86))-($B$3*SQRT((C86/B86)*(1-(C86/B86))/B86+$B$3^2/(4*B86^2))))/(1+$B$3^2/B86)) -> 0.4804911 | I86: =IF(B86=0,"",(((C86/B86)+$B$3^2/(2*B86))+($B$3*SQRT((C86/B86)*(1-(C86/B86))/B86+$B$3^2/(4*B86^2))))/(1+$B$3^2/B86)) -> 0.89102724 | J86: =IF(B86=0,"",(C86+D86)/B86) -> 0.73333333 | K86: =IF(B86=0,"",E86/B86) -> 0.2
A87: C - Edge | B87: =COUNTIFS(Supplier!$P$5:$P$91,"<>",Supplier!$B$5:$B$91,"C - Edge") -> 10 | C87: =COUNTIFS(Supplier!$P$5:$P$91,"Correct",Supplier!$B$5:$B$91,"C - Edge") -> 9 | D87: =COUNTIFS(Supplier!$P$5:$P$91,"Safe ask",Supplier!$B$5:$B$91,"C - Edge") -> 1 | E87: =COUNTIFS(Supplier!$P$5:$P$91,"Silent wrong",Supplier!$B$5:$B$91,"C - Edge") -> 0 | F87: =COUNTIFS(Supplier!$P$5:$P$91,"Missed",Supplier!$B$5:$B$91,"C - Edge") -> 0 | G87: =IF(B87=0,"",C87/B87) -> 0.9 | H87: =IF(B87=0,"",(((C87/B87)+$B$3^2/(2*B87))-($B$3*SQRT((C87/B87)*(1-(C87/B87))/B87+$B$3^2/(4*B87^2))))/(1+$B$3^2/B87)) -> 0.59584361 | I87: =IF(B87=0,"",(((C87/B87)+$B$3^2/(2*B87))+($B$3*SQRT((C87/B87)*(1-(C87/B87))/B87+$B$3^2/(4*B87^2))))/(1+$B$3^2/B87)) -> 0.98212425 | J87: =IF(B87=0,"",(C87+D87)/B87) -> 1 | K87: =IF(B87=0,"",E87/B87) -> 0
A88: D - Other business | B88: =COUNTIFS(Supplier!$P$5:$P$91,"<>",Supplier!$B$5:$B$91,"D - Other business") -> 12 | C88: =COUNTIFS(Supplier!$P$5:$P$91,"Correct",Supplier!$B$5:$B$91,"D - Other business") -> 10 | D88: =COUNTIFS(Supplier!$P$5:$P$91,"Safe ask",Supplier!$B$5:$B$91,"D - Other business") -> 0 | E88: =COUNTIFS(Supplier!$P$5:$P$91,"Silent wrong",Supplier!$B$5:$B$91,"D - Other business") -> 2 | F88: =COUNTIFS(Supplier!$P$5:$P$91,"Missed",Supplier!$B$5:$B$91,"D - Other business") -> 0 | G88: =IF(B88=0,"",C88/B88) -> 0.83333333 | H88: =IF(B88=0,"",(((C88/B88)+$B$3^2/(2*B88))-($B$3*SQRT((C88/B88)*(1-(C88/B88))/B88+$B$3^2/(4*B88^2))))/(1+$B$3^2/B88)) -> 0.55196364 | I88: =IF(B88=0,"",(((C88/B88)+$B$3^2/(2*B88))+($B$3*SQRT((C88/B88)*(1-(C88/B88))/B88+$B$3^2/(4*B88^2))))/(1+$B$3^2/B88)) -> 0.95303585 | J88: =IF(B88=0,"",(C88+D88)/B88) -> 0.83333333 | K88: =IF(B88=0,"",E88/B88) -> 0.16666667
A89: E - Mixed | B89: =COUNTIFS(Supplier!$P$5:$P$91,"<>",Supplier!$B$5:$B$91,"E - Mixed") -> 24 | C89: =COUNTIFS(Supplier!$P$5:$P$91,"Correct",Supplier!$B$5:$B$91,"E - Mixed") -> 20 | D89: =COUNTIFS(Supplier!$P$5:$P$91,"Safe ask",Supplier!$B$5:$B$91,"E - Mixed") -> 2 | E89: =COUNTIFS(Supplier!$P$5:$P$91,"Silent wrong",Supplier!$B$5:$B$91,"E - Mixed") -> 1 | F89: =COUNTIFS(Supplier!$P$5:$P$91,"Missed",Supplier!$B$5:$B$91,"E - Mixed") -> 1 | G89: =IF(B89=0,"",C89/B89) -> 0.83333333 | H89: =IF(B89=0,"",(((C89/B89)+$B$3^2/(2*B89))-($B$3*SQRT((C89/B89)*(1-(C89/B89))/B89+$B$3^2/(4*B89^2))))/(1+$B$3^2/B89)) -> 0.6414653 | I89: =IF(B89=0,"",(((C89/B89)+$B$3^2/(2*B89))+($B$3*SQRT((C89/B89)*(1-(C89/B89))/B89+$B$3^2/(4*B89^2))))/(1+$B$3^2/B89)) -> 0.93321432 | J89: =IF(B89=0,"",(C89+D89)/B89) -> 0.91666667 | K89: =IF(B89=0,"",E89/B89) -> 0.041666667
A90: All categories | B90: =COUNTIFS(Supplier!$P$5:$P$91,"<>") -> 82 | C90: =COUNTIFS(Supplier!$P$5:$P$91,"Correct") -> 70 | D90: =COUNTIFS(Supplier!$P$5:$P$91,"Safe ask") -> 3 | E90: =COUNTIFS(Supplier!$P$5:$P$91,"Silent wrong") -> 7 | F90: =COUNTIFS(Supplier!$P$5:$P$91,"Missed") -> 2 | G90: =IF(B90=0,"",C90/B90) -> 0.85365854 | H90: =IF(B90=0,"",(((C90/B90)+$B$3^2/(2*B90))-($B$3*SQRT((C90/B90)*(1-(C90/B90))/B90+$B$3^2/(4*B90^2))))/(1+$B$3^2/B90)) -> 0.76140386 | I90: =IF(B90=0,"",(((C90/B90)+$B$3^2/(2*B90))+($B$3*SQRT((C90/B90)*(1-(C90/B90))/B90+$B$3^2/(4*B90^2))))/(1+$B$3^2/B90)) -> 0.91425922 | J90: =IF(B90=0,"",(C90+D90)/B90) -> 0.8902439 | K90: =IF(B90=0,"",E90/B90) -> 0.085365854
A93: 8. Expense — before (baseline), Hinglish
A94: Category | B94: Rows | C94: Correct | D94: Safe ask | E94: Silent wrong | F94: Missed | G94: Strict accuracy | H94: 95% CI low | I94: 95% CI high | J94: Safe rate | K94: Silent-error rate
A95: A - Daily | B95: =COUNTIFS(Expense!$M$5:$M$113,"<>",Expense!$B$5:$B$113,"A - Daily") -> 20 | C95: =COUNTIFS(Expense!$M$5:$M$113,"Correct",Expense!$B$5:$B$113,"A - Daily") -> 11 | D95: =COUNTIFS(Expense!$M$5:$M$113,"Safe ask",Expense!$B$5:$B$113,"A - Daily") -> 0 | E95: =COUNTIFS(Expense!$M$5:$M$113,"Silent wrong",Expense!$B$5:$B$113,"A - Daily") -> 1 | F95: =COUNTIFS(Expense!$M$5:$M$113,"Missed",Expense!$B$5:$B$113,"A - Daily") -> 8 | G95: =IF(B95=0,"",C95/B95) -> 0.55 | H95: =IF(B95=0,"",(((C95/B95)+$B$3^2/(2*B95))-($B$3*SQRT((C95/B95)*(1-(C95/B95))/B95+$B$3^2/(4*B95^2))))/(1+$B$3^2/B95)) -> 0.34208201 | I95: =IF(B95=0,"",(((C95/B95)+$B$3^2/(2*B95))+($B$3*SQRT((C95/B95)*(1-(C95/B95))/B95+$B$3^2/(4*B95^2))))/(1+$B$3^2/B95)) -> 0.74180498 | J95: =IF(B95=0,"",(C95+D95)/B95) -> 0.55 | K95: =IF(B95=0,"",E95/B95) -> 0.05
A96: B - Tricky | B96: =COUNTIFS(Expense!$M$5:$M$113,"<>",Expense!$B$5:$B$113,"B - Tricky") -> 21 | C96: =COUNTIFS(Expense!$M$5:$M$113,"Correct",Expense!$B$5:$B$113,"B - Tricky") -> 6 | D96: =COUNTIFS(Expense!$M$5:$M$113,"Safe ask",Expense!$B$5:$B$113,"B - Tricky") -> 2 | E96: =COUNTIFS(Expense!$M$5:$M$113,"Silent wrong",Expense!$B$5:$B$113,"B - Tricky") -> 4 | F96: =COUNTIFS(Expense!$M$5:$M$113,"Missed",Expense!$B$5:$B$113,"B - Tricky") -> 9 | G96: =IF(B96=0,"",C96/B96) -> 0.28571429 | H96: =IF(B96=0,"",(((C96/B96)+$B$3^2/(2*B96))-($B$3*SQRT((C96/B96)*(1-(C96/B96))/B96+$B$3^2/(4*B96^2))))/(1+$B$3^2/B96)) -> 0.13813676 | I96: =IF(B96=0,"",(((C96/B96)+$B$3^2/(2*B96))+($B$3*SQRT((C96/B96)*(1-(C96/B96))/B96+$B$3^2/(4*B96^2))))/(1+$B$3^2/B96)) -> 0.49956774 | J96: =IF(B96=0,"",(C96+D96)/B96) -> 0.38095238 | K96: =IF(B96=0,"",E96/B96) -> 0.19047619
A97: C - Edge | B97: =COUNTIFS(Expense!$M$5:$M$113,"<>",Expense!$B$5:$B$113,"C - Edge") -> 14 | C97: =COUNTIFS(Expense!$M$5:$M$113,"Correct",Expense!$B$5:$B$113,"C - Edge") -> 6 | D97: =COUNTIFS(Expense!$M$5:$M$113,"Safe ask",Expense!$B$5:$B$113,"C - Edge") -> 0 | E97: =COUNTIFS(Expense!$M$5:$M$113,"Silent wrong",Expense!$B$5:$B$113,"C - Edge") -> 4 | F97: =COUNTIFS(Expense!$M$5:$M$113,"Missed",Expense!$B$5:$B$113,"C - Edge") -> 4 | G97: =IF(B97=0,"",C97/B97) -> 0.42857143 | H97: =IF(B97=0,"",(((C97/B97)+$B$3^2/(2*B97))-($B$3*SQRT((C97/B97)*(1-(C97/B97))/B97+$B$3^2/(4*B97^2))))/(1+$B$3^2/B97)) -> 0.2138051 | I97: =IF(B97=0,"",(((C97/B97)+$B$3^2/(2*B97))+($B$3*SQRT((C97/B97)*(1-(C97/B97))/B97+$B$3^2/(4*B97^2))))/(1+$B$3^2/B97)) -> 0.67409733 | J97: =IF(B97=0,"",(C97+D97)/B97) -> 0.42857143 | K97: =IF(B97=0,"",E97/B97) -> 0.28571429
A98: D - Other business | B98: =COUNTIFS(Expense!$M$5:$M$113,"<>",Expense!$B$5:$B$113,"D - Other business") -> 21 | C98: =COUNTIFS(Expense!$M$5:$M$113,"Correct",Expense!$B$5:$B$113,"D - Other business") -> 9 | D98: =COUNTIFS(Expense!$M$5:$M$113,"Safe ask",Expense!$B$5:$B$113,"D - Other business") -> 4 | E98: =COUNTIFS(Expense!$M$5:$M$113,"Silent wrong",Expense!$B$5:$B$113,"D - Other business") -> 1 | F98: =COUNTIFS(Expense!$M$5:$M$113,"Missed",Expense!$B$5:$B$113,"D - Other business") -> 7 | G98: =IF(B98=0,"",C98/B98) -> 0.42857143 | H98: =IF(B98=0,"",(((C98/B98)+$B$3^2/(2*B98))-($B$3*SQRT((C98/B98)*(1-(C98/B98))/B98+$B$3^2/(4*B98^2))))/(1+$B$3^2/B98)) -> 0.24469699 | I98: =IF(B98=0,"",(((C98/B98)+$B$3^2/(2*B98))+($B$3*SQRT((C98/B98)*(1-(C98/B98))/B98+$B$3^2/(4*B98^2))))/(1+$B$3^2/B98)) -> 0.63453784 | J98: =IF(B98=0,"",(C98+D98)/B98) -> 0.61904762 | K98: =IF(B98=0,"",E98/B98) -> 0.047619048
A99: E - Mixed | B99: =COUNTIFS(Expense!$M$5:$M$113,"<>",Expense!$B$5:$B$113,"E - Mixed") -> 33 | C99: =COUNTIFS(Expense!$M$5:$M$113,"Correct",Expense!$B$5:$B$113,"E - Mixed") -> 20 | D99: =COUNTIFS(Expense!$M$5:$M$113,"Safe ask",Expense!$B$5:$B$113,"E - Mixed") -> 3 | E99: =COUNTIFS(Expense!$M$5:$M$113,"Silent wrong",Expense!$B$5:$B$113,"E - Mixed") -> 1 | F99: =COUNTIFS(Expense!$M$5:$M$113,"Missed",Expense!$B$5:$B$113,"E - Mixed") -> 9 | G99: =IF(B99=0,"",C99/B99) -> 0.60606061 | H99: =IF(B99=0,"",(((C99/B99)+$B$3^2/(2*B99))-($B$3*SQRT((C99/B99)*(1-(C99/B99))/B99+$B$3^2/(4*B99^2))))/(1+$B$3^2/B99)) -> 0.43683143 | I99: =IF(B99=0,"",(((C99/B99)+$B$3^2/(2*B99))+($B$3*SQRT((C99/B99)*(1-(C99/B99))/B99+$B$3^2/(4*B99^2))))/(1+$B$3^2/B99)) -> 0.75317118 | J99: =IF(B99=0,"",(C99+D99)/B99) -> 0.6969697 | K99: =IF(B99=0,"",E99/B99) -> 0.03030303
A100: All categories | B100: =COUNTIFS(Expense!$M$5:$M$113,"<>") -> 109 | C100: =COUNTIFS(Expense!$M$5:$M$113,"Correct") -> 52 | D100: =COUNTIFS(Expense!$M$5:$M$113,"Safe ask") -> 9 | E100: =COUNTIFS(Expense!$M$5:$M$113,"Silent wrong") -> 11 | F100: =COUNTIFS(Expense!$M$5:$M$113,"Missed") -> 37 | G100: =IF(B100=0,"",C100/B100) -> 0.47706422 | H100: =IF(B100=0,"",(((C100/B100)+$B$3^2/(2*B100))-($B$3*SQRT((C100/B100)*(1-(C100/B100))/B100+$B$3^2/(4*B100^2))))/(1+$B$3^2/B100)) -> 0.38568353 | I100: =IF(B100=0,"",(((C100/B100)+$B$3^2/(2*B100))+($B$3*SQRT((C100/B100)*(1-(C100/B100))/B100+$B$3^2/(4*B100^2))))/(1+$B$3^2/B100)) -> 0.57000657 | J100: =IF(B100=0,"",(C100+D100)/B100) -> 0.55963303 | K100: =IF(B100=0,"",E100/B100) -> 0.10091743
A103: 9. Expense — after fixes (full run 6 Oct 17:42), Hinglish
A104: Category | B104: Rows | C104: Correct | D104: Safe ask | E104: Silent wrong | F104: Missed | G104: Strict accuracy | H104: 95% CI low | I104: 95% CI high | J104: Safe rate | K104: Silent-error rate
A105: A - Daily | B105: =COUNTIFS(Expense!$P$5:$P$113,"<>",Expense!$B$5:$B$113,"A - Daily") -> 20 | C105: =COUNTIFS(Expense!$P$5:$P$113,"Correct",Expense!$B$5:$B$113,"A - Daily") -> 18 | D105: =COUNTIFS(Expense!$P$5:$P$113,"Safe ask",Expense!$B$5:$B$113,"A - Daily") -> 2 | E105: =COUNTIFS(Expense!$P$5:$P$113,"Silent wrong",Expense!$B$5:$B$113,"A - Daily") -> 0 | F105: =COUNTIFS(Expense!$P$5:$P$113,"Missed",Expense!$B$5:$B$113,"A - Daily") -> 0 | G105: =IF(B105=0,"",C105/B105) -> 0.9 | H105: =IF(B105=0,"",(((C105/B105)+$B$3^2/(2*B105))-($B$3*SQRT((C105/B105)*(1-(C105/B105))/B105+$B$3^2/(4*B105^2))))/(1+$B$3^2/B105)) -> 0.69896179 | I105: =IF(B105=0,"",(((C105/B105)+$B$3^2/(2*B105))+($B$3*SQRT((C105/B105)*(1-(C105/B105))/B105+$B$3^2/(4*B105^2))))/(1+$B$3^2/B105)) -> 0.97213411 | J105: =IF(B105=0,"",(C105+D105)/B105) -> 1 | K105: =IF(B105=0,"",E105/B105) -> 0
A106: B - Tricky | B106: =COUNTIFS(Expense!$P$5:$P$113,"<>",Expense!$B$5:$B$113,"B - Tricky") -> 20 | C106: =COUNTIFS(Expense!$P$5:$P$113,"Correct",Expense!$B$5:$B$113,"B - Tricky") -> 20 | D106: =COUNTIFS(Expense!$P$5:$P$113,"Safe ask",Expense!$B$5:$B$113,"B - Tricky") -> 0 | E106: =COUNTIFS(Expense!$P$5:$P$113,"Silent wrong",Expense!$B$5:$B$113,"B - Tricky") -> 0 | F106: =COUNTIFS(Expense!$P$5:$P$113,"Missed",Expense!$B$5:$B$113,"B - Tricky") -> 0 | G106: =IF(B106=0,"",C106/B106) -> 1 | H106: =IF(B106=0,"",(((C106/B106)+$B$3^2/(2*B106))-($B$3*SQRT((C106/B106)*(1-(C106/B106))/B106+$B$3^2/(4*B106^2))))/(1+$B$3^2/B106)) -> 0.83886987 | I106: =IF(B106=0,"",(((C106/B106)+$B$3^2/(2*B106))+($B$3*SQRT((C106/B106)*(1-(C106/B106))/B106+$B$3^2/(4*B106^2))))/(1+$B$3^2/B106)) -> 1 | J106: =IF(B106=0,"",(C106+D106)/B106) -> 1 | K106: =IF(B106=0,"",E106/B106) -> 0
A107: C - Edge | B107: =COUNTIFS(Expense!$P$5:$P$113,"<>",Expense!$B$5:$B$113,"C - Edge") -> 12 | C107: =COUNTIFS(Expense!$P$5:$P$113,"Correct",Expense!$B$5:$B$113,"C - Edge") -> 10 | D107: =COUNTIFS(Expense!$P$5:$P$113,"Safe ask",Expense!$B$5:$B$113,"C - Edge") -> 1 | E107: =COUNTIFS(Expense!$P$5:$P$113,"Silent wrong",Expense!$B$5:$B$113,"C - Edge") -> 0 | F107: =COUNTIFS(Expense!$P$5:$P$113,"Missed",Expense!$B$5:$B$113,"C - Edge") -> 1 | G107: =IF(B107=0,"",C107/B107) -> 0.83333333 | H107: =IF(B107=0,"",(((C107/B107)+$B$3^2/(2*B107))-($B$3*SQRT((C107/B107)*(1-(C107/B107))/B107+$B$3^2/(4*B107^2))))/(1+$B$3^2/B107)) -> 0.55196364 | I107: =IF(B107=0,"",(((C107/B107)+$B$3^2/(2*B107))+($B$3*SQRT((C107/B107)*(1-(C107/B107))/B107+$B$3^2/(4*B107^2))))/(1+$B$3^2/B107)) -> 0.95303585 | J107: =IF(B107=0,"",(C107+D107)/B107) -> 0.91666667 | K107: =IF(B107=0,"",E107/B107) -> 0
A108: D - Other business | B108: =COUNTIFS(Expense!$P$5:$P$113,"<>",Expense!$B$5:$B$113,"D - Other business") -> 20 | C108: =COUNTIFS(Expense!$P$5:$P$113,"Correct",Expense!$B$5:$B$113,"D - Other business") -> 20 | D108: =COUNTIFS(Expense!$P$5:$P$113,"Safe ask",Expense!$B$5:$B$113,"D - Other business") -> 0 | E108: =COUNTIFS(Expense!$P$5:$P$113,"Silent wrong",Expense!$B$5:$B$113,"D - Other business") -> 0 | F108: =COUNTIFS(Expense!$P$5:$P$113,"Missed",Expense!$B$5:$B$113,"D - Other business") -> 0 | G108: =IF(B108=0,"",C108/B108) -> 1 | H108: =IF(B108=0,"",(((C108/B108)+$B$3^2/(2*B108))-($B$3*SQRT((C108/B108)*(1-(C108/B108))/B108+$B$3^2/(4*B108^2))))/(1+$B$3^2/B108)) -> 0.83886987 | I108: =IF(B108=0,"",(((C108/B108)+$B$3^2/(2*B108))+($B$3*SQRT((C108/B108)*(1-(C108/B108))/B108+$B$3^2/(4*B108^2))))/(1+$B$3^2/B108)) -> 1 | J108: =IF(B108=0,"",(C108+D108)/B108) -> 1 | K108: =IF(B108=0,"",E108/B108) -> 0
A109: E - Mixed | B109: =COUNTIFS(Expense!$P$5:$P$113,"<>",Expense!$B$5:$B$113,"E - Mixed") -> 33 | C109: =COUNTIFS(Expense!$P$5:$P$113,"Correct",Expense!$B$5:$B$113,"E - Mixed") -> 33 | D109: =COUNTIFS(Expense!$P$5:$P$113,"Safe ask",Expense!$B$5:$B$113,"E - Mixed") -> 0 | E109: =COUNTIFS(Expense!$P$5:$P$113,"Silent wrong",Expense!$B$5:$B$113,"E - Mixed") -> 0 | F109: =COUNTIFS(Expense!$P$5:$P$113,"Missed",Expense!$B$5:$B$113,"E - Mixed") -> 0 | G109: =IF(B109=0,"",C109/B109) -> 1 | H109: =IF(B109=0,"",(((C109/B109)+$B$3^2/(2*B109))-($B$3*SQRT((C109/B109)*(1-(C109/B109))/B109+$B$3^2/(4*B109^2))))/(1+$B$3^2/B109)) -> 0.89572657 | I109: =IF(B109=0,"",(((C109/B109)+$B$3^2/(2*B109))+($B$3*SQRT((C109/B109)*(1-(C109/B109))/B109+$B$3^2/(4*B109^2))))/(1+$B$3^2/B109)) -> 1 | J109: =IF(B109=0,"",(C109+D109)/B109) -> 1 | K109: =IF(B109=0,"",E109/B109) -> 0
A110: All categories | B110: =COUNTIFS(Expense!$P$5:$P$113,"<>") -> 105 | C110: =COUNTIFS(Expense!$P$5:$P$113,"Correct") -> 101 | D110: =COUNTIFS(Expense!$P$5:$P$113,"Safe ask") -> 3 | E110: =COUNTIFS(Expense!$P$5:$P$113,"Silent wrong") -> 0 | F110: =COUNTIFS(Expense!$P$5:$P$113,"Missed") -> 1 | G110: =IF(B110=0,"",C110/B110) -> 0.96190476 | H110: =IF(B110=0,"",(((C110/B110)+$B$3^2/(2*B110))-($B$3*SQRT((C110/B110)*(1-(C110/B110))/B110+$B$3^2/(4*B110^2))))/(1+$B$3^2/B110)) -> 0.90611558 | I110: =IF(B110=0,"",(((C110/B110)+$B$3^2/(2*B110))+($B$3*SQRT((C110/B110)*(1-(C110/B110))/B110+$B$3^2/(4*B110^2))))/(1+$B$3^2/B110)) -> 0.98508778 | J110: =IF(B110=0,"",(C110+D110)/B110) -> 0.99047619 | K110: =IF(B110=0,"",E110/B110) -> 0
A113: 10. Family — before (baseline), Hinglish
A114: Category | B114: Rows | C114: Correct | D114: Safe ask | E114: Silent wrong | F114: Missed | G114: Strict accuracy | H114: 95% CI low | I114: 95% CI high | J114: Safe rate | K114: Silent-error rate
A115: A - Daily | B115: =COUNTIFS(Family!$M$5:$M$80,"<>",Family!$B$5:$B$80,"A - Daily") -> 10 | C115: =COUNTIFS(Family!$M$5:$M$80,"Correct",Family!$B$5:$B$80,"A - Daily") -> 4 | D115: =COUNTIFS(Family!$M$5:$M$80,"Safe ask",Family!$B$5:$B$80,"A - Daily") -> 1 | E115: =COUNTIFS(Family!$M$5:$M$80,"Silent wrong",Family!$B$5:$B$80,"A - Daily") -> 1 | F115: =COUNTIFS(Family!$M$5:$M$80,"Missed",Family!$B$5:$B$80,"A - Daily") -> 4 | G115: =IF(B115=0,"",C115/B115) -> 0.4 | H115: =IF(B115=0,"",(((C115/B115)+$B$3^2/(2*B115))-($B$3*SQRT((C115/B115)*(1-(C115/B115))/B115+$B$3^2/(4*B115^2))))/(1+$B$3^2/B115)) -> 0.16817758 | I115: =IF(B115=0,"",(((C115/B115)+$B$3^2/(2*B115))+($B$3*SQRT((C115/B115)*(1-(C115/B115))/B115+$B$3^2/(4*B115^2))))/(1+$B$3^2/B115)) -> 0.68733045 | J115: =IF(B115=0,"",(C115+D115)/B115) -> 0.5 | K115: =IF(B115=0,"",E115/B115) -> 0.1
A116: B - Tricky | B116: =COUNTIFS(Family!$M$5:$M$80,"<>",Family!$B$5:$B$80,"B - Tricky") -> 15 | C116: =COUNTIFS(Family!$M$5:$M$80,"Correct",Family!$B$5:$B$80,"B - Tricky") -> 3 | D116: =COUNTIFS(Family!$M$5:$M$80,"Safe ask",Family!$B$5:$B$80,"B - Tricky") -> 6 | E116: =COUNTIFS(Family!$M$5:$M$80,"Silent wrong",Family!$B$5:$B$80,"B - Tricky") -> 4 | F116: =COUNTIFS(Family!$M$5:$M$80,"Missed",Family!$B$5:$B$80,"B - Tricky") -> 2 | G116: =IF(B116=0,"",C116/B116) -> 0.2 | H116: =IF(B116=0,"",(((C116/B116)+$B$3^2/(2*B116))-($B$3*SQRT((C116/B116)*(1-(C116/B116))/B116+$B$3^2/(4*B116^2))))/(1+$B$3^2/B116)) -> 0.070474206 | I116: =IF(B116=0,"",(((C116/B116)+$B$3^2/(2*B116))+($B$3*SQRT((C116/B116)*(1-(C116/B116))/B116+$B$3^2/(4*B116^2))))/(1+$B$3^2/B116)) -> 0.45185935 | J116: =IF(B116=0,"",(C116+D116)/B116) -> 0.6 | K116: =IF(B116=0,"",E116/B116) -> 0.26666667
A117: C - Edge | B117: =COUNTIFS(Family!$M$5:$M$80,"<>",Family!$B$5:$B$80,"C - Edge") -> 11 | C117: =COUNTIFS(Family!$M$5:$M$80,"Correct",Family!$B$5:$B$80,"C - Edge") -> 9 | D117: =COUNTIFS(Family!$M$5:$M$80,"Safe ask",Family!$B$5:$B$80,"C - Edge") -> 0 | E117: =COUNTIFS(Family!$M$5:$M$80,"Silent wrong",Family!$B$5:$B$80,"C - Edge") -> 1 | F117: =COUNTIFS(Family!$M$5:$M$80,"Missed",Family!$B$5:$B$80,"C - Edge") -> 1 | G117: =IF(B117=0,"",C117/B117) -> 0.81818182 | H117: =IF(B117=0,"",(((C117/B117)+$B$3^2/(2*B117))-($B$3*SQRT((C117/B117)*(1-(C117/B117))/B117+$B$3^2/(4*B117^2))))/(1+$B$3^2/B117)) -> 0.52301386 | I117: =IF(B117=0,"",(((C117/B117)+$B$3^2/(2*B117))+($B$3*SQRT((C117/B117)*(1-(C117/B117))/B117+$B$3^2/(4*B117^2))))/(1+$B$3^2/B117)) -> 0.9486334 | J117: =IF(B117=0,"",(C117+D117)/B117) -> 0.81818182 | K117: =IF(B117=0,"",E117/B117) -> 0.090909091
A118: D - Other business | B118: =COUNTIFS(Family!$M$5:$M$80,"<>",Family!$B$5:$B$80,"D - Other business") -> 14 | C118: =COUNTIFS(Family!$M$5:$M$80,"Correct",Family!$B$5:$B$80,"D - Other business") -> 5 | D118: =COUNTIFS(Family!$M$5:$M$80,"Safe ask",Family!$B$5:$B$80,"D - Other business") -> 1 | E118: =COUNTIFS(Family!$M$5:$M$80,"Silent wrong",Family!$B$5:$B$80,"D - Other business") -> 3 | F118: =COUNTIFS(Family!$M$5:$M$80,"Missed",Family!$B$5:$B$80,"D - Other business") -> 5 | G118: =IF(B118=0,"",C118/B118) -> 0.35714286 | H118: =IF(B118=0,"",(((C118/B118)+$B$3^2/(2*B118))-($B$3*SQRT((C118/B118)*(1-(C118/B118))/B118+$B$3^2/(4*B118^2))))/(1+$B$3^2/B118)) -> 0.16344491 | I118: =IF(B118=0,"",(((C118/B118)+$B$3^2/(2*B118))+($B$3*SQRT((C118/B118)*(1-(C118/B118))/B118+$B$3^2/(4*B118^2))))/(1+$B$3^2/B118)) -> 0.61235995 | J118: =IF(B118=0,"",(C118+D118)/B118) -> 0.42857143 | K118: =IF(B118=0,"",E118/B118) -> 0.21428571
...

Sheet Holdout Summary
A1: Final evaluation on unseen data (holdout) — round 1 vs round 2 (final)
A2: Numbers are live formulas over the two holdout sheets (Wilson 95% interval, z from Summary!B3). 'Tests fully right' = every expected entry of the statement correct (counted from the run files).
A4: 1. Holdout round 2 — FINAL (run 2026-10-08 16:51, no fixes after it)
A5: Bundle | B5: Rows | C5: Correct | D5: Safe ask | E5: Silent wrong | F5: Missed | G5: Strict accuracy | H5: 95% CI low | I5: 95% CI high | J5: Safe rate | K5: Silent-error rate | L5: Tests fully right
A6: Employee | B6: =COUNTIFS('Holdout R2 (final)'!$I$5:$I$170,"<>",'Holdout R2 (final)'!$B$5:$B$170,"Employee") -> 18 | C6: =COUNTIFS('Holdout R2 (final)'!$I$5:$I$170,"Correct",'Holdout R2 (final)'!$B$5:$B$170,"Employee") -> 16 | D6: =COUNTIFS('Holdout R2 (final)'!$I$5:$I$170,"Safe ask",'Holdout R2 (final)'!$B$5:$B$170,"Employee") -> 0 | E6: =COUNTIFS('Holdout R2 (final)'!$I$5:$I$170,"Silent wrong",'Holdout R2 (final)'!$B$5:$B$170,"Employee") -> 0 | F6: =COUNTIFS('Holdout R2 (final)'!$I$5:$I$170,"Missed",'Holdout R2 (final)'!$B$5:$B$170,"Employee") -> 2 | G6: =IF(B6=0,"",C6/B6) -> 0.88888889 | H6: =IF(B6=0,"",(((C6/B6)+Summary!$B$3^2/(2*B6))-(Summary!$B$3*SQRT((C6/B6)*(1-(C6/B6))/B6+Summary!$B$3^2/(4*B6^2))))/(1+Summary!$B$3^2/B6)) -> 0.67199755 | I6: =IF(B6=0,"",(((C6/B6)+Summary!$B$3^2/(2*B6))+(Summary!$B$3*SQRT((C6/B6)*(1-(C6/B6))/B6+Summary!$B$3^2/(4*B6^2))))/(1+Summary!$B$3^2/B6)) -> 0.96898113 | J6: =IF(B6=0,"",(C6+D6)/B6) -> 0.88888889 | K6: =IF(B6=0,"",E6/B6) -> 0 | L6: 13/15
A7: Customer | B7: =COUNTIFS('Holdout R2 (final)'!$I$5:$I$170,"<>",'Holdout R2 (final)'!$B$5:$B$170,"Customer") -> 18 | C7: =COUNTIFS('Holdout R2 (final)'!$I$5:$I$170,"Correct",'Holdout R2 (final)'!$B$5:$B$170,"Customer") -> 11 | D7: =COUNTIFS('Holdout R2 (final)'!$I$5:$I$170,"Safe ask",'Holdout R2 (final)'!$B$5:$B$170,"Customer") -> 1 | E7: =COUNTIFS('Holdout R2 (final)'!$I$5:$I$170,"Silent wrong",'Holdout R2 (final)'!$B$5:$B$170,"Customer") -> 2 | F7: =COUNTIFS('Holdout R2 (final)'!$I$5:$I$170,"Missed",'Holdout R2 (final)'!$B$5:$B$170,"Customer") -> 4 | G7: =IF(B7=0,"",C7/B7) -> 0.61111111 | H7: =IF(B7=0,"",(((C7/B7)+Summary!$B$3^2/(2*B7))-(Summary!$B$3*SQRT((C7/B7)*(1-(C7/B7))/B7+Summary!$B$3^2/(4*B7^2))))/(1+Summary!$B$3^2/B7)) -> 0.38618669 | I7: =IF(B7=0,"",(((C7/B7)+Summary!$B$3^2/(2*B7))+(Summary!$B$3*SQRT((C7/B7)*(1-(C7/B7))/B7+Summary!$B$3^2/(4*B7^2))))/(1+Summary!$B$3^2/B7)) -> 0.79695008 | J7: =IF(B7=0,"",(C7+D7)/B7) -> 0.66666667 | K7: =IF(B7=0,"",E7/B7) -> 0.11111111 | L7: 8/15
A8: Supplier | B8: =COUNTIFS('Holdout R2 (final)'!$I$5:$I$170,"<>",'Holdout R2 (final)'!$B$5:$B$170,"Supplier") -> 16 | C8: =COUNTIFS('Holdout R2 (final)'!$I$5:$I$170,"Correct",'Holdout R2 (final)'!$B$5:$B$170,"Supplier") -> 15 | D8: =COUNTIFS('Holdout R2 (final)'!$I$5:$I$170,"Safe ask",'Holdout R2 (final)'!$B$5:$B$170,"Supplier") -> 0 | E8: =COUNTIFS('Holdout R2 (final)'!$I$5:$I$170,"Silent wrong",'Holdout R2 (final)'!$B$5:$B$170,"Supplier") -> 1 | F8: =COUNTIFS('Holdout R2 (final)'!$I$5:$I$170,"Missed",'Holdout R2 (final)'!$B$5:$B$170,"Supplier") -> 0 | G8: =IF(B8=0,"",C8/B8) -> 0.9375 | H8: =IF(B8=0,"",(((C8/B8)+Summary!$B$3^2/(2*B8))-(Summary!$B$3*SQRT((C8/B8)*(1-(C8/B8))/B8+Summary!$B$3^2/(4*B8^2))))/(1+Summary!$B$3^2/B8)) -> 0.71670732 | I8: =IF(B8=0,"",(((C8/B8)+Summary!$B$3^2/(2*B8))+(Summary!$B$3*SQRT((C8/B8)*(1-(C8/B8))/B8+Summary!$B$3^2/(4*B8^2))))/(1+Summary!$B$3^2/B8)) -> 0.98888094 | J8: =IF(B8=0,"",(C8+D8)/B8) -> 0.9375 | K8: =IF(B8=0,"",E8/B8) -> 0.0625 | L8: 14/15
A9: Expense | B9: =COUNTIFS('Holdout R2 (final)'!$I$5:$I$170,"<>",'Holdout R2 (final)'!$B$5:$B$170,"Expense") -> 31 | C9: =COUNTIFS('Holdout R2 (final)'!$I$5:$I$170,"Correct",'Holdout R2 (final)'!$B$5:$B$170,"Expense") -> 24 | D9: =COUNTIFS('Holdout R2 (final)'!$I$5:$I$170,"Safe ask",'Holdout R2 (final)'!$B$5:$B$170,"Expense") -> 2 | E9: =COUNTIFS('Holdout R2 (final)'!$I$5:$I$170,"Silent wrong",'Holdout R2 (final)'!$B$5:$B$170,"Expense") -> 1 | F9: =COUNTIFS('Holdout R2 (final)'!$I$5:$I$170,"Missed",'Holdout R2 (final)'!$B$5:$B$170,"Expense") -> 4 | G9: =IF(B9=0,"",C9/B9) -> 0.77419355 | H9: =IF(B9=0,"",(((C9/B9)+Summary!$B$3^2/(2*B9))-(Summary!$B$3*SQRT((C9/B9)*(1-(C9/B9))/B9+Summary!$B$3^2/(4*B9^2))))/(1+Summary!$B$3^2/B9)) -> 0.6018724 | I9: =IF(B9=0,"",(((C9/B9)+Summary!$B$3^2/(2*B9))+(Summary!$B$3*SQRT((C9/B9)*(1-(C9/B9))/B9+Summary!$B$3^2/(4*B9^2))))/(1+Summary!$B$3^2/B9)) -> 0.88605008 | J9: =IF(B9=0,"",(C9+D9)/B9) -> 0.83870968 | K9: =IF(B9=0,"",E9/B9) -> 0.032258065 | L9: 12/15
A10: Family | B10: =COUNTIFS('Holdout R2 (final)'!$I$5:$I$170,"<>",'Holdout R2 (final)'!$B$5:$B$170,"Family") -> 17 | C10: =COUNTIFS('Holdout R2 (final)'!$I$5:$I$170,"Correct",'Holdout R2 (final)'!$B$5:$B$170,"Family") -> 11 | D10: =COUNTIFS('Holdout R2 (final)'!$I$5:$I$170,"Safe ask",'Holdout R2 (final)'!$B$5:$B$170,"Family") -> 1 | E10: =COUNTIFS('Holdout R2 (final)'!$I$5:$I$170,"Silent wrong",'Holdout R2 (final)'!$B$5:$B$170,"Family") -> 2 | F10: =COUNTIFS('Holdout R2 (final)'!$I$5:$I$170,"Missed",'Holdout R2 (final)'!$B$5:$B$170,"Family") -> 3 | G10: =IF(B10=0,"",C10/B10) -> 0.64705882 | H10: =IF(B10=0,"",(((C10/B10)+Summary!$B$3^2/(2*B10))-(Summary!$B$3*SQRT((C10/B10)*(1-(C10/B10))/B10+Summary!$B$3^2/(4*B10^2))))/(1+Summary!$B$3^2/B10)) -> 0.41299967 | I10: =IF(B10=0,"",(((C10/B10)+Summary!$B$3^2/(2*B10))+(Summary!$B$3*SQRT((C10/B10)*(1-(C10/B10))/B10+Summary!$B$3^2/(4*B10^2))))/(1+Summary!$B$3^2/B10)) -> 0.82690514 | J10: =IF(B10=0,"",(C10+D10)/B10) -> 0.70588235 | K10: =IF(B10=0,"",E10/B10) -> 0.11764706 | L10: 10/15
A11: Stock | B11: =COUNTIFS('Holdout R2 (final)'!$I$5:$I$170,"<>",'Holdout R2 (final)'!$B$5:$B$170,"Stock") -> 17 | C11: =COUNTIFS('Holdout R2 (final)'!$I$5:$I$170,"Correct",'Holdout R2 (final)'!$B$5:$B$170,"Stock") -> 13 | D11: =COUNTIFS('Holdout R2 (final)'!$I$5:$I$170,"Safe ask",'Holdout R2 (final)'!$B$5:$B$170,"Stock") -> 0 | E11: =COUNTIFS('Holdout R2 (final)'!$I$5:$I$170,"Silent wrong",'Holdout R2 (final)'!$B$5:$B$170,"Stock") -> 1 | F11: =COUNTIFS('Holdout R2 (final)'!$I$5:$I$170,"Missed",'Holdout R2 (final)'!$B$5:$B$170,"Stock") -> 3 | G11: =IF(B11=0,"",C11/B11) -> 0.76470588 | H11: =IF(B11=0,"",(((C11/B11)+Summary!$B$3^2/(2*B11))-(Summary!$B$3*SQRT((C11/B11)*(1-(C11/B11))/B11+Summary!$B$3^2/(4*B11^2))))/(1+Summary!$B$3^2/B11)) -> 0.52737754 | I11: =IF(B11=0,"",(((C11/B11)+Summary!$B$3^2/(2*B11))+(Summary!$B$3*SQRT((C11/B11)*(1-(C11/B11))/B11+Summary!$B$3^2/(4*B11^2))))/(1+Summary!$B$3^2/B11)) -> 0.90445111 | J11: =IF(B11=0,"",(C11+D11)/B11) -> 0.76470588 | K11: =IF(B11=0,"",E11/B11) -> 0.058823529 | L11: 12/15
A12: Purchase | B12: =COUNTIFS('Holdout R2 (final)'!$I$5:$I$170,"<>",'Holdout R2 (final)'!$B$5:$B$170,"Purchase") -> 19 | C12: =COUNTIFS('Holdout R2 (final)'!$I$5:$I$170,"Correct",'Holdout R2 (final)'!$B$5:$B$170,"Purchase") -> 11 | D12: =COUNTIFS('Holdout R2 (final)'!$I$5:$I$170,"Safe ask",'Holdout R2 (final)'!$B$5:$B$170,"Purchase") -> 2 | E12: =COUNTIFS('Holdout R2 (final)'!$I$5:$I$170,"Silent wrong",'Holdout R2 (final)'!$B$5:$B$170,"Purchase") -> 3 | F12: =COUNTIFS('Holdout R2 (final)'!$I$5:$I$170,"Missed",'Holdout R2 (final)'!$B$5:$B$170,"Purchase") -> 3 | G12: =IF(B12=0,"",C12/B12) -> 0.57894737 | H12: =IF(B12=0,"",(((C12/B12)+Summary!$B$3^2/(2*B12))-(Summary!$B$3*SQRT((C12/B12)*(1-(C12/B12))/B12+Summary!$B$3^2/(4*B12^2))))/(1+Summary!$B$3^2/B12)) -> 0.36275551 | I12: =IF(B12=0,"",(((C12/B12)+Summary!$B$3^2/(2*B12))+(Summary!$B$3*SQRT((C12/B12)*(1-(C12/B12))/B12+Summary!$B$3^2/(4*B12^2))))/(1+Summary!$B$3^2/B12)) -> 0.7685838 | J12: =IF(B12=0,"",(C12+D12)/B12) -> 0.68421053 | K12: =IF(B12=0,"",E12/B12) -> 0.15789474 | L12: 10/15
A13: Report | B13: =COUNTIFS('Holdout R2 (final)'!$I$5:$I$170,"<>",'Holdout R2 (final)'!$B$5:$B$170,"Report") -> 10 | C13: =COUNTIFS('Holdout R2 (final)'!$I$5:$I$170,"Correct",'Holdout R2 (final)'!$B$5:$B$170,"Report") -> 7 | D13: =COUNTIFS('Holdout R2 (final)'!$I$5:$I$170,"Safe ask",'Holdout R2 (final)'!$B$5:$B$170,"Report") -> 0 | E13: =COUNTIFS('Holdout R2 (final)'!$I$5:$I$170,"Silent wrong",'Holdout R2 (final)'!$B$5:$B$170,"Report") -> 3 | F13: =COUNTIFS('Holdout R2 (final)'!$I$5:$I$170,"Missed",'Holdout R2 (final)'!$B$5:$B$170,"Report") -> 0 | G13: =IF(B13=0,"",C13/B13) -> 0.7 | H13: =IF(B13=0,"",(((C13/B13)+Summary!$B$3^2/(2*B13))-(Summary!$B$3*SQRT((C13/B13)*(1-(C13/B13))/B13+Summary!$B$3^2/(4*B13^2))))/(1+Summary!$B$3^2/B13)) -> 0.39677322 | I13: =IF(B13=0,"",(((C13/B13)+Summary!$B$3^2/(2*B13))+(Summary!$B$3*SQRT((C13/B13)*(1-(C13/B13))/B13+Summary!$B$3^2/(4*B13^2))))/(1+Summary!$B$3^2/B13)) -> 0.89221071 | J13: =IF(B13=0,"",(C13+D13)/B13) -> 0.7 | K13: =IF(B13=0,"",E13/B13) -> 0.3 | L13: 7/10
A14: Correction | B14: =COUNTIFS('Holdout R2 (final)'!$I$5:$I$170,"<>",'Holdout R2 (final)'!$B$5:$B$170,"Correction") -> 10 | C14: =COUNTIFS('Holdout R2 (final)'!$I$5:$I$170,"Correct",'Holdout R2 (final)'!$B$5:$B$170,"Correction") -> 8 | D14: =COUNTIFS('Holdout R2 (final)'!$I$5:$I$170,"Safe ask",'Holdout R2 (final)'!$B$5:$B$170,"Correction") -> 0 | E14: =COUNTIFS('Holdout R2 (final)'!$I$5:$I$170,"Silent wrong",'Holdout R2 (final)'!$B$5:$B$170,"Correction") -> 2 | F14: =COUNTIFS('Holdout R2 (final)'!$I$5:$I$170,"Missed",'Holdout R2 (final)'!$B$5:$B$170,"Correction") -> 0 | G14: =IF(B14=0,"",C14/B14) -> 0.8 | H14: =IF(B14=0,"",(((C14/B14)+Summary!$B$3^2/(2*B14))-(Summary!$B$3*SQRT((C14/B14)*(1-(C14/B14))/B14+Summary!$B$3^2/(4*B14^2))))/(1+Summary!$B$3^2/B14)) -> 0.49015685 | I14: =IF(B14=0,"",(((C14/B14)+Summary!$B$3^2/(2*B14))+(Summary!$B$3*SQRT((C14/B14)*(1-(C14/B14))/B14+Summary!$B$3^2/(4*B14^2))))/(1+Summary!$B$3^2/B14)) -> 0.94331905 | J14: =IF(B14=0,"",(C14+D14)/B14) -> 0.8 | K14: =IF(B14=0,"",E14/B14) -> 0.2 | L14: 8/10
A15: Router | B15: =COUNTIFS('Holdout R2 (final)'!$I$5:$I$170,"<>",'Holdout R2 (final)'!$B$5:$B$170,"Router") -> 10 | C15: =COUNTIFS('Holdout R2 (final)'!$I$5:$I$170,"Correct",'Holdout R2 (final)'!$B$5:$B$170,"Router") -> 9 | D15: =COUNTIFS('Holdout R2 (final)'!$I$5:$I$170,"Safe ask",'Holdout R2 (final)'!$B$5:$B$170,"Router") -> 0 | E15: =COUNTIFS('Holdout R2 (final)'!$I$5:$I$170,"Silent wrong",'Holdout R2 (final)'!$B$5:$B$170,"Router") -> 1 | F15: =COUNTIFS('Holdout R2 (final)'!$I$5:$I$170,"Missed",'Holdout R2 (final)'!$B$5:$B$170,"Router") -> 0 | G15: =IF(B15=0,"",C15/B15) -> 0.9 | H15: =IF(B15=0,"",(((C15/B15)+Summary!$B$3^2/(2*B15))-(Summary!$B$3*SQRT((C15/B15)*(1-(C15/B15))/B15+Summary!$B$3^2/(4*B15^2))))/(1+Summary!$B$3^2/B15)) -> 0.59584361 | I15: =IF(B15=0,"",(((C15/B15)+Summary!$B$3^2/(2*B15))+(Summary!$B$3*SQRT((C15/B15)*(1-(C15/B15))/B15+Summary!$B$3^2/(4*B15^2))))/(1+Summary!$B$3^2/B15)) -> 0.98212425 | J15: =IF(B15=0,"",(C15+D15)/B15) -> 0.9 | K15: =IF(B15=0,"",E15/B15) -> 0.1 | L15: 9/10
A16: All | B16: =COUNTIFS('Holdout R2 (final)'!$I$5:$I$170,"<>") -> 166 | C16: =COUNTIFS('Holdout R2 (final)'!$I$5:$I$170,"Correct") -> 125 | D16: =COUNTIFS('Holdout R2 (final)'!$I$5:$I$170,"Safe ask") -> 6 | E16: =COUNTIFS('Holdout R2 (final)'!$I$5:$I$170,"Silent wrong") -> 16 | F16: =COUNTIFS('Holdout R2 (final)'!$I$5:$I$170,"Missed") -> 19 | G16: =IF(B16=0,"",C16/B16) -> 0.75301205 | H16: =IF(B16=0,"",(((C16/B16)+Summary!$B$3^2/(2*B16))-(Summary!$B$3*SQRT((C16/B16)*(1-(C16/B16))/B16+Summary!$B$3^2/(4*B16^2))))/(1+Summary!$B$3^2/B16)) -> 0.68217786 | I16: =IF(B16=0,"",(((C16/B16)+Summary!$B$3^2/(2*B16))+(Summary!$B$3*SQRT((C16/B16)*(1-(C16/B16))/B16+Summary!$B$3^2/(4*B16^2))))/(1+Summary!$B$3^2/B16)) -> 0.81240062 | J16: =IF(B16=0,"",(C16+D16)/B16) -> 0.78915663 | K16: =IF(B16=0,"",E16/B16) -> 0.096385542 | L16: 103/135
A19: 2. Holdout round 1 (run 2026-10-08 14:40; used for fixes afterwards)
A20: Bundle | B20: Rows | C20: Correct | D20: Safe ask | E20: Silent wrong | F20: Missed | G20: Strict accuracy | H20: 95% CI low | I20: 95% CI high | J20: Safe rate | K20: Silent-error rate | L20: Tests fully right
A21: Employee | B21: =COUNTIFS('Holdout R1'!$I$5:$I$182,"<>",'Holdout R1'!$B$5:$B$182,"Employee") -> 19 | C21: =COUNTIFS('Holdout R1'!$I$5:$I$182,"Correct",'Holdout R1'!$B$5:$B$182,"Employee") -> 15 | D21: =COUNTIFS('Holdout R1'!$I$5:$I$182,"Safe ask",'Holdout R1'!$B$5:$B$182,"Employee") -> 1 | E21: =COUNTIFS('Holdout R1'!$I$5:$I$182,"Silent wrong",'Holdout R1'!$B$5:$B$182,"Employee") -> 2 | F21: =COUNTIFS('Holdout R1'!$I$5:$I$182,"Missed",'Holdout R1'!$B$5:$B$182,"Employee") -> 1 | G21: =IF(B21=0,"",C21/B21) -> 0.78947368 | H21: =IF(B21=0,"",(((C21/B21)+Summary!$B$3^2/(2*B21))-(Summary!$B$3*SQRT((C21/B21)*(1-(C21/B21))/B21+Summary!$B$3^2/(4*B21^2))))/(1+Summary!$B$3^2/B21)) -> 0.56665286 | I21: =IF(B21=0,"",(((C21/B21)+Summary!$B$3^2/(2*B21))+(Summary!$B$3*SQRT((C21/B21)*(1-(C21/B21))/B21+Summary!$B$3^2/(4*B21^2))))/(1+Summary!$B$3^2/B21)) -> 0.91492462 | J21: =IF(B21=0,"",(C21+D21)/B21) -> 0.84210526 | K21: =IF(B21=0,"",E21/B21) -> 0.10526316 | L21: 12/15
A22: Customer | B22: =COUNTIFS('Holdout R1'!$I$5:$I$182,"<>",'Holdout R1'!$B$5:$B$182,"Customer") -> 19 | C22: =COUNTIFS('Holdout R1'!$I$5:$I$182,"Correct",'Holdout R1'!$B$5:$B$182,"Customer") -> 11 | D22: =COUNTIFS('Holdout R1'!$I$5:$I$182,"Safe ask",'Holdout R1'!$B$5:$B$182,"Customer") -> 0 | E22: =COUNTIFS('Holdout R1'!$I$5:$I$182,"Silent wrong",'Holdout R1'!$B$5:$B$182,"Customer") -> 6 | F22: =COUNTIFS('Holdout R1'!$I$5:$I$182,"Missed",'Holdout R1'!$B$5:$B$182,"Customer") -> 2 | G22: =IF(B22=0,"",C22/B22) -> 0.57894737 | H22: =IF(B22=0,"",(((C22/B22)+Summary!$B$3^2/(2*B22))-(Summary!$B$3*SQRT((C22/B22)*(1-(C22/B22))/B22+Summary!$B$3^2/(4*B22^2))))/(1+Summary!$B$3^2/B22)) -> 0.36275551 | I22: =IF(B22=0,"",(((C22/B22)+Summary!$B$3^2/(2*B22))+(Summary!$B$3*SQRT((C22/B22)*(1-(C22/B22))/B22+Summary!$B$3^2/(4*B22^2))))/(1+Summary!$B$3^2/B22)) -> 0.7685838 | J22: =IF(B22=0,"",(C22+D22)/B22) -> 0.57894737 | K22: =IF(B22=0,"",E22/B22) -> 0.31578947 | L22: 9/15
A23: Supplier | B23: =COUNTIFS('Holdout R1'!$I$5:$I$182,"<>",'Holdout R1'!$B$5:$B$182,"Supplier") -> 18 | C23: =COUNTIFS('Holdout R1'!$I$5:$I$182,"Correct",'Holdout R1'!$B$5:$B$182,"Supplier") -> 10 | D23: =COUNTIFS('Holdout R1'!$I$5:$I$182,"Safe ask",'Holdout R1'!$B$5:$B$182,"Supplier") -> 1 | E23: =COUNTIFS('Holdout R1'!$I$5:$I$182,"Silent wrong",'Holdout R1'!$B$5:$B$182,"Supplier") -> 3 | F23: =COUNTIFS('Holdout R1'!$I$5:$I$182,"Missed",'Holdout R1'!$B$5:$B$182,"Supplier") -> 4 | G23: =IF(B23=0,"",C23/B23) -> 0.55555556 | H23: =IF(B23=0,"",(((C23/B23)+Summary!$B$3^2/(2*B23))-(Summary!$B$3*SQRT((C23/B23)*(1-(C23/B23))/B23+Summary!$B$3^2/(4*B23^2))))/(1+Summary!$B$3^2/B23)) -> 0.33716069 | I23: =IF(B23=0,"",(((C23/B23)+Summary!$B$3^2/(2*B23))+(Summary!$B$3*SQRT((C23/B23)*(1-(C23/B23))/B23+Summary!$B$3^2/(4*B23^2))))/(1+Summary!$B$3^2/B23)) -> 0.75440769 | J23: =IF(B23=0,"",(C23+D23)/B23) -> 0.61111111 | K23: =IF(B23=0,"",E23/B23) -> 0.16666667 | L23: 9/15
A24: Expense | B24: =COUNTIFS('Holdout R1'!$I$5:$I$182,"<>",'Holdout R1'!$B$5:$B$182,"Expense") -> 33 | C24: =COUNTIFS('Holdout R1'!$I$5:$I$182,"Correct",'Holdout R1'!$B$5:$B$182,"Expense") -> 16 | D24: =COUNTIFS('Holdout R1'!$I$5:$I$182,"Safe ask",'Holdout R1'!$B$5:$B$182,"Expense") -> 0 | E24: =COUNTIFS('Holdout R1'!$I$5:$I$182,"Silent wrong",'Holdout R1'!$B$5:$B$182,"Expense") -> 7 | F24: =COUNTIFS('Holdout R1'!$I$5:$I$182,"Missed",'Holdout R1'!$B$5:$B$182,"Expense") -> 10 | G24: =IF(B24=0,"",C24/B24) -> 0.48484848 | H24: =IF(B24=0,"",(((C24/B24)+Summary!$B$3^2/(2*B24))-(Summary!$B$3*SQRT((C24/B24)*(1-(C24/B24))/B24+Summary!$B$3^2/(4*B24^2))))/(1+Summary!$B$3^2/B24)) -> 0.32503782 | I24: =IF(B24=0,"",(((C24/B24)+Summary!$B$3^2/(2*B24))+(Summary!$B$3*SQRT((C24/B24)*(1-(C24/B24))/B24+Summary!$B$3^2/(4*B24^2))))/(1+Summary!$B$3^2/B24)) -> 0.64781895 | J24: =IF(B24=0,"",(C24+D24)/B24) -> 0.48484848 | K24: =IF(B24=0,"",E24/B24) -> 0.21212121 | L24: 6/15
A25: Family | B25: =COUNTIFS('Holdout R1'!$I$5:$I$182,"<>",'Holdout R1'!$B$5:$B$182,"Family") -> 19 | C25: =COUNTIFS('Holdout R1'!$I$5:$I$182,"Correct",'Holdout R1'!$B$5:$B$182,"Family") -> 12 | D25: =COUNTIFS('Holdout R1'!$I$5:$I$182,"Safe ask",'Holdout R1'!$B$5:$B$182,"Family") -> 1 | E25: =COUNTIFS('Holdout R1'!$I$5:$I$182,"Silent wrong",'Holdout R1'!$B$5:$B$182,"Family") -> 4 | F25: =COUNTIFS('Holdout R1'!$I$5:$I$182,"Missed",'Holdout R1'!$B$5:$B$182,"Family") -> 2 | G25: =IF(B25=0,"",C25/B25) -> 0.63157895 | H25: =IF(B25=0,"",(((C25/B25)+Summary!$B$3^2/(2*B25))-(Summary!$B$3*SQRT((C25/B25)*(1-(C25/B25))/B25+Summary!$B$3^2/(4*B25^2))))/(1+Summary!$B$3^2/B25)) -> 0.41039157 | I25: =IF(B25=0,"",(((C25/B25)+Summary!$B$3^2/(2*B25))+(Summary!$B$3*SQRT((C25/B25)*(1-(C25/B25))/B25+Summary!$B$3^2/(4*B25^2))))/(1+Summary!$B$3^2/B25)) -> 0.80850728 | J25: =IF(B25=0,"",(C25+D25)/B25) -> 0.68421053 | K25: =IF(B25=0,"",E25/B25) -> 0.21052632 | L25: 10/15
A26: Stock | B26: =COUNTIFS('Holdout R1'!$I$5:$I$182,"<>",'Holdout R1'!$B$5:$B$182,"Stock") -> 18 | C26: =COUNTIFS('Holdout R1'!$I$5:$I$182,"Correct",'Holdout R1'!$B$5:$B$182,"Stock") -> 11 | D26: =COUNTIFS('Holdout R1'!$I$5:$I$182,"Safe ask",'Holdout R1'!$B$5:$B$182,"Stock") -> 0 | E26: =COUNTIFS('Holdout R1'!$I$5:$I$182,"Silent wrong",'Holdout R1'!$B$5:$B$182,"Stock") -> 2 | F26: =COUNTIFS('Holdout R1'!$I$5:$I$182,"Missed",'Holdout R1'!$B$5:$B$182,"Stock") -> 5 | G26: =IF(B26=0,"",C26/B26) -> 0.61111111 | H26: =IF(B26=0,"",(((C26/B26)+Summary!$B$3^2/(2*B26))-(Summary!$B$3*SQRT((C26/B26)*(1-(C26/B26))/B26+Summary!$B$3^2/(4*B26^2))))/(1+Summary!$B$3^2/B26)) -> 0.38618669 | I26: =IF(B26=0,"",(((C26/B26)+Summary!$B$3^2/(2*B26))+(Summary!$B$3*SQRT((C26/B26)*(1-(C26/B26))/B26+Summary!$B$3^2/(4*B26^2))))/(1+Summary!$B$3^2/B26)) -> 0.79695008 | J26: =IF(B26=0,"",(C26+D26)/B26) -> 0.61111111 | K26: =IF(B26=0,"",E26/B26) -> 0.11111111 | L26: 10/15
A27: Purchase | B27: =COUNTIFS('Holdout R1'!$I$5:$I$182,"<>",'Holdout R1'!$B$5:$B$182,"Purchase") -> 22 | C27: =COUNTIFS('Holdout R1'!$I$5:$I$182,"Correct",'Holdout R1'!$B$5:$B$182,"Purchase") -> 11 | D27: =COUNTIFS('Holdout R1'!$I$5:$I$182,"Safe ask",'Holdout R1'!$B$5:$B$182,"Purchase") -> 1 | E27: =COUNTIFS('Holdout R1'!$I$5:$I$182,"Silent wrong",'Holdout R1'!$B$5:$B$182,"Purchase") -> 5 | F27: =COUNTIFS('Holdout R1'!$I$5:$I$182,"Missed",'Holdout R1'!$B$5:$B$182,"Purchase") -> 5 | G27: =IF(B27=0,"",C27/B27) -> 0.5 | H27: =IF(B27=0,"",(((C27/B27)+Summary!$B$3^2/(2*B27))-(Summary!$B$3*SQRT((C27/B27)*(1-(C27/B27))/B27+Summary!$B$3^2/(4*B27^2))))/(1+Summary!$B$3^2/B27)) -> 0.30721805 | I27: =IF(B27=0,"",(((C27/B27)+Summary!$B$3^2/(2*B27))+(Summary!$B$3*SQRT((C27/B27)*(1-(C27/B27))/B27+Summary!$B$3^2/(4*B27^2))))/(1+Summary!$B$3^2/B27)) -> 0.69278195 | J27: =IF(B27=0,"",(C27+D27)/B27) -> 0.54545455 | K27: =IF(B27=0,"",E27/B27) -> 0.22727273 | L27: 8/15
A28: Report | B28: =COUNTIFS('Holdout R1'!$I$5:$I$182,"<>",'Holdout R1'!$B$5:$B$182,"Report") -> 10 | C28: =COUNTIFS('Holdout R1'!$I$5:$I$182,"Correct",'Holdout R1'!$B$5:$B$182,"Report") -> 7 | D28: =COUNTIFS('Holdout R1'!$I$5:$I$182,"Safe ask",'Holdout R1'!$B$5:$B$182,"Report") -> 0 | E28: =COUNTIFS('Holdout R1'!$I$5:$I$182,"Silent wrong",'Holdout R1'!$B$5:$B$182,"Report") -> 3 | F28: =COUNTIFS('Holdout R1'!$I$5:$I$182,"Missed",'Holdout R1'!$B$5:$B$182,"Report") -> 0 | G28: =IF(B28=0,"",C28/B28) -> 0.7 | H28: =IF(B28=0,"",(((C28/B28)+Summary!$B$3^2/(2*B28))-(Summary!$B$3*SQRT((C28/B28)*(1-(C28/B28))/B28+Summary!$B$3^2/(4*B28^2))))/(1+Summary!$B$3^2/B28)) -> 0.39677322 | I28: =IF(B28=0,"",(((C28/B28)+Summary!$B$3^2/(2*B28))+(Summary!$B$3*SQRT((C28/B28)*(1-(C28/B28))/B28+Summary!$B$3^2/(4*B28^2))))/(1+Summary!$B$3^2/B28)) -> 0.89221071 | J28: =IF(B28=0,"",(C28+D28)/B28) -> 0.7 | K28: =IF(B28=0,"",E28/B28) -> 0.3 | L28: 7/10
A29: Correction | B29: =COUNTIFS('Holdout R1'!$I$5:$I$182,"<>",'Holdout R1'!$B$5:$B$182,"Correction") -> 10 | C29: =COUNTIFS('Holdout R1'!$I$5:$I$182,"Correct",'Holdout R1'!$B$5:$B$182,"Correction") -> 9 | D29: =COUNTIFS('Holdout R1'!$I$5:$I$182,"Safe ask",'Holdout R1'!$B$5:$B$182,"Correction") -> 0 | E29: =COUNTIFS('Holdout R1'!$I$5:$I$182,"Silent wrong",'Holdout R1'!$B$5:$B$182,"Correction") -> 1 | F29: =COUNTIFS('Holdout R1'!$I$5:$I$182,"Missed",'Holdout R1'!$B$5:$B$182,"Correction") -> 0 | G29: =IF(B29=0,"",C29/B29) -> 0.9 | H29: =IF(B29=0,"",(((C29/B29)+Summary!$B$3^2/(2*B29))-(Summary!$B$3*SQRT((C29/B29)*(1-(C29/B29))/B29+Summary!$B$3^2/(4*B29^2))))/(1+Summary!$B$3^2/B29)) -> 0.59584361 | I29: =IF(B29=0,"",(((C29/B29)+Summary!$B$3^2/(2*B29))+(Summary!$B$3*SQRT((C29/B29)*(1-(C29/B29))/B29+Summary!$B$3^2/(4*B29^2))))/(1+Summary!$B$3^2/B29)) -> 0.98212425 | J29: =IF(B29=0,"",(C29+D29)/B29) -> 0.9 | K29: =IF(B29=0,"",E29/B29) -> 0.1 | L29: 9/10
A30: Router | B30: =COUNTIFS('Holdout R1'!$I$5:$I$182,"<>",'Holdout R1'!$B$5:$B$182,"Router") -> 10 | C30: =COUNTIFS('Holdout R1'!$I$5:$I$182,"Correct",'Holdout R1'!$B$5:$B$182,"Router") -> 10 | D30: =COUNTIFS('Holdout R1'!$I$5:$I$182,"Safe ask",'Holdout R1'!$B$5:$B$182,"Router") -> 0 | E30: =COUNTIFS('Holdout R1'!$I$5:$I$182,"Silent wrong",'Holdout R1'!$B$5:$B$182,"Router") -> 0 | F30: =COUNTIFS('Holdout R1'!$I$5:$I$182,"Missed",'Holdout R1'!$B$5:$B$182,"Router") -> 0 | G30: =IF(B30=0,"",C30/B30) -> 1 | H30: =IF(B30=0,"",(((C30/B30)+Summary!$B$3^2/(2*B30))-(Summary!$B$3*SQRT((C30/B30)*(1-(C30/B30))/B30+Summary!$B$3^2/(4*B30^2))))/(1+Summary!$B$3^2/B30)) -> 0.72245983 | I30: =IF(B30=0,"",(((C30/B30)+Summary!$B$3^2/(2*B30))+(Summary!$B$3*SQRT((C30/B30)*(1-(C30/B30))/B30+Summary!$B$3^2/(4*B30^2))))/(1+Summary!$B$3^2/B30)) -> 1 | J30: =IF(B30=0,"",(C30+D30)/B30) -> 1 | K30: =IF(B30=0,"",E30/B30) -> 0 | L30: 10/10
A31: All | B31: =COUNTIFS('Holdout R1'!$I$5:$I$182,"<>") -> 178 | C31: =COUNTIFS('Holdout R1'!$I$5:$I$182,"Correct") -> 112 | D31: =COUNTIFS('Holdout R1'!$I$5:$I$182,"Safe ask") -> 4 | E31: =COUNTIFS('Holdout R1'!$I$5:$I$182,"Silent wrong") -> 33 | F31: =COUNTIFS('Holdout R1'!$I$5:$I$182,"Missed") -> 29 | G31: =IF(B31=0,"",C31/B31) -> 0.62921348 | H31: =IF(B31=0,"",(((C31/B31)+Summary!$B$3^2/(2*B31))-(Summary!$B$3*SQRT((C31/B31)*(1-(C31/B31))/B31+Summary!$B$3^2/(4*B31^2))))/(1+Summary!$B$3^2/B31)) -> 0.55622527 | I31: =IF(B31=0,"",(((C31/B31)+Summary!$B$3^2/(2*B31))+(Summary!$B$3*SQRT((C31/B31)*(1-(C31/B31))/B31+Summary!$B$3^2/(4*B31^2))))/(1+Summary!$B$3^2/B31)) -> 0.69674214 | J31: =IF(B31=0,"",(C31+D31)/B31) -> 0.65168539 | K31: =IF(B31=0,"",E31/B31) -> 0.18539326 | L31: 90/135
A34: 3. Round 2 by statement type (entry bundles only)
A35: Bundle | B35: Rows | C35: Correct | D35: Safe ask | E35: Silent wrong | F35: Missed | G35: Strict accuracy | H35: 95% CI low | I35: 95% CI high | J35: Safe rate | K35: Silent-error rate | L35: Tests fully right
A36: Papa-style | B36: =COUNTIFS('Holdout R2 (final)'!$I$5:$I$170,"<>",'Holdout R2 (final)'!$C$5:$C$170,"Papa-style") -> 70 | C36: =COUNTIFS('Holdout R2 (final)'!$I$5:$I$170,"Correct",'Holdout R2 (final)'!$C$5:$C$170,"Papa-style") -> 53 | D36: =COUNTIFS('Holdout R2 (final)'!$I$5:$I$170,"Safe ask",'Holdout R2 (final)'!$C$5:$C$170,"Papa-style") -> 4 | E36: =COUNTIFS('Holdout R2 (final)'!$I$5:$I$170,"Silent wrong",'Holdout R2 (final)'!$C$5:$C$170,"Papa-style") -> 4 | F36: =COUNTIFS('Holdout R2 (final)'!$I$5:$I$170,"Missed",'Holdout R2 (final)'!$C$5:$C$170,"Papa-style") -> 9 | G36: =IF(B36=0,"",C36/B36) -> 0.75714286 | H36: =IF(B36=0,"",(((C36/B36)+Summary!$B$3^2/(2*B36))-(Summary!$B$3*SQRT((C36/B36)*(1-(C36/B36))/B36+Summary!$B$3^2/(4*B36^2))))/(1+Summary!$B$3^2/B36)) -> 0.64504739 | I36: =IF(B36=0,"",(((C36/B36)+Summary!$B$3^2/(2*B36))+(Summary!$B$3*SQRT((C36/B36)*(1-(C36/B36))/B36+Summary!$B$3^2/(4*B36^2))))/(1+Summary!$B$3^2/B36)) -> 0.84248267 | J36: =IF(B36=0,"",(C36+D36)/B36) -> 0.81428571 | K36: =IF(B36=0,"",E36/B36) -> 0.057142857
A37: Mixed | B37: =COUNTIFS('Holdout R2 (final)'!$I$5:$I$170,"<>",'Holdout R2 (final)'!$C$5:$C$170,"Mixed") -> 66 | C37: =COUNTIFS('Holdout R2 (final)'!$I$5:$I$170,"Correct",'Holdout R2 (final)'!$C$5:$C$170,"Mixed") -> 48 | D37: =COUNTIFS('Holdout R2 (final)'!$I$5:$I$170,"Safe ask",'Holdout R2 (final)'!$C$5:$C$170,"Mixed") -> 2 | E37: =COUNTIFS('Holdout R2 (final)'!$I$5:$I$170,"Silent wrong",'Holdout R2 (final)'!$C$5:$C$170,"Mixed") -> 6 | F37: =COUNTIFS('Holdout R2 (final)'!$I$5:$I$170,"Missed",'Holdout R2 (final)'!$C$5:$C$170,"Mixed") -> 10 | G37: =IF(B37=0,"",C37/B37) -> 0.72727273 | H37: =IF(B37=0,"",(((C37/B37)+Summary!$B$3^2/(2*B37))-(Summary!$B$3*SQRT((C37/B37)*(1-(C37/B37))/B37+Summary!$B$3^2/(4*B37^2))))/(1+Summary!$B$3^2/B37)) -> 0.60957546 | I37: =IF(B37=0,"",(((C37/B37)+Summary!$B$3^2/(2*B37))+(Summary!$B$3*SQRT((C37/B37)*(1-(C37/B37))/B37+Summary!$B$3^2/(4*B37^2))))/(1+Summary!$B$3^2/B37)) -> 0.81996797 | J37: =IF(B37=0,"",(C37+D37)/B37) -> 0.75757576 | K37: =IF(B37=0,"",E37/B37) -> 0.090909091
A38: Entry bundles | B38: =COUNTIFS('Holdout R2 (final)'!$I$5:$I$170,"<>",'Holdout R2 (final)'!$C$5:$C$170,"<>—") -> 136 | C38: =COUNTIFS('Holdout R2 (final)'!$I$5:$I$170,"Correct",'Holdout R2 (final)'!$C$5:$C$170,"<>—") -> 101 | D38: =COUNTIFS('Holdout R2 (final)'!$I$5:$I$170,"Safe ask",'Holdout R2 (final)'!$C$5:$C$170,"<>—") -> 6 | E38: =COUNTIFS('Holdout R2 (final)'!$I$5:$I$170,"Silent wrong",'Holdout R2 (final)'!$C$5:$C$170,"<>—") -> 10 | F38: =COUNTIFS('Holdout R2 (final)'!$I$5:$I$170,"Missed",'Holdout R2 (final)'!$C$5:$C$170,"<>—") -> 19 | G38: =IF(B38=0,"",C38/B38) -> 0.74264706 | H38: =IF(B38=0,"",(((C38/B38)+Summary!$B$3^2/(2*B38))-(Summary!$B$3*SQRT((C38/B38)*(1-(C38/B38))/B38+Summary!$B$3^2/(4*B38^2))))/(1+Summary!$B$3^2/B38)) -> 0.6632161 | I38: =IF(B38=0,"",(((C38/B38)+Summary!$B$3^2/(2*B38))+(Summary!$B$3*SQRT((C38/B38)*(1-(C38/B38))/B38+Summary!$B$3^2/(4*B38^2))))/(1+Summary!$B$3^2/B38)) -> 0.80874646 | J38: =IF(B38=0,"",(C38+D38)/B38) -> 0.78676471 | K38: =IF(B38=0,"",E38/B38) -> 0.073529412
A41: 4. Round 1 by statement type (entry bundles only)
A42: Bundle | B42: Rows | C42: Correct | D42: Safe ask | E42: Silent wrong | F42: Missed | G42: Strict accuracy | H42: 95% CI low | I42: 95% CI high | J42: Safe rate | K42: Silent-error rate | L42: Tests fully right
A43: Papa-style | B43: =COUNTIFS('Holdout R1'!$I$5:$I$182,"<>",'Holdout R1'!$C$5:$C$182,"Papa-style") -> 75 | C43: =COUNTIFS('Holdout R1'!$I$5:$I$182,"Correct",'Holdout R1'!$C$5:$C$182,"Papa-style") -> 43 | D43: =COUNTIFS('Holdout R1'!$I$5:$I$182,"Safe ask",'Holdout R1'!$C$5:$C$182,"Papa-style") -> 3 | E43: =COUNTIFS('Holdout R1'!$I$5:$I$182,"Silent wrong",'Holdout R1'!$C$5:$C$182,"Papa-style") -> 17 | F43: =COUNTIFS('Holdout R1'!$I$5:$I$182,"Missed",'Holdout R1'!$C$5:$C$182,"Papa-style") -> 12 | G43: =IF(B43=0,"",C43/B43) -> 0.57333333 | H43: =IF(B43=0,"",(((C43/B43)+Summary!$B$3^2/(2*B43))-(Summary!$B$3*SQRT((C43/B43)*(1-(C43/B43))/B43+Summary!$B$3^2/(4*B43^2))))/(1+Summary!$B$3^2/B43)) -> 0.46052589 | I43: =IF(B43=0,"",(((C43/B43)+Summary!$B$3^2/(2*B43))+(Summary!$B$3*SQRT((C43/B43)*(1-(C43/B43))/B43+Summary!$B$3^2/(4*B43^2))))/(1+Summary!$B$3^2/B43)) -> 0.67899437 | J43: =IF(B43=0,"",(C43+D43)/B43) -> 0.61333333 | K43: =IF(B43=0,"",E43/B43) -> 0.22666667
A44: Mixed | B44: =COUNTIFS('Holdout R1'!$I$5:$I$182,"<>",'Holdout R1'!$C$5:$C$182,"Mixed") -> 73 | C44: =COUNTIFS('Holdout R1'!$I$5:$I$182,"Correct",'Holdout R1'!$C$5:$C$182,"Mixed") -> 43 | D44: =COUNTIFS('Holdout R1'!$I$5:$I$182,"Safe ask",'Holdout R1'!$C$5:$C$182,"Mixed") -> 1 | E44: =COUNTIFS('Holdout R1'!$I$5:$I$182,"Silent wrong",'Holdout R1'!$C$5:$C$182,"Mixed") -> 12 | F44: =COUNTIFS('Holdout R1'!$I$5:$I$182,"Missed",'Holdout R1'!$C$5:$C$182,"Mixed") -> 17 | G44: =IF(B44=0,"",C44/B44) -> 0.5890411 | H44: =IF(B44=0,"",(((C44/B44)+Summary!$B$3^2/(2*B44))-(Summary!$B$3*SQRT((C44/B44)*(1-(C44/B44))/B44+Summary!$B$3^2/(4*B44^2))))/(1+Summary!$B$3^2/B44)) -> 0.47449015 | I44: =IF(B44=0,"",(((C44/B44)+Summary!$B$3^2/(2*B44))+(Summary!$B$3*SQRT((C44/B44)*(1-(C44/B44))/B44+Summary!$B$3^2/(4*B44^2))))/(1+Summary!$B$3^2/B44)) -> 0.69468904 | J44: =IF(B44=0,"",(C44+D44)/B44) -> 0.60273973 | K44: =IF(B44=0,"",E44/B44) -> 0.16438356
A45: Entry bundles | B45: =COUNTIFS('Holdout R1'!$I$5:$I$182,"<>",'Holdout R1'!$C$5:$C$182,"<>—") -> 148 | C45: =COUNTIFS('Holdout R1'!$I$5:$I$182,"Correct",'Holdout R1'!$C$5:$C$182,"<>—") -> 86 | D45: =COUNTIFS('Holdout R1'!$I$5:$I$182,"Safe ask",'Holdout R1'!$C$5:$C$182,"<>—") -> 4 | E45: =COUNTIFS('Holdout R1'!$I$5:$I$182,"Silent wrong",'Holdout R1'!$C$5:$C$182,"<>—") -> 29 | F45: =COUNTIFS('Holdout R1'!$I$5:$I$182,"Missed",'Holdout R1'!$C$5:$C$182,"<>—") -> 29 | G45: =IF(B45=0,"",C45/B45) -> 0.58108108 | H45: =IF(B45=0,"",(((C45/B45)+Summary!$B$3^2/(2*B45))-(Summary!$B$3*SQRT((C45/B45)*(1-(C45/B45))/B45+Summary!$B$3^2/(4*B45^2))))/(1+Summary!$B$3^2/B45)) -> 0.50052562 | I45: =IF(B45=0,"",(((C45/B45)+Summary!$B$3^2/(2*B45))+(Summary!$B$3*SQRT((C45/B45)*(1-(C45/B45))/B45+Summary!$B$3^2/(4*B45^2))))/(1+Summary!$B$3^2/B45)) -> 0.65753383 | J45: =IF(B45=0,"",(C45+D45)/B45) -> 0.60810811 | K45: =IF(B45=0,"",E45/B45) -> 0.19594595
A48: How to read this
A49: • Round 2 is the headline result on unseen data: it was written after the round-1 fixes and run once, with no fix after it.
A50: • Round 1 is shown for honesty: its failures were used to make 7 fix groups, so it shows the system BEFORE those fixes.
A51: • The dev bundle numbers (Summary) are higher because the fixes were made while looking at those tests; holdout numbers are the realistic estimate.
A52: • Round 2 is smaller in rows (166 vs 178) because fewer extra (wrong) entries were created — extra entries add rows.
A53: • Main remaining failure families (round 2): a short employee name matched inside a longer name ('Mange Ram' → 'Ram'), 'le gaya' read as goods instead of money, amount split from its person, stock shortage words, home vs business expense, person name in report requests. See Known issues and Roadmap.

Sheet Holdout R2 (final)
A1: Holdout round 2 (FINAL) — 135 new unseen statements (run 2026-10-08 16:51, Hinglish)
A2: Same design as round 1, new statements, written after the round-1 fixes and locked 16:49. Run ONCE; no fix was made after this run, so these are the final numbers on unseen data. Before the run the user simplified 5 statements (EMP-04, EMP-07, EMP-08, SUP-07, PUR-01).
A3: Same scorer and rules as round 1 and the dev bundles. A correctly asked question on an ASK test counts as Correct. Debatable rows kept as scored: RPT-03 'pichle paanch din' (start 3 Oct vs 4 Oct), CUS-06 quantity 0 vs 1.
A4: Test ID | B4: Bundle | C4: Statement type | D4: Event # | E4: Statement (Hinglish) | F4: Expected outcome | G4: Expected entry / route | H4: Actual (system output) | I4: Result | J4: Remark (scorer)
A5: F2-EMP-01 | B5: Employee | C5: Papa-style | D5: 1 | E5: Naresh beldar ki aaj ki 550 mazdoori chuka di | F5: ENTRY | G5: employee_transaction(employee_name=Naresh, transaction_type=payment, amount=550, date=T) | H5: employee_transaction(note=mazdoori chuka di, amount=550.0, employee_name=Naresh beldar, transaction_date=2026-10-08, transaction_type=payment) | I5: Correct
A6: F2-EMP-02 | B6: Employee | C6: Papa-style | D6: 1 | E6: Sohan aaj site pe nahi aaya, beemar hai | F6: ENTRY | G6: attendance(employee_name=Sohan, attendance=absent, date=T) | H6: attendance(note=beemar hai, driving=absent, attendance=absent, employee_name=Sohan, attendance_date=2026-10-08) | I6: Correct
A7: F2-EMP-03 | B7: Employee | C7: Papa-style | D7: 1 | E7: Ram ne gudam mein darwaze chhaante, 700 bante hain | F7: ENTRY | G7: employee_transaction(employee_name=Ram, transaction_type=work, amount=700, date=T) | H7: (no entry) | I7: Missed | J7: record_employee_transaction: no entry, no question (route=accounting)
A8: F2-EMP-04 | B8: Employee | C8: Papa-style | D8: 1 | E8: Kitanu aaj kaam pe aaya, tractor bhi usi ne chalaya | F8: ENTRY | G8: attendance(employee_name=Kitanu, attendance=P, driving=P, date=T) | H8: attendance(driving=P, attendance=P, employee_name=Kitanu, attendance_date=2026-10-08) | I8: Correct
A9: F2-EMP-05 | B9: Employee | C9: Papa-style | D9: 1 | E9: Pappu ko kal 300 aur aaj 400 diye | F9: ENTRY | G9: employee_transaction(employee_name=Pappu, transaction_type=payment, amount=300, date=T-1) | H9: employee_transaction(amount=300.0, employee_name=Pappu, transaction_date=2026-10-07, transaction_type=payment); employee_transaction(amount=400.0, employee_name=Pappu, transaction_date=2026-10-08, transaction_type=payment) | I9: Correct
A10: F2-EMP-05 | B10: Employee | C10: Papa-style | D10: 2 | E10: Pappu ko kal 300 aur aaj 400 diye | F10: ENTRY | G10: employee_transaction(employee_name=Pappu, transaction_type=payment, amount=400, date=T) | H10: ″ | I10: Correct
A11: F2-EMP-06 | B11: Employee | C11: Papa-style | D11: 1 | E11: sohan ko saade teen sau thama diye dopahar mein | F11: ENTRY | G11: employee_transaction(employee_name=Sohan, transaction_type=payment, amount=350, date=T) | H11: employee_transaction(amount=350.0, employee_name=Sohan, transaction_date=2026-10-08, transaction_type=payment) | I11: Correct
A12: F2-EMP-07 | B12: Employee | C12: Papa-style | D12: 1 | E12: Naresh aaj aaya aur 600 le gaya | F12: ENTRY | G12: attendance(employee_name=Naresh, attendance=P, date=T) | H12: attendance(driving=absent, attendance=P, employee_name=Naresh, attendance_date=2026-10-08) | I12: Correct | J12: record_employee_transaction: no entry, no question (route=accounting)
A13: F2-EMP-07 | B13: Employee | C13: Papa-style | D13: 2 | E13: Naresh aaj aaya aur 600 le gaya | F13: ENTRY | G13: employee_transaction(employee_name=Naresh, transaction_type=payment, amount=600, date=T) | H13: ″ | I13: Missed
A14: F2-EMP-08 | B14: Employee | C14: Papa-style | D14: 1 | E14: Pappu ko agle hafte 500 denge | F14: NO-ENTRY | G14: (no entry) | H14: (no entry) | I14: Correct
A15: F2-EMP-09 | B15: Employee | C15: Mixed | D15: 1 | E15: Naresh ne aaj gudam pe chaukhat saaf ki, 500 banta hai | F15: ENTRY | G15: employee_transaction(employee_name=Naresh, transaction_type=work, amount=500, date=T) | H15: employee_transaction(note=gudam pe chaukhat saaf ki, amount=500.0, employee_name=Naresh, transaction_date=2026-10-08, transaction_type=work) | I15: Correct
A16: F2-EMP-10 | B16: Employee | C16: Mixed | D16: 1 | E16: Ram lunch ke baad nikal gaya aaj, aadha din hi raha | F16: ENTRY | G16: attendance(employee_name=Ram, attendance=half, date=T) | H16: attendance(driving=absent, attendance=half, employee_name=Ram, attendance_date=2026-10-08) | I16: Correct
A17: F2-EMP-11 | B17: Employee | C17: Mixed | D17: 1 | E17: Pappu ko 1000 advance de diye shaadi ke liye | F17: ENTRY | G17: employee_transaction(employee_name=Pappu, transaction_type=payment, amount=1000, date=T) | H17: employee_transaction(note=advance de diye shaadi ke liye, amount=1000.0, employee_name=Pappu, transaction_date=2026-10-08, transaction_type=payment) | I17: Correct
A18: F2-EMP-12 | B18: Employee | C18: Mixed | D18: 1 | E18: Kitanu ko aaj 250 kharche ke diye | F18: ENTRY | G18: employee_transaction(employee_name=Kitanu, transaction_type=payment, amount=250, date=T) | H18: employee_transaction(note=kharche ke diye, amount=250.0, employee_name=Kitanu, transaction_date=2026-10-08, transaction_type=payment) | I18: Correct
A19: F2-EMP-13 | B19: Employee | C19: Mixed | D19: 1 | E19: Naresh ki aaj chhutti rahi | F19: ENTRY | G19: attendance(employee_name=Naresh, attendance=absent, date=T) | H19: attendance(note=chhutti rahi, driving=absent, attendance=absent, employee_name=Naresh, attendance_date=2026-10-08) | I19: Correct
A20: F2-EMP-14 | B20: Employee | C20: Mixed | D20: 1 | E20: pappu kal aadha din aaya tha, aaj poora | F20: ENTRY | G20: attendance(employee_name=Pappu, attendance=half, date=T-1) | H20: attendance(driving=absent, attendance=half, employee_name=Pappu, attendance_date=2026-10-07); attendance(driving=absent, attendance=P, employee_name=Pappu, attendance_date=2026-10-08) | I20: Correct
A21: F2-EMP-14 | B21: Employee | C21: Mixed | D21: 2 | E21: pappu kal aadha din aaya tha, aaj poora | F21: ENTRY | G21: attendance(employee_name=Pappu, attendance=P, date=T) | H21: ″ | I21: Correct
A22: F2-EMP-15 | B22: Employee | C22: Mixed | D22: 1 | E22: Naresh ko kuch paise de diye | F22: ASK | G22: employee_transaction(employee_name=Naresh, transaction_type=payment, date=T) | H22: (no entry) | asked: missing_argument | I22: Correct | J22: record_employee_transaction: asked missing_argument:record_employee_transaction ['amount']
A23: F2-CUS-01 | B23: Customer | C23: Papa-style | D23: 1 | E23: Dalbir ko 12 purani khidkiyan 6000 mein bechi | F23: ENTRY | G23: sale_transaction(customer_name=Dalbir, item_name=khidki, quantity=12, amount=6000, date=T) | H23: (no entry) | asked: material_movement, material_movement, missing_argument | I23: Safe ask | J23: record_sale_transaction: asked missing_argument:record_sale_transaction ['amount']
A24: F2-CUS-02 | B24: Customer | C24: Papa-style | D24: 1 | E24: Kuldeep ji ne 4500 bheje PhonePe se | F24: ENTRY | G24: sale_payment(customer_name=Kuldeep ji, amount=4500, date=T) | H24: sale_payment(amount=4500.0, payment_date=2026-10-08, customer_name=Kuldeep ji) | I24: Correct
A25: F2-CUS-03 | B25: Customer | C25: Papa-style | D25: 1 | E25: Gudam se 2000 eent Sharma ji ke plot pe gayi, 6 ka rate | F25: ENTRY | G25: sale_transaction(customer_name=Sharma ji, item_name=eent, quantity=2000, rate=6, amount=12000, source=gudam, date=T) | H25: sale_transaction(rate=6.0, unit=piece, amount=12000.0, source=Gudam, quantity=2000.0, item_name=eent, sale_date=2026-10-08, customer_name=Sharma ji, destination_name=plot, update_inventory=True) | I25: Correct
A26: F2-CUS-04 | B26: Customer | C26: Papa-style | D26: 1 | E26: Dalbir pe pehle ka 3500 nikalta hai | F26: ENTRY | G26: opening_balance(party_name=Dalbir, amount=3500, direction=lena) | H26: (no entry) | asked: correction | I26: Missed | J26: record_opening_balance: asked correction:
A27: F2-CUS-05 | B27: Customer | C27: Papa-style | D27: 1 | E27: Suresh Traders 5 shahteer le gaye 10000 ke, 4000 de gaye | F27: ENTRY | G27: sale_transaction(customer_name=Suresh Traders, item_name=shahteer, quantity=5, amount=10000, date=T) | H27: sale_transaction(amount=10000.0, quantity=5.0, item_name=shahteer, sale_date=2026-10-08, customer_name=Suresh Traders, supplier_name=Suresh Traders, update_inventory=True); sale_payment(amount=4000.0, payment_date=2026-10-08, customer_name=Suresh Traders) | I27: Correct
A28: F2-CUS-05 | B28: Customer | C28: Papa-style | D28: 2 | E28: Suresh Traders 5 shahteer le gaye 10000 ke, 4000 de gaye | F28: ENTRY | G28: sale_payment(customer_name=Suresh Traders, amount=4000, date=T) | H28: ″ | I28: Correct
A29: F2-CUS-06 | B29: Customer | C29: Papa-style | D29: 1 | E29: kuldeep ji ko dhai hazaar ki ek purani almari di | F29: ENTRY | G29: sale_transaction(customer_name=Kuldeep ji, item_name=almari, quantity=1, amount=2500, date=T) | H29: sale_transaction(amount=2500.0, item_name=purani almari, sale_date=2026-10-08, customer_name=kuldeep ji, update_inventory=True) | asked: material_movement, material_movement | I29: Silent wrong | J29: record_sale_transaction: quantity 0.0≠1
A30: F2-CUS-07 | B30: Customer | C30: Papa-style | D30: 1 | E30: Dalbir 300 eent le gaya | F30: ASK | G30: sale_transaction(customer_name=Dalbir, item_name=eent, quantity=300, date=T) | H30: (no entry) | asked: material_movement, material_movement | I30: Missed | J30: record_sale_transaction: no entry, no question (route=accounting)
A31: F2-CUS-08 | B31: Customer | C31: Papa-style | D31: 1 | E31: Sharma ji ne bola hai parso tak 5000 pahuncha denge | F31: NO-ENTRY | G31: (no entry) | H31: (no entry) | I31: Correct
A32: F2-CUS-09 | B32: Customer | C32: Mixed | D32: 1 | E32: Kuldeep ji ko 20 balli 6000 mein di, gudam se | F32: ENTRY | G32: sale_transaction(customer_name=Kuldeep ji, item_name=balli, quantity=20, amount=6000, source=gudam, date=T) | H32: (no entry) | asked: material_movement | I32: Missed | J32: record_sale_transaction: no entry, no question (route=accounting)
A33: F2-CUS-10 | B33: Customer | C33: Mixed | D33: 1 | E33: Dalbir ne purane 1500 de diye | F33: ENTRY | G33: sale_payment(customer_name=Dalbir, amount=1500, date=T) | H33: sale_payment(note=purane, amount=1500.0, payment_date=2026-10-08, customer_name=Dalbir) | I33: Correct
A34: F2-CUS-11 | B34: Customer | C34: Mixed | D34: 1 | E34: Sharma ji ko 4 girder 16000 ke diye, 10000 aaye | F34: ENTRY | G34: sale_transaction(customer_name=Sharma ji, item_name=girder, quantity=4, amount=16000, date=T) | H34: sale_transaction(amount=16000.0, quantity=4.0, item_name=girder, sale_date=2026-10-08, customer_name=Sharma ji, supplier_name=Sharma ji, update_inventory=True); sale_payment(amount=10000.0, payment_date=2026-10-08, customer_name=Sharma ji) | I34: Correct
A35: F2-CUS-11 | B35: Customer | C35: Mixed | D35: 2 | E35: Sharma ji ko 4 girder 16000 ke diye, 10000 aaye | F35: ENTRY | G35: sale_payment(customer_name=Sharma ji, amount=10000, date=T) | H35: ″ | I35: Correct
A36: F2-CUS-12 | B36: Customer | C36: Mixed | D36: 1 | E36: Kuldeep ji ka 2000 aaya | F36: ENTRY | G36: sale_payment(customer_name=Kuldeep ji, amount=2000, date=T) | H36: sale_payment(amount=2000.0, payment_date=2026-10-08, customer_name=Kuldeep ji) | I36: Correct
A37: F2-CUS-13 | B37: Customer | C37: Mixed | D37: 1 | E37: Satbir paanch sau eent le gaya teen hazaar ki | F37: ENTRY | G37: sale_transaction(customer_name=Satbir, item_name=eent, quantity=500, amount=3000, date=T) | H37: (no entry) | asked: material_movement, material_movement | I37: Missed | J37: record_sale_transaction: no entry, no question (route=accounting)
A38: F2-CUS-14 | B38: Customer | C38: Mixed | D38: 1 | E38: dalbir ko sava sau eent saade paanch ke rate se | F38: ENTRY | G38: sale_transaction(customer_name=Dalbir, item_name=eent, quantity=125, rate=5.5, amount=687.5, date=T) | H38: sale_transaction(rate=5.0, amount=3750.0, quantity=750.0, item_name=eent, sale_date=2026-10-08, customer_name=Dalbir, update_inventory=True) | asked: material_movement, material_movement | I38: Silent wrong | J38: record_sale_transaction: amount 3750.0≠687.5; quantity 750.0≠125; rate 5.0≠5.5
A39: F2-CUS-15 | B39: Customer | C39: Mixed | D39: 1 | E39: Dalbir se 1000 aaye, aur Sharma ji 300 eent 1800 mein le gaye | F39: ENTRY | G39: sale_payment(customer_name=Dalbir, amount=1000, date=T) | H39: sale_payment(amount=1000.0, payment_date=2026-10-08, customer_name=Dalbir); sale_transaction(amount=1800.0, quantity=300.0, item_name=eent, sale_date=2026-10-08, customer_name=Sharma ji, update_inventory=True) | asked: material_movement | I39: Correct
A40: F2-CUS-15 | B40: Customer | C40: Mixed | D40: 2 | E40: Dalbir se 1000 aaye, aur Sharma ji 300 eent 1800 mein le gaye | F40: ENTRY | G40: sale_transaction(customer_name=Sharma ji, item_name=eent, quantity=300, amount=1800, date=T) | H40: ″ | I40: Correct
A41: F2-SUP-01 | B41: Supplier | C41: Papa-style | D41: 1 | E41: Hanuman bhatte se 4000 eent gudam aayi, 6.5 ka rate | F41: ENTRY | G41: supplier_transaction(supplier_name=Hanuman, item_name=eent, quantity=4000, rate=6.5, amount=26000, destination_location=gudam, date=T) | H41: supplier_transaction(rate=6.5, unit=kg, amount=26000.0, quantity=4000.0, item_name=eent, supplier_name=Hanuman bhatte, transaction_date=2026-10-08, destination_location=Gudam) | asked: material_movement | I41: Correct
A42: F2-SUP-02 | B42: Supplier | C42: Papa-style | D42: 1 | E42: Garg timber wale ko 12000 cheque diya | F42: ENTRY | G42: supplier_payment(supplier_name=Garg timber, amount=12000, date=T) | H42: supplier_payment(note=cheque, amount=12000.0, payment_date=2026-10-08, supplier_name=Garg) | I42: Correct
A43: F2-SUP-03 | B43: Supplier | C43: Papa-style | D43: 1 | E43: SBI se 2500 eent dukaan pe utri 17500 ki, Kitanu laya | F43: ENTRY | G43: supplier_transaction(supplier_name=SBI Bhatta, item_name=eent, quantity=2500, amount=17500, destination_location=shop, driver_name=Kitanu, date=T) | H43: supplier_transaction(amount=17500.0, quantity=2500.0, item_name=eent, driver_name=Kitanu, supplier_name=SBI Bhatta, transaction_date=2026-10-08, destination_location=Dukaan) | I43: Correct
A44: F2-SUP-04 | B44: Supplier | C44: Papa-style | D44: 1 | E44: Garg timber se 40 balli aayi 8000 ki, gudam mein | F44: ENTRY | G44: supplier_transaction(supplier_name=Garg timber, item_name=balli, quantity=40, amount=8000, destination_location=gudam, date=T) | H44: supplier_transaction(amount=8000.0, quantity=40.0, item_name=balli, supplier_name=Garg timber, transaction_date=2026-10-08, destination_location=Gudam) | asked: material_movement | I44: Correct
A45: F2-SUP-05 | B45: Supplier | C45: Papa-style | D45: 1 | E45: Hanuman bhatte ke 20000 purane dene hain | F45: ENTRY | G45: opening_balance(party_name=Hanuman, amount=20000, direction=dena) | H45: opening_balance(amount=20000.0, direction=dena, as_of_date=2026-10-08, party_name=Hanuman bhatte, party_type=supplier) | I45: Correct
A46: F2-SUP-06 | B46: Supplier | C46: Papa-style | D46: 1 | E46: hanuman wale ko aath hazaar online kar diye | F46: ENTRY | G46: supplier_payment(supplier_name=Hanuman, amount=8000, date=T) | H46: supplier_payment(amount=8000.0, payment_date=2026-10-08, supplier_name=hanuman) | I46: Correct
A47: F2-SUP-07 | B47: Supplier | C47: Papa-style | D47: 1 | E47: Garg timber se 25 phatte aaye 5000 ke, poore de diye | F47: ENTRY | G47: supplier_transaction(supplier_name=Garg timber, item_name=phatta, quantity=25, amount=5000, date=T) | H47: supplier_transaction(amount=5000.0, quantity=25.0, item_name=phatte, supplier_name=Garg timber, transaction_date=2026-10-08); supplier_payment(note=poore de diye, amount=5000.0, payment_date=2026-10-08, supplier_name=Garg timber) | asked: material_movement, material_movement | I47: Correct
A48: F2-SUP-07 | B48: Supplier | C48: Papa-style | D48: 2 | E48: Garg timber se 25 phatte aaye 5000 ke, poore de diye | F48: ENTRY | G48: supplier_payment(supplier_name=Garg timber, amount=5000, date=T) | H48: ″ | I48: Correct
A49: F2-SUP-08 | B49: Supplier | C49: Papa-style | D49: 1 | E49: SBI wale bol rahe the rate badhega agle hafte | F49: NO-ENTRY | G49: (no entry) | H49: (no entry) | I49: Correct
A50: F2-SUP-09 | B50: Supplier | C50: Mixed | D50: 1 | E50: SBI se 3000 eent shop pe aayi 21000 ki | F50: ENTRY | G50: supplier_transaction(supplier_name=SBI Bhatta, item_name=eent, quantity=3000, amount=21000, destination_location=shop, date=T) | H50: supplier_transaction(amount=21000.0, quantity=3000.0, item_name=eent, supplier_name=SBI Bhatta, transaction_date=2026-10-08, destination_location=Shop) | I50: Correct
... A55: F2-SUP-14 | B55: Supplier | C55: Mixed | D55: 1 | E55: garg wale se dedh sau phatte aaye, sau rupaye ka ek, dukaan pe | F55: ENTRY | G55: supplier_transaction(supplier_name=Garg timber, item_name=phatta, quantity=150, rate=100, amount=15000, destination_location=shop, date=T) | H55: supplier_transaction(rate=100.0, amount=15000.0, quantity=150.0, item_name=phatte, supplier_name=garg, transaction_date=2026-10-08, destination_location=Dukaan) | asked: material_movement | I55: Correct
A56: F2-SUP-15 | B56: Supplier | C56: Mixed | D56: 1 | E56: Hanuman wale ki gaadi aayi thi eent lekar | F56: ASK | G56: supplier_transaction(supplier_name=Hanuman, item_name=eent, date=T) | H56: supplier_transaction(note=gaadi aayi thi, item_name=eent, supplier_name=Hanuman, transaction_date=2026-10-08) | asked: material_movement, material_movement | I56: Silent wrong | J56: record_supplier_transaction: recorded instead of asking (values guessed)
A57: F2-EXP-01 | B57: Expense | C57: Papa-style | D57: 1 | E57: Dumper chalane ko 3000 ka tel daalwa diya pump pe | F57: ENTRY | G57: expense(category=fuel, amount=3000, date=T) | H57: expense(note=pump pe, amount=3000.0, category=fuel, description=tel daalwa, expense_date=2026-10-08); expense_payment(note=pump pe, amount=3000.0, description=tel daalwa, payment_date=2026-10-08) | I57: Correct
A58: F2-EXP-01 | B58: Expense | C58: Papa-style | D58: 2 | E58: Dumper chalane ko 3000 ka tel daalwa diya pump pe | F58: ENTRY | G58: expense_payment(amount=3000, date=T) | H58: ″ | I58: Correct
A59: F2-EXP-02 | B59: Expense | C59: Papa-style | D59: 1 | E59: Gudam ki tubelight aur wire 450 ki aayi | F59: ENTRY | G59: expense(category=misc, amount=450, date=T) | H59: (no entry) | asked: material_movement | I59: Missed | J59: record_expense: no entry, no question (route=accounting) · record_expense_payment: no entry, no question (route=accounting)
A60: F2-EXP-02 | B60: Expense | C60: Papa-style | D60: 2 | E60: Gudam ki tubelight aur wire 450 ki aayi | F60: ENTRY | G60: expense_payment(amount=450, date=T) | H60: ″ | I60: Missed
A61: F2-EXP-03 | B61: Expense | C61: Papa-style | D61: 1 | E61: Hydra 2 ghante lagi Dhani wali site pe, 2400 diye | F61: ENTRY | G61: expense(category=rent, amount=2400, date=T) | H61: (no entry) | asked: missing_argument | I61: Safe ask | J61: record_expense: asked missing_argument:record_employee_transaction ['amount'] · record_expense_payment: asked missing_argument:record_employee_transaction ['amount']
A62: F2-EXP-03 | B62: Expense | C62: Papa-style | D62: 2 | E62: Hydra 2 ghante lagi Dhani wali site pe, 2400 diye | F62: ENTRY | G62: expense_payment(amount=2400, date=T) | H62: ″ | I62: Safe ask
A63: F2-EXP-04 | B63: Expense | C63: Papa-style | D63: 1 | E63: Gudam ka kiraya 7000 de diya is mahine ka | F63: ENTRY | G63: expense(category=rent, amount=7000, date=T) | H63: expense(note=is mahine ka, amount=7000.0, category=rent, description=kiraya, expense_date=2026-10-08); expense_payment(note=is mahine ka, amount=7000.0, description=kiraya, payment_date=2026-10-08) | I63: Correct
A64: F2-EXP-04 | B64: Expense | C64: Papa-style | D64: 2 | E64: Gudam ka kiraya 7000 de diya is mahine ka | F64: ENTRY | G64: expense_payment(amount=7000, date=T) | H64: ″ | I64: Correct
A65: F2-EXP-05 | B65: Expense | C65: Papa-style | D65: 1 | E65: Trolley ki welding karwayi 600 mein | F65: ENTRY | G65: expense(category=repair, amount=600, date=T) | H65: expense(amount=600.0, category=repair, description=Trolley ki welding, expense_date=2026-10-08); expense_payment(amount=600.0, description=trolley ki welding, payment_date=2026-10-08) | I65: Correct
A66: F2-EXP-05 | B66: Expense | C66: Papa-style | D66: 2 | E66: Trolley ki welding karwayi 600 mein | F66: ENTRY | G66: expense_payment(amount=600, date=T) | H66: ″ | I66: Correct
A67: F2-EXP-06 | B67: Expense | C67: Papa-style | D67: 1 | E67: chai paani mein aaj dedh sau gaye | F67: ENTRY | G67: expense(category=misc, amount=150, date=T) | H67: expense(amount=150.0, category=misc, description=chai paani, expense_date=2026-10-08); expense_payment(amount=150.0, description=chai paani, payment_date=2026-10-08) | I67: Correct
A68: F2-EXP-06 | B68: Expense | C68: Papa-style | D68: 2 | E68: chai paani mein aaj dedh sau gaye | F68: ENTRY | G68: expense_payment(amount=150, date=T) | H68: ″ | I68: Correct
A69: F2-EXP-07 | B69: Expense | C69: Papa-style | D69: 1 | E69: Generator theek karwaya | F69: ASK | G69: (no entry) | H69: (no entry) | asked: missing_argument | I69: Correct | J69: asked/stopped: missing_argument: record_expense ['amount']
A70: F2-EXP-08 | B70: Expense | C70: Papa-style | D70: 1 | E70: Agle hafte malba uthwane ko hydra mangwani padegi | F70: NO-ENTRY | G70: (no entry) | H70: (no entry) | I70: Correct
A71: F2-EXP-09 | B71: Expense | C71: Mixed | D71: 1 | E71: Tractor ka filter badalwaya 800 ka | F71: ENTRY | G71: expense(category=repair, amount=800, date=T) | H71: expense(amount=800.0, category=repair, description=Tractor ka filter badalwaya, expense_date=2026-10-08); expense_payment(amount=800.0, description=tractor ka filter badalwaya, payment_date=2026-10-08) | I71: Correct
A72: F2-EXP-09 | B72: Expense | C72: Mixed | D72: 2 | E72: Tractor ka filter badalwaya 800 ka | F72: ENTRY | G72: expense_payment(amount=800, date=T) | H72: ″ | I72: Correct
A73: F2-EXP-10 | B73: Expense | C73: Mixed | D73: 1 | E73: Bijli daftar mein dukaan ka 1900 bhara | F73: ENTRY | G73: expense(category=misc, amount=1900, date=T) | H73: expense(amount=1900.0, category=misc, description=bijli daftar mein dukaan ka, expense_date=2026-10-08); expense_payment(amount=1900.0, description=dukaan ka, payment_date=2026-10-08) | I73: Correct
A74: F2-EXP-10 | B74: Expense | C74: Mixed | D74: 2 | E74: Bijli daftar mein dukaan ka 1900 bhara | F74: ENTRY | G74: expense_payment(amount=1900, date=T) | H74: ″ | I74: Correct
A75: F2-EXP-11 | B75: Expense | C75: Mixed | D75: 1 | E75: JCB ka 3 ghante ka 2700 diya Kalanaur site pe | F75: ENTRY | G75: expense(category=rent, amount=2700, date=T) | H75: employee_transaction(note=JCB ka 3 ghante ka Kalanaur site pe, amount=2700.0, employee_name=Kalanaur, transaction_date=2026-10-08, transaction_type=payment) | I75: Missed | J75: record_expense: no entry, no question (route=accounting) · record_expense_payment: no entry, no question (route=accounting) · EXTRA entry: record_employee_transaction Kalanaur 2700.0
A76: F2-EXP-11 | B76: Expense | C76: Mixed | D76: 2 | E76: JCB ka 3 ghante ka 2700 diya Kalanaur site pe | F76: ENTRY | G76: expense_payment(amount=2700, date=T) | H76: ″ | I76: Missed
A77: F2-EXP-11 | B77: Expense | C77: Mixed | D77: 3 | E77: JCB ka 3 ghante ka 2700 diya Kalanaur site pe | F77: ENTRY | G77: (extra entry) | H77: ″ | I77: Silent wrong
A78: F2-EXP-12 | B78: Expense | C78: Mixed | D78: 1 | E78: Petrol 300 ka | F78: ENTRY | G78: expense(category=fuel, amount=300, date=T) | H78: expense(amount=300.0, category=fuel, description=petrol, expense_date=2026-10-08); expense_payment(amount=300.0, description=petrol, payment_date=2026-10-08) | I78: Correct
A79: F2-EXP-12 | B79: Expense | C79: Mixed | D79: 2 | E79: Petrol 300 ka | F79: ENTRY | G79: expense_payment(amount=300, date=T) | H79: ″ | I79: Correct
A80: F2-EXP-13 | B80: Expense | C80: Mixed | D80: 1 | E80: Chai 120 ki | F80: ENTRY | G80: expense(category=misc, amount=120, date=T) | H80: expense(amount=120.0, category=misc, description=Chai, expense_date=2026-10-08); expense_payment(amount=120.0, description=chai, payment_date=2026-10-08) | I80: Correct
A81: F2-EXP-13 | B81: Expense | C81: Mixed | D81: 2 | E81: Chai 120 ki | F81: ENTRY | G81: expense_payment(amount=120, date=T) | H81: ″ | I81: Correct
A82: F2-EXP-14 | B82: Expense | C82: Mixed | D82: 1 | E82: gudam ke taale ki chaabi banwayi, pachaas lage | F82: ENTRY | G82: expense(category=misc, amount=50, date=T) | H82: expense(amount=50.0, category=misc, description=gudam ke taale ki chaabi banwayi, expense_date=2026-10-08); expense_payment(amount=50.0, description=gudam ke taale ki chaabi banwayi, payment_date=2026-10-08) | I82: Correct
A83: F2-EXP-14 | B83: Expense | C83: Mixed | D83: 2 | E83: gudam ke taale ki chaabi banwayi, pachaas lage | F83: ENTRY | G83: expense_payment(amount=50, date=T) | H83: ″ | I83: Correct
A84: F2-EXP-15 | B84: Expense | C84: Mixed | D84: 1 | E84: Diesel 1500 ka aur tyre puncture 200 ka | F84: ENTRY | G84: expense(category=fuel, amount=1500, date=T) | H84: expense(amount=1500.0, category=fuel, description=diesel, expense_date=2026-10-08); expense_payment(amount=1500.0, description=diesel, payment_date=2026-10-08); expense(amount=200.0, category=repair, description=tyre puncture, expense_date=2026-10-08); expense_payment(amount=200.0, description=tyre puncture, payment_date=2026-10-08) | I84: Correct
A85: F2-EXP-15 | B85: Expense | C85: Mixed | D85: 2 | E85: Diesel 1500 ka aur tyre puncture 200 ka | F85: ENTRY | G85: expense_payment(amount=1500, date=T) | H85: ″ | I85: Correct
A86: F2-EXP-15 | B86: Expense | C86: Mixed | D86: 3 | E86: Diesel 1500 ka aur tyre puncture 200 ka | F86: ENTRY | G86: expense(category=repair, amount=200, date=T) | H86: ″ | I86: Correct
A87: F2-EXP-15 | B87: Expense | C87: Mixed | D87: 4 | E87: Diesel 1500 ka aur tyre puncture 200 ka | F87: ENTRY | G87: expense_payment(amount=200, date=T) | H87: ″ | I87: Correct
... A91: F2-FAM-04 | B91: Family | C91: Papa-style | D91: 1 | E91: Beti ki school fees 6500 bhar di | F91: ENTRY | G91: family_transaction(transaction_type=kharcha, amount=6500, date=T, member_name=Beti) | H91: family_transaction(amount=6500.0, purpose=school fees, member_name=Beti, transaction_date=2026-10-08, transaction_type=kharcha) | I91: Correct
A92: F2-FAM-05 | B92: Family | C92: Papa-style | D92: 1 | E92: Ghar ki gas khatam thi, nayi tanki 1050 mein bharwayi | F92: ENTRY | G92: family_transaction(transaction_type=kharcha, amount=1050, date=T) | H92: expense(amount=1050.0, category=fuel, description=nayi tanki, expense_date=2026-10-08); expense_payment(amount=1050.0, description=nayi tanki, payment_date=2026-10-08) | I92: Missed | J92: record_family_transaction: no entry, no question (route=accounting) · EXTRA entry: record_expense 1050.0
A93: F2-FAM-05 | B93: Family | C93: Papa-style | D93: 2 | E93: Ghar ki gas khatam thi, nayi tanki 1050 mein bharwayi | F93: ENTRY | G93: (extra entry) | H93: ″ | I93: Silent wrong
A94: F2-FAM-06 | B94: Family | C94: Papa-style | D94: 1 | E94: chhote ko kitabon ke liye paanch sau pakda diye | F94: ENTRY | G94: family_transaction(transaction_type=kharcha, amount=500, date=T, member_name=Chhote) | H94: family_transaction(amount=500.0, purpose=kitabon ke liye, member_name=chhote, transaction_date=2026-10-08, transaction_type=kharcha) | I94: Correct
A95: F2-FAM-07 | B95: Family | C95: Papa-style | D95: 1 | E95: Papa 2000 le gaye aur Mummy ne 500 wapas rakhe | F95: ENTRY | G95: family_transaction(transaction_type=kharcha, amount=2000, date=T, member_name=Papa) | H95: family_transaction(amount=2000.0, member_name=Papa, transaction_date=2026-10-08, transaction_type=kharcha); family_transaction(amount=500.0, member_name=Mummy, transaction_date=2026-10-08, transaction_type=jama) | I95: Correct
A96: F2-FAM-07 | B96: Family | C96: Papa-style | D96: 2 | E96: Papa 2000 le gaye aur Mummy ne 500 wapas rakhe | F96: ENTRY | G96: family_transaction(transaction_type=jama, amount=500, date=T, member_name=Mummy) | H96: ″ | I96: Correct
A97: F2-FAM-08 | B97: Family | C97: Papa-style | D97: 1 | E97: Diwali pe ghar ki safai karwani hai, 3000 lagenge | F97: NO-ENTRY | G97: (no entry) | H97: family_transaction(note=Diwali pe, amount=3000.0, purpose=ghar ki safai, member_name=Ghar, transaction_date=2026-10-08, transaction_type=kharcha) | I97: Silent wrong | J97: entry made: record_family_transaction
A98: F2-FAM-09 | B98: Family | C98: Mixed | D98: 1 | E98: Mummy 1000 le gayi galle se | F98: ENTRY | G98: family_transaction(transaction_type=kharcha, amount=1000, date=T, member_name=Mummy) | H98: family_transaction(note=le gayi galle se, amount=1000.0, member_name=Mummy, transaction_date=2026-10-08, transaction_type=kharcha) | I98: Correct
A99: F2-FAM-10 | B99: Family | C99: Mixed | D99: 1 | E99: Papa ko 5000 diye mandi ke liye | F99: ENTRY | G99: family_transaction(transaction_type=kharcha, amount=5000, date=T, member_name=Papa) | H99: family_transaction(amount=5000.0, purpose=mandi ke liye, member_name=Papa, transaction_date=2026-10-08, transaction_type=kharcha) | I99: Correct
A100: F2-FAM-11 | B100: Family | C100: Mixed | D100: 1 | E100: Bhai apni jeb se 2000 laya, galle mein daal gaya | F100: ENTRY | G100: family_transaction(transaction_type=jama, amount=2000, date=T, member_name=Bhai) | H100: (no entry) | asked: missing_argument | I100: Safe ask | J100: record_family_transaction: asked missing_argument:record_family_transaction ['amount']
A101: F2-FAM-12 | B101: Family | C101: Mixed | D101: 1 | E101: Beti ko jeb kharch ke 200 diye | F101: ENTRY | G101: family_transaction(transaction_type=kharcha, amount=200, date=T, member_name=Beti) | H101: family_transaction(amount=200.0, member_name=Beti, transaction_date=2026-10-08, transaction_type=kharcha) | I101: Correct
A102: F2-FAM-13 | B102: Family | C102: Mixed | D102: 1 | E102: Mahine bhar ka ghar ka saman 2500 mein aaya | F102: ENTRY | G102: family_transaction(transaction_type=kharcha, amount=2500, date=T) | H102: (no entry) | asked: material_movement, material_movement | I102: Missed | J102: record_family_transaction: no entry, no question (route=accounting)
A103: F2-FAM-14 | B103: Family | C103: Mixed | D103: 1 | E103: mummy ne galle se teen hazaar nikale dawai ke | F103: ENTRY | G103: family_transaction(transaction_type=kharcha, amount=3000, date=T, member_name=Mummy) | H103: family_transaction(amount=3000.0, purpose=dawai, member_name=Mummy, transaction_date=2026-10-08, transaction_type=kharcha) | I103: Correct
A104: F2-FAM-15 | B104: Family | C104: Mixed | D104: 1 | E104: Bhai ne galle se pata nahi kitne nikale | F104: ASK | G104: (no entry) | H104: (no entry) | I104: Missed | J104: no entry, no question (route=accounting)
A105: F2-STK-01 | B105: Stock | C105: Papa-style | D105: 1 | E105: Dhani site se 60 balli gudam aayi | F105: ENTRY | G105: material_movement(item_name=balli, quantity=60, source_name=dhani, destination_name=gudam, date=T) | H105: material_movement(quantity=60.0, item_name=balli, source_name=Dhani site, source_type=site, movement_date=2026-10-08, destination_name=Gudam, destination_type=storage) | asked: material_movement | I105: Correct
A106: F2-STK-02 | B106: Stock | C106: Papa-style | D106: 1 | E106: Gudam se dukaan 30 chaukhat bheji | F106: ENTRY | G106: material_movement(item_name=chaukhat, quantity=30, source_name=gudam, destination_name=shop, date=T) | H106: material_movement(quantity=30.0, item_name=chaukhat, source_name=Gudam, source_type=storage, movement_date=2026-10-08, destination_name=Dukaan, destination_type=storage) | I106: Correct
A107: F2-STK-03 | B107: Stock | C107: Papa-style | D107: 1 | E107: Kalanaur site pe 5 labour lage, chhat utaari | F107: ENTRY | G107: work_log(location_type=site, location_name=kalanaur, labour_count=5, date=T) | H107: work_log(description=chhat utaari, labour_count=5, activity_date=2026-10-08, location_name=Kalanaur, location_type=site) | I107: Correct
...

Sheet Holdout R1
A1: Holdout round 1 — 135 unseen statements (run 2026-10-08 14:40, Hinglish)
A2: Written by the assistant in the owner's business style, locked by the user before the run, never seen by the prompts or the dev test sets (difflib similarity ≤ 0.69). 7 entry bundles × 15 (8 papa-style + 7 mixed) + Report / Correction / Router × 10.
A3: This round was USED for fixing afterwards (7 fix groups, see Changelog), so after the fixes it is no longer unseen. Scorer fix after the run: STK-02 / STK-12 driver_name removed (the movement tool has no driver field).
A4: Test ID | B4: Bundle | C4: Statement type | D4: Event # | E4: Statement (Hinglish) | F4: Expected outcome | G4: Expected entry / route | H4: Actual (system output) | I4: Result | J4: Remark (scorer)
A5: FIN-EMP-01 | B5: Employee | C5: Papa-style | D5: 1 | E5: Bhupender ko aaj ki dihadi 600 de di | F5: ENTRY | G5: employee_transaction(employee_name=Bhupender, transaction_type=payment, amount=600, date=T) | H5: employee_transaction(note=aaj ki dihadi, amount=600.0, employee_name=Bhupender, transaction_date=2026-10-08, transaction_type=payment) | I5: Correct
A6: FIN-EMP-02 | B6: Employee | C6: Papa-style | D6: 1 | E6: Kitanu aaj trolley lekar do chakkar Kalanaur gaya | F6: ENTRY | G6: attendance(employee_name=Kitanu, attendance=P, driving=P, date=T) | H6: (no entry) | asked: material_movement, material_movement | I6: Missed | J6: record_attendance: no entry, no question (route=accounting)
A7: FIN-EMP-03 | B7: Employee | C7: Papa-style | D7: 1 | E7: Sohan ne Dhani wali site pe chaukhat nikalne ka 800 ka kaam kiya | F7: ENTRY | G7: employee_transaction(employee_name=Sohan, transaction_type=work, amount=800, date=T) | H7: employee_transaction(note=Dhani wali site pe chaukhat nikalne ka, amount=800.0, employee_name=Sohan, transaction_date=2026-10-08, transaction_type=work) | I7: Correct
A8: FIN-EMP-04 | B8: Employee | C8: Papa-style | D8: 1 | E8: Ram aaj dopahar baad aaya, aadha din | F8: ENTRY | G8: attendance(employee_name=Ram, attendance=half, date=T) | H8: (no entry) | asked: missing_argument | I8: Safe ask | J8: record_attendance: asked missing_argument:record_employee_transaction ['amount']
A9: FIN-EMP-05 | B9: Employee | C9: Papa-style | D9: 1 | E9: Mahavir mistri ko 2000 advance diye, agle hafte se kaam pe aayega | F9: ENTRY | G9: employee_transaction(employee_name=Mahavir, transaction_type=payment, amount=2000, date=T) | H9: employee_transaction(note=advance, amount=2000.0, employee_name=Mahavir mistri, transaction_date=2026-10-08, transaction_type=payment) | I9: Correct
A10: FIN-EMP-06 | B10: Employee | C10: Papa-style | D10: 1 | E10: Sohan aur Ram dono ne aaj girder katai ki, 500-500 banta hai | F10: ENTRY | G10: employee_transaction(employee_name=Sohan, transaction_type=work, amount=500, date=T) | H10: employee_transaction(amount=500.0, employee_name=Sohan, transaction_date=2026-10-08, transaction_type=payment); employee_transaction(amount=500.0, employee_name=Ram, transaction_date=2026-10-08, transaction_type=payment) | I10: Silent wrong | J10: record_employee_transaction: transaction_type payment≠work · record_employee_transaction: transaction_type payment≠work
A11: FIN-EMP-06 | B11: Employee | C11: Papa-style | D11: 2 | E11: Sohan aur Ram dono ne aaj girder katai ki, 500-500 banta hai | F11: ENTRY | G11: employee_transaction(employee_name=Ram, transaction_type=work, amount=500, date=T) | H11: ″ | I11: Silent wrong
A12: FIN-EMP-07 | B12: Employee | C12: Papa-style | D12: 1 | E12: Kitanu kal chutti pe tha | F12: ENTRY | G12: attendance(employee_name=Kitanu, attendance=absent, date=T-1) | H12: attendance(note=chutti pe tha, driving=absent, attendance=absent, employee_name=Kitanu, attendance_date=2026-10-07) | I12: Correct
A13: FIN-EMP-08 | B13: Employee | C13: Papa-style | D13: 1 | E13: Bhupender ke purane hisab ke 1500 dene baaki hain | F13: ENTRY | G13: opening_balance(party_name=Bhupender, amount=1500, direction=dena) | H13: opening_balance(note=purane hisab ke dene baaki hain, amount=1500.0, direction=dena, as_of_date=2026-10-08, party_name=Bhupender, party_type=employee) | I13: Correct
A14: FIN-EMP-09 | B14: Employee | C14: Mixed | D14: 1 | E14: Sohan ko 300 kharchi di | F14: ENTRY | G14: employee_transaction(employee_name=Sohan, transaction_type=payment, amount=300, date=T) | H14: employee_transaction(note=kharchi di, amount=300.0, employee_name=Sohan, transaction_date=2026-10-08, transaction_type=payment) | I14: Correct
A15: FIN-EMP-10 | B15: Employee | C15: Mixed | D15: 1 | E15: Ram subah saat baje hi pahunch gaya tha aaj | F15: ENTRY | G15: attendance(employee_name=Ram, attendance=P, date=T) | H15: attendance(note=subah saat baje hi pahunch gaya tha, driving=absent, attendance=P, employee_name=Ram, attendance_date=2026-10-08) | I15: Correct
A16: FIN-EMP-11 | B16: Employee | C16: Mixed | D16: 1 | E16: ram ko kal 5 sau diye the uske baad aaj 2 sau aur | F16: ENTRY | G16: employee_transaction(employee_name=Ram, transaction_type=payment, amount=500, date=T-1) | H16: employee_transaction(amount=500.0, employee_name=Ram, transaction_date=2026-10-07, transaction_type=payment); employee_transaction(amount=200.0, employee_name=Ram, transaction_date=2026-10-08, transaction_type=payment) | I16: Correct
A17: FIN-EMP-11 | B17: Employee | C17: Mixed | D17: 2 | E17: ram ko kal 5 sau diye the uske baad aaj 2 sau aur | F17: ENTRY | G17: employee_transaction(employee_name=Ram, transaction_type=payment, amount=200, date=T) | H17: ″ | I17: Correct
A18: FIN-EMP-12 | B18: Employee | C18: Mixed | D18: 1 | E18: Mahavir ka number 9812233445 hai, mistri hai wo | F18: ENTRY | G18: manage_employee(employee_name=Mahavir) | H18: manage_employee(role=mistri, phone=9812233445, employee_name=Mahavir) | I18: Correct
A19: FIN-EMP-13 | B19: Employee | C19: Mixed | D19: 1 | E19: Mahavir ka hisab chuka diya | F19: ASK | G19: employee_transaction(employee_name=Mahavir, transaction_type=payment, date=T) | H19: (no entry) | asked: missing_argument | I19: Correct | J19: record_employee_transaction: asked missing_argument:record_employee_transaction ['amount']
A20: FIN-EMP-14 | B20: Employee | C20: Mixed | D20: 1 | E20: Ram aaj aaya, 650 ka kaam kiya aur 400 le gaya | F20: ENTRY | G20: attendance(employee_name=Ram, attendance=P, date=T) | H20: attendance(driving=absent, attendance=P, employee_name=Ram, attendance_date=2026-10-08); employee_transaction(amount=650.0, employee_name=Ram, transaction_date=2026-10-08, transaction_type=work); employee_transaction(amount=400.0, employee_name=Ram, transaction_date=2026-10-08, transaction_type=payment) | I20: Correct
A21: FIN-EMP-14 | B21: Employee | C21: Mixed | D21: 2 | E21: Ram aaj aaya, 650 ka kaam kiya aur 400 le gaya | F21: ENTRY | G21: employee_transaction(employee_name=Ram, transaction_type=work, amount=650, date=T) | H21: ″ | I21: Correct
A22: FIN-EMP-14 | B22: Employee | C22: Mixed | D22: 3 | E22: Ram aaj aaya, 650 ka kaam kiya aur 400 le gaya | F22: ENTRY | G22: employee_transaction(employee_name=Ram, transaction_type=payment, amount=400, date=T) | H22: ″ | I22: Correct
A23: FIN-EMP-15 | B23: Employee | C23: Mixed | D23: 1 | E23: Agle somvar Bhupender ka 700 ka hisab karna hai | F23: NO-ENTRY | G23: (no entry) | H23: (no entry) | I23: Correct
A24: FIN-CUS-01 | B24: Customer | C24: Papa-style | D24: 1 | E24: Rajbir ko 1500 purani eent di, 4 rupaye wali, Gudam se | F24: ENTRY | G24: sale_transaction(customer_name=Rajbir, item_name=eent, quantity=1500, rate=4, amount=6000, source=gudam, date=T) | H24: sale_transaction(rate=4.0, amount=6000.0, quantity=1500.0, item_name=purani eent, sale_date=2026-10-08, customer_name=Rajbir, update_inventory=True) | asked: material_movement, material_movement | I24: Silent wrong | J24: record_sale_transaction: source ≠gudam
A25: FIN-CUS-02 | B25: Customer | C25: Papa-style | D25: 1 | E25: Sharma ji 3 purane darwaze le gaye 4500 ke | F25: ENTRY | G25: sale_transaction(customer_name=Sharma ji, item_name=darwaza, quantity=3, amount=4500, date=T) | H25: sale_transaction(note=purane, unit=piece, amount=4500.0, quantity=3.0, item_name=darwaze, sale_date=2026-10-08, customer_name=Sharma ji, update_inventory=True) | asked: material_movement | I25: Correct
A26: FIN-CUS-03 | B26: Customer | C26: Papa-style | D26: 1 | E26: Rajbir ne 3000 de diye baaki baad mein dega | F26: ENTRY | G26: sale_payment(customer_name=Rajbir, amount=3000, date=T) | H26: sale_payment(amount=3000.0, payment_date=2026-10-08, customer_name=Rajbir) | I26: Correct
A27: FIN-CUS-04 | B27: Customer | C27: Papa-style | D27: 1 | E27: Dukaan se 2 chaukhat Satbir ko becha 1800 mein, cash mil gaya | F27: ENTRY | G27: sale_transaction(customer_name=Satbir, item_name=chaukhat, quantity=2, amount=1800, source=shop, date=T) | H27: sale_transaction(unit=piece, amount=1800.0, source=Dukaan, quantity=2.0, item_name=chaukhat, sale_date=2026-10-08, customer_name=Satbir, update_inventory=True); sale_payment(note=cash mil gaya, amount=1800.0, payment_date=2026-10-08, customer_name=Satbir) | asked: material_movement | I27: Correct
A28: FIN-CUS-04 | B28: Customer | C28: Papa-style | D28: 2 | E28: Dukaan se 2 chaukhat Satbir ko becha 1800 mein, cash mil gaya | F28: ENTRY | G28: sale_payment(customer_name=Satbir, amount=1800, date=T) | H28: ″ | I28: Correct
A29: FIN-CUS-05 | B29: Customer | C29: Papa-style | D29: 1 | E29: Suresh Traders ko 2 quintal sariya 9000 ka, udhaar | F29: ENTRY | G29: sale_transaction(customer_name=Suresh Traders, item_name=sariya, quantity=2, unit=quintal, amount=9000, date=T) | H29: sale_transaction(note=udhaar, rate=45.0, unit=kg, amount=9000.0, quantity=200.0, item_name=sariya, sale_date=2026-10-08, customer_name=Suresh Traders, supplier_name=Suresh Traders, update_inventory=True) | I29: Correct
A30: FIN-CUS-06 | B30: Customer | C30: Papa-style | D30: 1 | E30: Kitanu trolley mein 800 eent Satbir ke yahan chhod aaya, 5 ka rate | F30: ENTRY | G30: sale_transaction(customer_name=Satbir, item_name=eent, quantity=800, rate=5, amount=4000, driver_name=Kitanu, date=T) | H30: sale_transaction(note=chhod aaya, rate=5.0, unit=trolley, amount=4000.0, quantity=800.0, item_name=eent, sale_date=2026-10-08, customer_name=Satbir, update_inventory=True) | asked: material_movement, material_movement | I30: Silent wrong | J30: record_sale_transaction: driver_name ≠Kitanu
A31: FIN-CUS-07 | B31: Customer | C31: Papa-style | D31: 1 | E31: Rajbir pe pichle saal ke 7000 baaki hain | F31: ENTRY | G31: opening_balance(party_name=Rajbir, amount=7000, direction=lena) | H31: opening_balance(note=pichle saal ke, amount=7000.0, direction=lena, as_of_date=2026-10-08, party_name=Rajbir, party_type=customer) | I31: Correct
A32: FIN-CUS-08 | B32: Customer | C32: Papa-style | D32: 1 | E32: Gudam se ek purani lakdi ki almari Mohan ji ko 3500 ki di, 2000 abhi diye | F32: ENTRY | G32: sale_transaction(customer_name=Mohan ji, item_name=almari, quantity=1, amount=3500, source=gudam, date=T) | H32: sale_transaction(note=2000 abhi diye, amount=3500.0, source=Gudam, item_name=lakdi ki almari, sale_date=2026-10-08, customer_name=Mohan ji, update_inventory=True); sale_payment(note=abhi diye, amount=2000.0, payment_date=2026-10-08, customer_name=Mohan ji) | asked: material_movement | I32: Silent wrong | J32: record_sale_transaction: quantity 0.0≠1
A33: FIN-CUS-08 | B33: Customer | C33: Papa-style | D33: 2 | E33: Gudam se ek purani lakdi ki almari Mohan ji ko 3500 ki di, 2000 abhi diye | F33: ENTRY | G33: sale_payment(customer_name=Mohan ji, amount=2000, date=T) | H33: ″ | I33: Correct
A34: FIN-CUS-09 | B34: Customer | C34: Mixed | D34: 1 | E34: Satbir se aaj 2500 aa gaye | F34: ENTRY | G34: sale_payment(customer_name=Satbir, amount=2500, date=T) | H34: sale_payment(amount=2500.0, payment_date=2026-10-08, customer_name=Satbir) | I34: Correct
A35: FIN-CUS-10 | B35: Customer | C35: Mixed | D35: 1 | E35: Suresh Traders ne 2000 online bheje | F35: ENTRY | G35: sale_payment(customer_name=Suresh Traders, amount=2000, date=T) | H35: sale_payment(amount=2000.0, payment_date=2026-10-08, customer_name=Suresh Traders) | I35: Correct
A36: FIN-CUS-11 | B36: Customer | C36: Mixed | D36: 1 | E36: satbir ko dedh sau eent saade chaar ke bhaav | F36: ENTRY | G36: sale_transaction(customer_name=Satbir, item_name=eent, quantity=150, rate=4.5, amount=675, date=T) | H36: sale_transaction(rate=4.0, unit=piece, amount=600.0, quantity=150.0, item_name=eent, sale_date=2026-10-08, customer_name=satbir, update_inventory=True) | asked: material_movement, material_movement | I36: Silent wrong | J36: record_sale_transaction: amount 600.0≠675; rate 4.0≠4.5
A37: FIN-CUS-12 | B37: Customer | C37: Mixed | D37: 1 | E37: Rajbir ka mobile 9416012345, Bhiwani bus adde ke paas dukaan hai | F37: ENTRY | G37: manage_customer(customer_name=Rajbir) | H37: (no entry) | I37: Missed | J37: manage_customer: no entry, no question (route=accounting)
A38: FIN-CUS-13 | B38: Customer | C38: Mixed | D38: 1 | E38: Mohan ji ko 4 khidki de di | F38: ASK | G38: sale_transaction(customer_name=Mohan ji, item_name=khidki, quantity=4, date=T) | H38: (no entry) | asked: material_movement, material_movement, missing_argument | I38: Correct | J38: record_sale_transaction: asked missing_argument:record_sale_transaction ['amount']
A39: FIN-CUS-14 | B39: Customer | C39: Mixed | D39: 1 | E39: Sharma ji ko 1000 eent 5500 ki gayi, Kitanu chhod ke aaya, 3000 haath mein diye | F39: ENTRY | G39: sale_transaction(customer_name=Sharma ji, item_name=eent, quantity=1000, amount=5500, driver_name=Kitanu, date=T) | H39: sale_transaction(amount=5500.0, quantity=1000.0, item_name=eent, sale_date=2026-10-08, customer_name=Sharma ji, update_inventory=True); employee_transaction(amount=3000.0, employee_name=Kitanu, payment_method=cash, transaction_date=2026-10-08, transaction_type=payment) | asked: material_movement | I39: Silent wrong | J39: record_sale_transaction: driver_name ≠Kitanu · record_sale_payment: no entry, no question (route=accounting) · EXTRA entry: record_employee_transaction Kitanu 3000.0
A40: FIN-CUS-14 | B40: Customer | C40: Mixed | D40: 2 | E40: Sharma ji ko 1000 eent 5500 ki gayi, Kitanu chhod ke aaya, 3000 haath mein diye | F40: ENTRY | G40: sale_payment(customer_name=Sharma ji, amount=3000, date=T) | H40: ″ | I40: Missed
A41: FIN-CUS-14 | B41: Customer | C41: Mixed | D41: 3 | E41: Sharma ji ko 1000 eent 5500 ki gayi, Kitanu chhod ke aaya, 3000 haath mein diye | F41: ENTRY | G41: (extra entry) | H41: ″ | I41: Silent wrong
A42: FIN-CUS-15 | B42: Customer | C42: Mixed | D42: 1 | E42: Rajbir agle hafte 3 girder lene aayega, 12000 bataye hain | F42: NO-ENTRY | G42: (no entry) | H42: (no entry) | I42: Correct
A43: FIN-SUP-01 | B43: Supplier | C43: Papa-style | D43: 1 | E43: SBI wala truck 3000 nayi eent Gudam utaar gaya, saat ka rate | F43: ENTRY | G43: supplier_transaction(supplier_name=SBI Bhatta, item_name=eent, quantity=3000, rate=7, amount=21000, destination_location=gudam, date=T) | H43: supplier_transaction(rate=7.0, amount=21000.0, quantity=3000.0, item_name=nayi eent, supplier_name=SBI wala truck, transaction_date=2026-10-08, destination_location=Gudam) | asked: material_movement | I43: Correct
A44: FIN-SUP-02 | B44: Supplier | C44: Papa-style | D44: 1 | E44: Gill saw mill se 20 shahteer aaye 16000 ke, dukaan pe utre | F44: ENTRY | G44: supplier_transaction(supplier_name=Gill saw mill, item_name=shahteer, quantity=20, amount=16000, destination_location=shop, date=T) | H44: supplier_transaction(amount=16000.0, quantity=20.0, item_name=shahteer, supplier_name=Gill saw mill, transaction_date=2026-10-08, destination_location=Dukaan) | asked: material_movement | I44: Correct
A45: FIN-SUP-03 | B45: Supplier | C45: Papa-style | D45: 1 | E45: SBI Bhatta ka 10 hazaar ka hisab chuka diya aaj | F45: ENTRY | G45: supplier_payment(supplier_name=SBI Bhatta, amount=10000, date=T) | H45: supplier_payment(note=ka hisab chuka diya, amount=10000.0, payment_date=2026-10-08, supplier_name=SBI Bhatta) | I45: Correct
A46: FIN-SUP-04 | B46: Supplier | C46: Papa-style | D46: 1 | E46: Jindal steel wale se 5 quintal sariya liya 26000 ka, aadha diya | F46: ENTRY | G46: supplier_transaction(supplier_name=Jindal steel, item_name=sariya, quantity=5, unit=quintal, amount=26000, date=T) | H46: supplier_transaction(note=aadha diya, unit=kg, amount=26000.0, quantity=500.0, item_name=sariya, supplier_name=Jindal, transaction_date=2026-10-08); supplier_payment(note=aadha diya, amount=13000.0, payment_date=2026-10-08, supplier_name=Jindal) | asked: material_movement, material_movement | I46: Correct
A47: FIN-SUP-04 | B47: Supplier | C47: Papa-style | D47: 2 | E47: Jindal steel wale se 5 quintal sariya liya 26000 ka, aadha diya | F47: ENTRY | G47: supplier_payment(supplier_name=Jindal steel, amount=13000, date=T) | H47: ″ | I47: Correct
A48: FIN-SUP-05 | B48: Supplier | C48: Papa-style | D48: 1 | E48: Gill saw mill wale ko 8000 PhonePe kiye | F48: ENTRY | G48: supplier_payment(supplier_name=Gill saw mill, amount=8000, date=T) | H48: supplier_payment(amount=8000.0, payment_date=2026-10-08, supplier_name=Gill saw) | I48: Correct
A49: FIN-SUP-06 | B49: Supplier | C49: Papa-style | D49: 1 | E49: Bhatte se 2 trolley rodi aayi, 4500 ki ek, site Haluwas pe | F49: ENTRY | G49: supplier_transaction(supplier_name=SBI Bhatta, item_name=rodi, quantity=2, unit=trolley, rate=4500, amount=9000, destination_location=haluwas, date=T) | H49: (no entry) | asked: material_movement | I49: Missed | J49: record_supplier_transaction: asked material_movement:LOCATION_TYPE_CONFIRMATION
A50: FIN-SUP-07 | B50: Supplier | C50: Papa-style | D50: 1 | E50: Jindal steel ke 12000 pehle ke dene baaki hain | F50: ENTRY | G50: opening_balance(party_name=Jindal steel, amount=12000, direction=dena) | H50: opening_balance(note=pehle ke dene baaki hain, amount=12000.0, direction=dena, as_of_date=2026-10-08, party_name=Jindal steel, party_type=supplier) | I50: Correct
A51: FIN-SUP-08 | B51: Supplier | C51: Papa-style | D51: 1 | E51: 300 eent tooti nikli thi, SBI Bhatte ko lauta di | F51: ENTRY | G51: supplier_transaction(supplier_name=SBI Bhatta, item_name=eent, quantity=-300, date=T) | H51: (no entry) | asked: missing_argument | I51: Safe ask | J51: record_supplier_transaction: asked missing_argument:record_supplier_payment ['amount']
A52: FIN-SUP-09 | B52: Supplier | C52: Mixed | D52: 1 | E52: Dukaan pe SBI ki 1500 eent utri, 10500 ka bill | F52: ENTRY | G52: supplier_transaction(supplier_name=SBI Bhatta, item_name=eent, quantity=1500, amount=10500, destination_location=shop, date=T) | H52: expense(note=Dukaan pe, amount=10500.0, category=misc, description=bill, expense_date=2026-10-08); expense_payment(amount=10500.0, description=bill, payment_date=2026-10-08) | asked: material_movement | I52: Missed | J52: record_supplier_transaction: no entry, no question (route=accounting) · EXTRA entry: record_expense 10500.0
A53: FIN-SUP-09 | B53: Supplier | C53: Mixed | D53: 2 | E53: Dukaan pe SBI ki 1500 eent utri, 10500 ka bill | F53: ENTRY | G53: (extra entry) | H53: ″ | I53: Silent wrong
A54: FIN-SUP-10 | B54: Supplier | C54: Mixed | D54: 1 | E54: Gill wale ko paanch hazaar nakad pakdaye | F54: ENTRY | G54: supplier_payment(supplier_name=Gill saw mill, amount=5000, date=T) | H54: supplier_payment(note=nakad pakdaye, amount=5000.0, payment_date=2026-10-08, supplier_name=Gill) | I54: Correct
A55: FIN-SUP-11 | B55: Supplier | C55: Mixed | D55: 1 | E55: jindal wale se dhai quintal sariya aaya, 52 rupaye kilo, gudam mein | F55: ENTRY | G55: supplier_transaction(supplier_name=Jindal steel, item_name=sariya, quantity=250, unit=kg, amount=13000, destination_location=gudam, date=T) | H55: supplier_transaction(rate=52.0, unit=kg, amount=13000.0, quantity=250.0, item_name=sariya, supplier_name=jindal, transaction_date=2026-10-08, destination_location=Gudam) | asked: material_movement | I55: Correct
A56: FIN-SUP-12 | B56: Supplier | C56: Mixed | D56: 1 | E56: Gill saw mill Charkhi Dadri road pe hai, number 9896011223 | F56: ENTRY | G56: manage_supplier(supplier_name=Gill saw mill) | H56: (no entry) | I56: Missed | J56: manage_supplier: no entry, no question (route=accounting)
A57: FIN-SUP-13 | B57: Supplier | C57: Mixed | D57: 1 | E57: Jindal steel se sariya aa gaya, bill baad mein aayega | F57: ASK | G57: supplier_transaction(supplier_name=Jindal steel, item_name=sariya, date=T) | H57: supplier_transaction(note=bill baad mein aayega, item_name=sariya, supplier_name=Jindal steel, transaction_date=2026-10-08) | asked: material_movement, material_movement | I57: Silent wrong | J57: record_supplier_transaction: recorded instead of asking (values guessed)
A58: FIN-SUP-14 | B58: Supplier | C58: Mixed | D58: 1 | E58: Jindal steel se 3 quintal sariya 15600 ka gudam aaya, 10000 diye, Kitanu trolley laya | F58: ENTRY | G58: supplier_transaction(supplier_name=Jindal steel, item_name=sariya, quantity=3, unit=quintal, amount=15600, destination_location=gudam, driver_name=Kitanu, date=T) | H58: supplier_transaction(unit=kg, amount=15600.0, quantity=300.0, item_name=sariya, supplier_name=Jindal steel, transaction_date=2026-10-08, destination_location=Gudam) | asked: material_movement | I58: Silent wrong | J58: record_supplier_transaction: driver_name ≠Kitanu · record_supplier_payment: no entry, no question (route=accounting)
A59: FIN-SUP-14 | B59: Supplier | C59: Mixed | D59: 2 | E59: Jindal steel se 3 quintal sariya 15600 ka gudam aaya, 10000 diye, Kitanu trolley laya | F59: ENTRY | G59: supplier_payment(supplier_name=Jindal steel, amount=10000, date=T) | H59: ″ | I59: Missed
A60: FIN-SUP-15 | B60: Supplier | C60: Mixed | D60: 1 | E60: Gill saw mill wale bol rahe the agle mahine shahteer mehenga hoga | F60: NO-ENTRY | G60: (no entry) | H60: (no entry) | I60: Correct
A61: FIN-EXP-01 | B61: Expense | C61: Papa-style | D61: 1 | E61: Kalanaur nikalne se pehle tractor mein 2500 ka tel daala | F61: ENTRY | G61: expense(category=fuel, amount=2500, date=T) | H61: expense(note=Kalanaur nikalne se pehle, amount=2500.0, category=fuel, description=tel, expense_date=2026-10-07); expense_payment(note=Kalanaur nikalne se pehle tractor mein daala, amount=2500.0, description=tel, payment_date=2026-10-07) | I61: Silent wrong | J61: record_expense: date 2026-10-07≠2026-10-08 · record_expense_payment: date 2026-10-07≠2026-10-08
A62: FIN-EXP-01 | B62: Expense | C62: Papa-style | D62: 2 | E62: Kalanaur nikalne se pehle tractor mein 2500 ka tel daala | F62: ENTRY | G62: expense_payment(amount=2500, date=T) | H62: ″ | I62: Silent wrong
A63: FIN-EXP-02 | B63: Expense | C63: Papa-style | D63: 1 | E63: Gas cutter ka cylinder bharwaya 1100 laga | F63: ENTRY | G63: expense(category=fuel, amount=1100, date=T) | H63: family_transaction(amount=1100.0, purpose=cylinder bharwaya, member_name=Ghar, transaction_date=2026-10-08, transaction_type=kharcha) | I63: Missed | J63: record_expense: no entry, no question (route=accounting) · record_expense_payment: no entry, no question (route=accounting) · EXTRA entry: record_family_transaction Ghar 1100.0
A64: FIN-EXP-02 | B64: Expense | C64: Papa-style | D64: 2 | E64: Gas cutter ka cylinder bharwaya 1100 laga | F64: ENTRY | G64: expense_payment(amount=1100, date=T) | H64: ″ | I64: Missed
A65: FIN-EXP-02 | B65: Expense | C65: Papa-style | D65: 3 | E65: Gas cutter ka cylinder bharwaya 1100 laga | F65: ENTRY | G65: (extra entry) | H65: ″ | I65: Silent wrong
A66: FIN-EXP-03 | B66: Expense | C66: Papa-style | D66: 1 | E66: JCB 3 ghante chali Haluwas site pe, 3600 de diye | F66: ENTRY | G66: expense(category=rent, amount=3600, date=T) | H66: work_log(note=3 ghante, description=JCB chali, activity_date=2026-10-08, location_name=Haluwas, location_type=site) | I66: Missed | J66: record_expense: no entry, no question (route=accounting) · record_expense_payment: no entry, no question (route=accounting) · EXTRA entry: record_work_log
A67: FIN-EXP-03 | B67: Expense | C67: Papa-style | D67: 2 | E67: JCB 3 ghante chali Haluwas site pe, 3600 de diye | F67: ENTRY | G67: expense_payment(amount=3600, date=T) | H67: ″ | I67: Missed
A68: FIN-EXP-03 | B68: Expense | C68: Papa-style | D68: 3 | E68: JCB 3 ghante chali Haluwas site pe, 3600 de diye | F68: ENTRY | G68: (extra entry) | H68: ″ | I68: Silent wrong
A69: FIN-EXP-04 | B69: Expense | C69: Papa-style | D69: 1 | E69: Bijli wale ko gudam ke meter ke 2300 de aaye | F69: ENTRY | G69: expense(category=misc, amount=2300, date=T) | H69: (no entry) | asked: material_movement | I69: Missed | J69: record_expense: no entry, no question (route=accounting) · record_expense_payment: no entry, no question (route=accounting)
A70: FIN-EXP-04 | B70: Expense | C70: Papa-style | D70: 2 | E70: Bijli wale ko gudam ke meter ke 2300 de aaye | F70: ENTRY | G70: expense_payment(amount=2300, date=T) | H70: ″ | I70: Missed
A71: FIN-EXP-05 | B71: Expense | C71: Papa-style | D71: 1 | E71: Trolley pankchar ho gayi thi raste mein, 150 ka lagwaya | F71: ENTRY | G71: expense(category=repair, amount=150, date=T) | H71: expense(note=raste mein lagwaya, amount=150.0, category=misc, description=trolley pankchar, expense_date=2026-10-08); expense_payment(note=raste mein, amount=150.0, description=trolley pankchar, payment_date=2026-10-08) | I71: Silent wrong | J71: record_expense: category misc≠repair; category misc≠repair
A72: FIN-EXP-05 | B72: Expense | C72: Papa-style | D72: 2 | E72: Trolley pankchar ho gayi thi raste mein, 150 ka lagwaya | F72: ENTRY | G72: expense_payment(amount=150, date=T) | H72: ″ | I72: Correct
A73: FIN-EXP-06 | B73: Expense | C73: Papa-style | D73: 1 | E73: Is mahine ki dukaan ki 6000 kiraye ki rakam baad mein denge | F73: ENTRY | G73: expense(category=rent, amount=6000, date=T) | H73: (no entry) | I73: Missed | J73: record_expense: no entry, no question (route=accounting)
A74: FIN-EXP-07 | B74: Expense | C74: Papa-style | D74: 1 | E74: Labour ko dopahar mein samose khilaye 240 ke | F74: ENTRY | G74: expense(category=misc, amount=240, date=T) | H74: expense(note=Labour ko dopahar mein, amount=240.0, category=misc, description=samose khilaye, expense_date=2026-10-08); expense_payment(note=dopahar mein, amount=240.0, description=samose, payment_date=2026-10-08) | I74: Correct
A75: FIN-EXP-07 | B75: Expense | C75: Papa-style | D75: 2 | E75: Labour ko dopahar mein samose khilaye 240 ke | F75: ENTRY | G75: expense_payment(amount=240, date=T) | H75: ″ | I75: Correct
A76: FIN-EXP-08 | B76: Expense | C76: Papa-style | D76: 1 | E76: Cutter machine theek karwayi, 850 ka kharcha | F76: ENTRY | G76: expense(category=repair, amount=850, date=T) | H76: expense(amount=850.0, category=repair, description=cutter machine theek karwayi, expense_date=2026-10-08); expense_payment(amount=850.0, description=cutter machine theek karwayi, payment_date=2026-10-08) | I76: Correct
A77: FIN-EXP-08 | B77: Expense | C77: Papa-style | D77: 2 | E77: Cutter machine theek karwayi, 850 ka kharcha | F77: ENTRY | G77: expense_payment(amount=850, date=T) | H77: ″ | I77: Correct
A78: FIN-EXP-09 | B78: Expense | C78: Mixed | D78: 1 | E78: Aaj 500 ka petrol bike mein | F78: ENTRY | G78: expense(category=fuel, amount=500, date=T) | H78: expense(note=bike mein bhara, amount=500.0, category=fuel, description=petrol, expense_date=2026-10-08); expense_payment(note=bike mein bhara, amount=500.0, description=petrol, payment_date=2026-10-08) | I78: Correct
A79: FIN-EXP-09 | B79: Expense | C79: Mixed | D79: 2 | E79: Aaj 500 ka petrol bike mein | F79: ENTRY | G79: expense_payment(amount=500, date=T) | H79: ″ | I79: Correct
A80: FIN-EXP-10 | B80: Expense | C80: Mixed | D80: 1 | E80: Phone recharge 299 ka karwaya | F80: ENTRY | G80: expense(category=misc, amount=299, date=T) | H80: expense(amount=299.0, category=misc, description=phone recharge, expense_date=2026-10-08); expense_payment(amount=299.0, description=phone recharge, payment_date=2026-10-08) | I80: Correct
A81: FIN-EXP-10 | B81: Expense | C81: Mixed | D81: 2 | E81: Phone recharge 299 ka karwaya | F81: ENTRY | G81: expense_payment(amount=299, date=T) | H81: ″ | I81: Correct
A82: FIN-EXP-11 | B82: Expense | C82: Mixed | D82: 1 | E82: dhai sau ki rassi aur taala laaye gudam ke liye | F82: ENTRY | G82: expense(category=misc, amount=250, date=T) | H82: (no entry) | asked: material_movement | I82: Missed | J82: record_expense: no entry, no question (route=accounting) · record_expense_payment: no entry, no question (route=accounting)
A83: FIN-EXP-11 | B83: Expense | C83: Mixed | D83: 2 | E83: dhai sau ki rassi aur taala laaye gudam ke liye | F83: ENTRY | G83: expense_payment(amount=250, date=T) | H83: ″ | I83: Missed
A84: FIN-EXP-12 | B84: Expense | C84: Mixed | D84: 1 | E84: JCB wale ke purane 1800 aaj chuka diye | F84: ENTRY | G84: expense_payment(amount=1800, date=T) | H84: employee_transaction(note=purane, amount=1800.0, employee_name=JCB, transaction_date=2026-10-08, transaction_type=payment) | I84: Missed | J84: record_expense_payment: no entry, no question (route=accounting) · EXTRA entry: record_employee_transaction JCB 1800.0
A85: FIN-EXP-12 | B85: Expense | C85: Mixed | D85: 2 | E85: JCB wale ke purane 1800 aaj chuka diye | F85: ENTRY | G85: (extra entry) | H85: ″ | I85: Silent wrong
A86: FIN-EXP-13 | B86: Expense | C86: Mixed | D86: 1 | E86: Tractor ki service karwa li | F86: ASK | G86: (no entry) | H86: (no entry) | asked: missing_argument | I86: Correct | J86: asked/stopped: missing_argument: record_expense ['amount']
A87: FIN-EXP-14 | B87: Expense | C87: Mixed | D87: 1 | E87: Diesel 2000 ka, tyre 1500 ka badalwaya, aur 100 ki chai | F87: ENTRY | G87: expense(category=fuel, amount=2000, date=T) | H87: expense(amount=2000.0, category=repair, description=diesel, expense_date=2026-10-08); expense_payment(amount=2000.0, description=diesel, payment_date=2026-10-08); expense(amount=1500.0, category=repair, description=Tyre badalwaya, expense_date=2026-10-08); expense_payment(amount=1500.0, description=Tyre, payment_date=2026-10-08); expense(amount=100.0, category=misc, description=Chai, expense_date=2026-10-08); expense_payment(amount=100.0, description=chai, payment_date=2026-10-08) | I87: Silent wrong | J87: record_expense: category repair≠fuel; category repair≠fuel
A88: FIN-EXP-14 | B88: Expense | C88: Mixed | D88: 2 | E88: Diesel 2000 ka, tyre 1500 ka badalwaya, aur 100 ki chai | F88: ENTRY | G88: expense_payment(amount=2000, date=T) | H88: ″ | I88: Correct
A89: FIN-EXP-14 | B89: Expense | C89: Mixed | D89: 3 | E89: Diesel 2000 ka, tyre 1500 ka badalwaya, aur 100 ki chai | F89: ENTRY | G89: expense(category=repair, amount=1500, date=T) | H89: ″ | I89: Correct
A90: FIN-EXP-14 | B90: Expense | C90: Mixed | D90: 4 | E90: Diesel 2000 ka, tyre 1500 ka badalwaya, aur 100 ki chai | F90: ENTRY | G90: expense_payment(amount=1500, date=T) | H90: ″ | I90: Correct
A91: FIN-EXP-14 | B91: Expense | C91: Mixed | D91: 5 | E91: Diesel 2000 ka, tyre 1500 ka badalwaya, aur 100 ki chai | F91: ENTRY | G91: expense(category=misc, amount=100, date=T) | H91: ″ | I91: Correct
A92: FIN-EXP-14 | B92: Expense | C92: Mixed | D92: 6 | E92: Diesel 2000 ka, tyre 1500 ka badalwaya, aur 100 ki chai | F92: ENTRY | G92: expense_payment(amount=100, date=T) | H92: ″ | I92: Correct
A93: FIN-EXP-15 | B93: Expense | C93: Mixed | D93: 1 | E93: Kal gudam ki bijli wala aayega, 3000 lagenge shayad | F93: NO-ENTRY | G93: (no entry) | H93: (no entry) | I93: Correct
A94: FIN-FAM-01 | B94: Family | C94: Papa-style | D94: 1 | E94: Mummy ne ghar ke kharche ke liye 3000 maange the, de diye | F94: ENTRY | G94: family_transaction(member_name=Mummy, transaction_type=kharcha, amount=3000, date=T) | H94: family_transaction(amount=3000.0, purpose=ghar ke kharche ke liye, member_name=Mummy, transaction_date=2026-10-08, transaction_type=kharcha); family_transaction(amount=3000.0, member_name=Mummy, transaction_date=2026-10-08, transaction_type=kharcha) | I94: Correct | J94: EXTRA entry: record_family_transaction Mummy 3000.0
A95: FIN-FAM-01 | B95: Family | C95: Papa-style | D95: 2 | E95: Mummy ne ghar ke kharche ke liye 3000 maange the, de diye | F95: ENTRY | G95: (extra entry) | H95: ″ | I95: Silent wrong
A96: FIN-FAM-02 | B96: Family | C96: Papa-style | D96: 1 | E96: Papa 1500 le gaye galle se, mandi jana tha | F96: ENTRY | G96: family_transaction(member_name=Papa, transaction_type=kharcha, amount=1500, date=T) | H96: family_transaction(note=galle se, amount=1500.0, member_name=Papa, transaction_date=2026-10-08, transaction_type=kharcha) | I96: Correct
A97: FIN-FAM-03 | B97: Family | C97: Papa-style | D97: 1 | E97: Chhote ki college fees 18000 bhari | F97: ENTRY | G97: family_transaction(member_name=Chhote, transaction_type=kharcha, amount=18000, date=T) | H97: family_transaction(amount=18000.0, purpose=college fees, member_name=Chhote, transaction_date=2026-10-08, transaction_type=kharcha) | I97: Correct
A98: FIN-FAM-04 | B98: Family | C98: Papa-style | D98: 1 | E98: Ghar ke liye 25 kilo aata aur daal 1800 ki aayi | F98: ENTRY | G98: family_transaction(transaction_type=kharcha, amount=1800, date=T) | H98: family_transaction(note=aata aaya, amount=25.0, purpose=ghar ke liye, member_name=Ghar, transaction_date=2026-10-08, transaction_type=jama); family_transaction(amount=1800.0, purpose=ghar ke liye, member_name=Ghar, transaction_date=2026-10-08, transaction_type=kharcha) | I98: Silent wrong | J98: record_family_transaction: transaction_type jama≠kharcha; amount 25.0≠1800 · EXTRA entry: record_family_transaction Ghar 1800.0
A99: FIN-FAM-04 | B99: Family | C99: Papa-style | D99: 2 | E99: Ghar ke liye 25 kilo aata aur daal 1800 ki aayi | F99: ENTRY | G99: (extra entry) | H99: ″ | I99: Silent wrong
A100: FIN-FAM-05 | B100: Family | C100: Papa-style | D100: 1 | E100: Bhai apne 5000 lauta gaya, galle mein rakh diye | F100: ENTRY | G100: family_transaction(member_name=Bhai, transaction_type=jama, amount=5000, date=T) | H100: (no entry) | asked: missing_argument | I100: Safe ask | J100: record_family_transaction: asked missing_argument:record_family_transaction ['amount']
...

Sheet Employee
A1: Employee bundle — test cases and results (before vs after fixes)
A2: Yellow = written and locked before the first run · Green = from the runs. Before = v1 code (2026-10-04, all 3 languages) · After = the last FULL run of the bundle after the fixes (Hinglish; every test in one run; run id in the After - Run column).
A3: After = full 50-test run 2026-10-05 13:49 (A–E), Hinglish.
A4: Test ID | B4: Category | C4: Event # | D4: Statement (Hinglish) | E4: Statement (Hindi) | F4: Statement (English) | G4: Expected Outcome | H4: Expected Role | I4: Expected Tool | J4: Expected Arguments | K4: Why this test | L4: Before — Actual (Hinglish) | M4: Before — Result (Hinglish) | N4: Before — Remark | O4: Before — Result (Hindi) | P4: Before — Result (English) | Q4: After — Actual (Hinglish) | R4: After — Result (Hinglish) | S4: After — Remark | T4: After — Run
A5: EMP-A-01 | B5: A - Daily | C5: 1 | D5: Sohan ko aaj 700 rupaye de diye | E5: सोहन को आज 700 रुपये दे दिए | F5: Gave Sohan 700 rupees today | G5: ENTRY | H5: Employee | I5: record_employee_transaction | J5: employee_name=Sohan; transaction_type=payment; amount=700; date=T | K5: Most common daily payment | L5: employee_transaction(transaction_type=payment, amount=700.0, employee_name=Sohan; 2026-10-04) | M5: Correct | O5: Correct | P5: Correct | Q5: employee_transaction(employee_name=Sohan, transaction_type=payment, amount=700, date=2026-10-05) | R5: Correct | T5: 1349
A6: EMP-A-02 | B6: A - Daily | C6: 1 | D6: Kitanu aaj subah se shaam tak kaam pe tha | E6: कितनू आज सुबह से शाम तक काम पे था | F6: Kitanu was at work from morning till evening today | G6: ENTRY | H6: Employee | I6: record_attendance | J6: employee_name=Kitanu; attendance=P; date=T | K6: Full-day attendance without the word 'present' | L6: asked amount (employee_transaction) | M6: Missed | N6: Picked work entry (asked amount) instead of attendance | O6: Missed | P6: Missed | Q6: attendance(employee_name=Kitanu, attendance=P, driving=absent, note=subah se shaam tak kaam pe tha, date=2026-10-05) | R6: Correct | T6: 1349
A7: EMP-A-03 | B7: A - Daily | C7: 1 | D7: Sohan ne aaj gudam mein 800 ka kaam kiya | E7: सोहन ने आज गोदाम में 800 का काम किया | F7: Sohan did work worth 800 at the warehouse today | G7: ENTRY | H7: Employee | I7: record_employee_transaction | J7: employee_name=Sohan; transaction_type=work; amount=800; date=T | K7: Daily work entry with place | L7: employee_transaction(transaction_type=work, amount=800.0, employee_name=Sohan; 2026-10-04) | M7: Correct | O7: Correct | P7: Correct | Q7: employee_transaction(employee_name=Sohan, transaction_type=work, amount=800, note=gudam mein, date=2026-10-05) | R7: Correct | T7: 1349
A8: EMP-A-04 | B8: A - Daily | C8: 1 | D8: Ram aaj kaam pe nahi aaya, ghar pe kuch kaam tha | E8: राम आज काम पे नहीं आया, घर पे कुछ काम था | F8: Ram didn't come to work today, he had something at home | G8: ENTRY | H8: Employee | I8: record_attendance | J8: employee_name=Ram; attendance=absent; date=T | K8: Absent with a reason that must NOT become a work entry | L8: went to general chat | M8: Missed | N8: Router sent it to general chat — no entry | O8: Missed | P8: Missed | Q8: attendance(employee_name=Ram, attendance=absent, driving=absent, note=ghar pe kuch kaam tha, date=2026-10-05) | R8: Correct | T8: 1349
A9: EMP-A-05 | B9: A - Daily | C9: 1 | D9: Kitanu ne 300 rupaye le liye kharche ke liye | E9: कितनू ने 300 रुपये ले लिए खर्चे के लिए | F9: Kitanu took 300 rupees for expenses | G9: ENTRY | H9: Employee | I9: record_employee_transaction | J9: employee_name=Kitanu; transaction_type=payment; amount=300; date=T | K9: 'le liye' = employee took money = payment | L9: employee_transaction(transaction_type=payment, amount=300.0, employee_name=Kitanu; 2026-10-04) | M9: Correct | O9: Correct | P9: Correct | Q9: employee_transaction(employee_name=Kitanu, transaction_type=payment, amount=300, note=kharche ke liye, date=2026-10-05) | R9: Correct | T9: 1349
A10: EMP-A-06 | B10: A - Daily | C10: 1 | D10: Sohan aaj aadhe din baad ghar chala gaya | E10: सोहन आज आधे दिन बाद घर चला गया | F10: Sohan went home after half a day today | G10: ENTRY | H10: Employee | I10: record_attendance | J10: employee_name=Sohan; attendance=half; date=T | K10: Half day phrased as leaving early | L10: went to general chat | M10: Missed | N10: Router sent it to general chat — no entry | O10: Missed | P10: Missed | Q10: attendance(employee_name=Sohan, attendance=half, driving=absent, note=ghar chala gaya, date=2026-10-05) | R10: Correct | T10: 1349
A11: EMP-A-07 | B11: A - Daily | C11: 1 | D11: Ram ne kal 650 ka kaam kiya tha | E11: राम ने कल 650 का काम किया था | F11: Ram did work worth 650 yesterday | G11: ENTRY | H11: Employee | I11: record_employee_transaction | J11: employee_name=Ram; transaction_type=work; amount=650; date=T-1 | K11: Past date 'kal' | L11: employee_transaction(transaction_type=work, amount=650.0, employee_name=Ram; 2026-10-03) | M11: Correct | O11: Correct | P11: Correct | Q11: employee_transaction(employee_name=Ram, transaction_type=work, amount=650, date=2026-10-04) | R11: Correct | T11: 1349
A12: EMP-A-08 | B12: A - Daily | C12: 1 | D12: Kitanu ne aaj poora din gaadi chalayi | E12: कितनू ने आज पूरा दिन गाड़ी चलाई | F12: Kitanu drove the vehicle the whole day today | G12: ENTRY | H12: Employee | I12: record_attendance | J12: employee_name=Kitanu; attendance=P; driving=P; date=T | K12: Driving without the word 'driving' | L12: asked amount (employee_transaction) | M12: Missed | N12: Picked work entry (asked amount) instead of attendance+driving | O12: Correct | P12: Correct | Q12: attendance(employee_name=Kitanu, attendance=P, driving=P, date=2026-10-05) | R12: Correct | T12: 1349
A13: EMP-A-09 | B13: A - Daily | C13: 1 | D13: Sohan ko agle hafte ki mazdoori ke 1000 pehle hi de diye | E13: सोहन को अगले हफ्ते की मज़दूरी के 1000 पहले ही दे दिए | F13: Gave Sohan 1000 in advance for next week's wages | G13: ENTRY | H13: Employee | I13: record_employee_transaction | J13: employee_name=Sohan; transaction_type=payment; amount=1000; date=T | K13: Advance = payment; 'agle hafte' must not change the date | L13: asked location type (UNKNOWN) | M13: Missed | N13: Grouped as material movement 'UNKNOWN → Sohan'; asked location type | O13: Missed | P13: Silent wrong | Q13: employee_transaction(employee_name=Sohan, transaction_type=payment, amount=1000, note=agle hafte ki mazdoori, date=2026-10-05) | R13: Correct | T13: 1349
A14: EMP-A-10 | B14: A - Daily | C14: 1 | D14: Ram ka aaj ka hisab 500 cash mein kar diya | E14: राम का आज का हिसाब 500 कैश में कर दिया | F14: Settled Ram's account for today with 500 cash | G14: ENTRY | H14: Employee | I14: record_employee_transaction | J14: employee_name=Ram; transaction_type=payment; amount=500; payment_method=cash; date=T | K14: 'hisab kar diya' = paid | L14: family_transaction(transaction_type=kharcha, amount=500.0, member_name=Ram; 2026-10-04) | M14: Silent wrong | N14: Recorded as FAMILY kharcha for Ram | O14: Correct | P14: Correct | Q14: employee_transaction(employee_name=Ram, transaction_type=payment, amount=500, payment_method=cash, note=aaj ka hisab, date=2026-10-05) | R14: Correct | T14: 1349
A15: EMP-B-01 | B15: B - Tricky | C15: 1 | D15: Sohan ke khaate mein 6k daal diye tankhwah ke | E15: सोहन के खाते में 6k डाल दिए तनख्वाह के | F15: Transferred 6k to Sohan's bank account as salary | G15: ENTRY | H15: Employee | I15: record_employee_transaction | J15: employee_name=Sohan; transaction_type=payment; amount=6000; payment_method=bank_transfer; date=T | K15: '6k', bank transfer, 'tankhwah' | L15: family_transaction(transaction_type=jama, amount=6000.0, member_name=Sohan; 2026-10-04) | M15: Silent wrong | N15: Recorded as FAMILY jama (cash IN) for Sohan — opposite direction | O15: Missed | P15: Correct | Q15: employee_transaction(employee_name=Sohan, transaction_type=payment, amount=6000, note=tankhwah ke, date=2026-10-05) | R15: Correct | T15: 1349
A16: EMP-B-02 | B16: B - Tricky | C16: 1 | D16: Kitanu ko dedh hazaar diye parso | E16: कितनू को डेढ़ हज़ार दिए परसों | F16: Gave Kitanu one and a half thousand the day before yesterday | G16: ENTRY | H16: Employee | I16: record_employee_transaction | J16: employee_name=Kitanu; transaction_type=payment; amount=1500; date=T-2 | K16: 'dedh hazaar' = 1500, 'parso' = T-2 | L16: employee_transaction(transaction_type=payment, amount=1500.0, employee_name=Kitanu; 2026-10-02) | M16: Correct | O16: Correct | P16: Correct | Q16: employee_transaction(employee_name=Kitanu, transaction_type=payment, amount=1500, date=2026-10-03) | R16: Correct | T16: 1349
A17: EMP-B-03 | B17: B - Tricky | C17: 1 | D17: ram ne aj 450 ka kam kia | E17: राम ने अज 450 का कम कीया | F17: ram did wrk worth 450 tody | G17: ENTRY | H17: Employee | I17: record_employee_transaction | J17: employee_name=Ram; transaction_type=work; amount=450; date=T | K17: Spelling mistakes in words | L17: employee_transaction(transaction_type=work, amount=450.0, employee_name=Ram; 2026-10-04) | M17: Correct | O17: Correct | P17: Correct | Q17: employee_transaction(employee_name=Ram, transaction_type=work, amount=450, date=2026-10-05) | R17: Correct | T17: 1349
A18: EMP-B-04 | B18: B - Tricky | C18: 1 | D18: Somvaar ko Sohan nahi aaya tha | E18: सोमवार को सोहन नहीं आया था | F18: Sohan didn't come on Monday | G18: ENTRY | H18: Employee | I18: record_attendance | J18: employee_name=Sohan; attendance=absent; date=LAST_MONDAY | K18: Weekday name as date | L18: attendance(attendance=absent, driving=absent, employee_name=Sohan; 2026-10-03) | M18: Silent wrong | N18: Date 03-Oct (expected last Monday 28-Sep) | O18: Silent wrong | P18: Missed | Q18: attendance(employee_name=Sohan, attendance=absent, driving=absent, date=2026-09-28) | R18: Correct | T18: 1349
A19: EMP-B-05 | B19: B - Tricky | C19: 1 | D19: Kitanu ki aaj ki haaziri lagao, aadha din gaadi bhi chalayi | E19: कितनू की आज की हाज़िरी लगाओ, आधा दिन गाड़ी भी चलाई | F19: Mark Kitanu present today, he also drove for half the day | G19: ENTRY | H19: Employee | I19: record_attendance | J19: employee_name=Kitanu; attendance=P; driving=half; date=T | K19: 'haaziri' + two values in one line | L19: asked amount (employee_transaction) | M19: Missed | N19: Picked work entry (asked amount) instead of attendance | O19: Silent wrong | P19: Silent wrong | Q19: attendance(employee_name=Kitanu, attendance=P, driving=half, date=2026-10-05) | R19: Correct | T19: 1349
A20: EMP-B-06 | B20: B - Tricky | C20: 1 | D20: Ram shanivaar ko 2 ghante extra ruka, 200 ka kaam aur kiya | E20: राम शनिवार को 2 घंटे एक्स्ट्रा रुका, 200 का काम और किया | F20: Ram stayed 2 extra hours on Saturday, did 200 more worth of work | G20: ENTRY | H20: Employee | I20: record_employee_transaction | J20: employee_name=Ram; transaction_type=work; amount=200; date=LAST_SATURDAY | K20: '2 ghante' is not the amount; weekday date | L20: employee_transaction(transaction_type=work, amount=200.0, employee_name=Ram; 2026-10-01) | M20: Silent wrong | N20: Date 01-Oct (expected Saturday 03-Oct) + extra attendance row | O20: Safe ask | P20: Safe ask | Q20: employee_transaction(employee_name=Ram, transaction_type=work, amount=200, date=2026-10-03) | R20: Correct | T20: 1349
A21: EMP-B-06 | B21: B - Tricky | C21: extra 1 | D21: Ram shanivaar ko 2 ghante extra ruka, 200 ka kaam aur kiya | E21: राम शनिवार को 2 घंटे एक्स्ट्रा रुका, 200 का काम और किया | F21: Ram stayed 2 extra hours on Saturday, did 200 more worth of work | G21: ENTRY | I21: (extra entry) | K21: '2 ghante' is not the amount; weekday date | R21: Silent wrong | T21: 1349
A22: EMP-B-07 | B22: B - Tricky | C22: 1 | D22: ₹750 Sohan ko, kal ki mazdoori ke | E22: ₹750 सोहन को, कल की मज़दूरी के | F22: ₹750 to Sohan, for yesterday's wages | G22: ENTRY | H22: Employee | I22: record_employee_transaction | J22: employee_name=Sohan; transaction_type=payment; amount=750; date=T | K22: Paid today; 'kal' is only the work day → date must be T | L22: employee_transaction(transaction_type=payment, amount=750.0, employee_name=Sohan; 2026-10-03) | M22: Silent wrong | N22: Date T-1 — 'kal ki mazdoori' is the work day, payment was today | O22: Silent wrong | P22: Missed | Q22: employee_transaction(employee_name=Sohan, transaction_type=payment, amount=750, note=mazdoori, date=2026-10-05) | R22: Correct | T22: 1349
A23: EMP-B-08 | B23: B - Tricky | C23: 1 | D23: Kitanu ne 2 hazaar maange the, abhi 1500 hi diye | E23: कितनू ने 2 हज़ार माँगे थे, अभी 1500 ही दिए | F23: Kitanu asked for 2 thousand, gave only 1500 for now | G23: ENTRY | H23: Employee | I23: record_employee_transaction | J23: employee_name=Kitanu; transaction_type=payment; amount=1500; date=T | K23: Two amounts — only 1500 was paid | L23: employee_transaction(transaction_type=payment, amount=1500.0, employee_name=Kitanu; 2026-10-04) | M23: Correct | O23: Correct | P23: Correct | Q23: employee_transaction(employee_name=Kitanu, transaction_type=payment, amount=1500, date=2026-10-05) | R23: Correct | T23: 1349
A24: EMP-B-09 | B24: B - Tricky | C24: 1 | D24: Ram ko paanch sau rupaye pakda diye | E24: राम को पाँच सौ रुपये पकड़ा दिए | F24: Handed Ram five hundred rupees | G24: ENTRY | H24: Employee | I24: record_employee_transaction | J24: employee_name=Ram; transaction_type=payment; amount=500; date=T | K24: Number in words; 'pakda diye' = gave | L24: employee_transaction(transaction_type=payment, amount=500.0, employee_name=Ram; 2026-10-04) | M24: Correct | O24: Correct | P24: Correct | Q24: employee_transaction(employee_name=Ram, transaction_type=payment, amount=500, date=2026-10-05) | R24: Correct | T24: 1349
A25: EMP-B-10 | B25: B - Tricky | C25: 1 | D25: Sohan ne kal raat ki shift mein 900 kamaye | E25: सोहन ने कल रात की शिफ्ट में 900 कमाए | F25: Sohan earned 900 in last night's shift | G25: ENTRY | H25: Employee | I25: record_employee_transaction | J25: employee_name=Sohan; transaction_type=work; amount=900; date=T-1 | K25: 'kamaye' = work, not payment | L25: employee_transaction(transaction_type=work, amount=900.0, employee_name=Sohan; 2026-10-03) | M25: Correct | O25: Correct | P25: Silent wrong | Q25: employee_transaction(employee_name=Sohan, transaction_type=work, amount=900, note=raat ki shift mein, date=2026-10-04) | R25: Correct | T25: 1349
A26: EMP-C-01 | B26: C - Edge | C26: 1 | D26: Kitanu aaj time pe aa gaya tha | E26: कितनू आज टाइम पे आ गया था | F26: Kitanu came on time today | G26: ASK | H26: Employee | I26: record_attendance | J26: employee_name=Kitanu; date=T | K26: Arrival known, length of the day unknown | L26: went to general chat | M26: Missed | N26: General chat — neither asked nor recorded | O26: Silent wrong | P26: Missed | Q26: attendance(employee_name=Kitanu, attendance=P, driving=absent, note=time pe aa gaya tha, date=2026-10-05) | R26: Silent wrong | S26: record_attendance: recorded instead of asking (values guessed) | T26: 1349
A27: EMP-C-02 | B27: C - Edge | C27: 1 | D27: Sohan ko uske paise de diye aaj | E27: सोहन को उसके पैसे दे दिए आज | F27: Gave Sohan his money today | G27: ASK | H27: Employee | I27: record_employee_transaction | J27: employee_name=Sohan; transaction_type=payment; date=T | K27: Amount missing | L27: asked location type (UNKNOWN) | M27: Safe ask | N27: Asked a location-type question (wrong flow) — nothing recorded | O27: Safe ask | P27: Safe ask | Q27: asked amount (employee_transaction) | R27: Correct | T27: 1349
A28: EMP-C-03 | B28: C - Edge | C28: 1 | D28: Kitanu ke saath 500 ka hisab hua | E28: कितनू के साथ 500 का हिसाब हुआ | F28: Settled 500 with Kitanu | G28: ASK | H28: Employee | I28: record_employee_transaction | J28: employee_name=Kitanu; amount=500; date=T | K28: Direction unclear | L28: employee_transaction(transaction_type=payment, amount=500.0, employee_name=Kitanu; 2026-10-04) | M28: Silent wrong | N28: Assumed payment 500 instead of asking work/payment | O28: Safe ask | P28: Silent wrong | Q28: employee_transaction(employee_name=Kitanu, transaction_type=payment, amount=500, note=ke saath hisab hua, date=2026-10-05) | R28: Silent wrong | S28: record_employee_transaction: recorded instead of asking (values guessed) | T28: 1349
A29: EMP-C-04 | B29: C - Edge | C29: 1 | D29: Sohan ka kitna baaki hai abhi? | E29: सोहन का कितना बाकी है अभी? | F29: How much is due to Sohan right now? | G29: NO-ENTRY | H29: — | I29: (nothing) | K29: A question (report), not an entry | L29: report flow | M29: Correct | O29: Correct | P29: Correct | Q29: asked report | R29: Correct | T29: 1349
A30: EMP-C-05 | B30: C - Edge | C30: 1 | D30: Ram ko aaj paise nahi diye, kal denge | E30: राम को आज पैसे नहीं दिए, कल देंगे | F30: Didn't pay Ram today, will pay tomorrow | G30: NO-ENTRY | H30: — | I30: (nothing) | K30: Negation + future plan | L30: CRASH: IndexError | M30: Missed | N30: Crash: IndexError in tool_argument_extraction (2 actions, 'kal denge') | O30: Safe ask | P30: Correct | Q30: no entry (route=accounting) | R30: Correct | T30: 1349
A31: EMP-C-06 | B31: C - Edge | C31: 1 | D31: Kitanu ko 400 diye, nahi nahi 450 diye the | E31: कितनू को 400 दिए, नहीं नहीं 450 दिए थे | F31: Gave Kitanu 400, no wait, it was 450 | G31: ENTRY | H31: Employee | I31: record_employee_transaction | J31: employee_name=Kitanu; transaction_type=payment; amount=450; date=T | K31: Self-correction inside the sentence — only 450, only once | L31: employee_transaction(transaction_type=payment, amount=400.0, employee_name=Kitanu; 2026-10-04) | M31: Silent wrong | N31: Recorded BOTH 400 and 450 | O31: Correct | P31: Correct | Q31: employee_transaction(employee_name=Kitanu, transaction_type=payment, amount=450, date=2026-10-05) | R31: Correct | T31: 1349
A32: EMP-C-07 | B32: C - Edge | C32: 1 | D32: Mukesh ko 600 diye | E32: मुकेश को 600 दिए | F32: Gave Mukesh 600 | G32: ASK | H32: Employee | I32: record_employee_transaction | J32: employee_name=Mukesh; transaction_type=payment; amount=600; date=T | K32: Name not in DB | L32: employee_transaction(transaction_type=payment, amount=600.0, employee_name=Mukesh; 2026-10-04) | M32: Correct | O32: Correct | P32: Correct | Q32: employee_transaction(employee_name=Mukesh, transaction_type=payment, amount=600, date=2026-10-05) | R32: Correct | T32: 1349
A33: EMP-C-08 | B33: C - Edge | C33: 1 | D33: Ram ko 5oo diye | E33: राम को 5oo दिए | F33: Gave Ram 5oo | G33: ENTRY | H33: Employee | I33: record_employee_transaction | J33: employee_name=Ram; transaction_type=payment; amount=500; date=T | K33: Letter 'o' inside the number; asking = Safe ask | L33: employee_transaction(transaction_type=payment, amount=500.0, employee_name=Ram; 2026-10-04) | M33: Correct | O33: Correct | P33: Correct | Q33: employee_transaction(employee_name=Ram, transaction_type=payment, amount=500, date=2026-10-05) | R33: Correct | T33: 1349
A34: EMP-C-09 | B34: C - Edge | C34: 1 | D34: Sohan aaj nahi aaya par 500 ka kaam kiya | E34: सोहन आज नहीं आया पर 500 का काम किया | F34: Sohan didn't come today but did 500 worth of work | G34: ASK | I34: (extra entry) | J34: Contradiction — absent or worked? | K34: Contradictory facts | L34: attendance(attendance=absent, driving=absent, employee_name=Sohan; 2026-10-04) | M34: Silent wrong | N34: Recorded absent AND work 500 without asking about the contradiction | O34: Silent wrong | P34: Silent wrong | Q34: attendance(employee_name=Sohan, attendance=absent, driving=absent, date=2026-10-05); employee_transaction(employee_name=Sohan, transaction_type=work, amount=500, date=2026-10-05) | R34: Silent wrong | S34: entry made instead of asking: record_attendance, record_employee_transaction | T34: 1349
A35: EMP-C-10 | B35: C - Edge | C35: 1 | D35: Kitanu ne pichle hafte wale 300 wapas kar diye | E35: कितनू ने पिछले हफ्ते वाले 300 वापस कर दिए | F35: Kitanu returned the 300 from last week | G35: ASK | I35: (extra entry) | J35: Employee returned money — no payment entry | K35: Repayment by employee; a 'payment 300' entry would be the opposite of reality | L35: correction flow | M35: Safe ask | N35: Opened correction flow (asked date) — repayment not supported; nothing recorded | O35: Safe ask | P35: Safe ask | Q35: asked correction | R35: Safe ask | S35: asked/stopped: correction: CorrectionDateHITLRequest | T35: 1349
A36: EMP-D-01 | B36: D - Other business | C36: 1 | D36: Sohan mistri ne aaj 2 kamron ki tile laga di, 1200 ka kaam hua | E36: सोहन मिस्त्री ने आज 2 कमरों की टाइल लगा दी, 1200 का काम हुआ | F36: Sohan the mason laid tiles in 2 rooms today, work worth 1200 | G36: ENTRY | H36: Employee | I36: record_employee_transaction | J36: employee_name=Sohan; transaction_type=work; amount=1200; date=T | K36: Tiles business; '2 kamron' is not the amount | L36: employee_transaction(transaction_type=work, amount=1200.0, employee_name=Sohan mistri; 2026-10-04) | M36: Silent wrong | N36: Name taken with title ('Sohan mistri' / 'Sohan the mason') → new employee | O36: Silent wrong | P36: Silent wrong | Q36: employee_transaction(employee_name=Sohan, transaction_type=work, amount=1200, note=2 kamron ki tile laga di, date=2026-10-05) | R36: Correct | T36: 1349
A37: EMP-D-02 | B37: D - Other business | C37: 1 | D37: Dukaan wale ladke Ram ko is mahine ki salary 9000 de di | E37: दुकान वाले लड़के राम को इस महीने की सैलरी 9000 दे दी | F37: Paid the shop boy Ram this month's salary of 9000 | G37: ENTRY | H37: Employee | I37: record_employee_transaction | J37: employee_name=Ram; transaction_type=payment; amount=9000; date=T | K37: Kirana shop wording | L37: asked location type (UNKNOWN) | M37: Missed | N37: Grouped as material movement; asked location type | O37: Missed | P37: Correct | Q37: employee_transaction(employee_name=Ram, transaction_type=payment, amount=9000, note=is mahine ki salary, date=2026-10-05) | R37: Correct | T37: 1349
A38: EMP-D-03 | B38: D - Other business | C38: 1 | D38: Kitanu karigar ne aaj 25 shirt silai ki, 20 rupaye piece ke hisab se | E38: कितनू कारीगर ने आज 25 शर्ट सिलाई की, 20 रुपये पीस के हिसाब से | F38: Kitanu the tailor stitched 25 shirts today at 20 rupees per piece | G38: ENTRY | H38: Employee | I38: record_employee_transaction | J38: employee_name=Kitanu; transaction_type=work; amount=500; date=T | K38: Piece rate — amount must be computed (25 × 20) | L38: employee_transaction(transaction_type=work, amount=500.0, employee_name=Kitanu; 2026-10-04) | M38: Correct | O38: Correct | P38: Silent wrong | Q38: employee_transaction(employee_name=Kitanu, transaction_type=work, amount=500, note=25 shirt silai ki, 20 rupaye piece ke hisab se, date=2026-10-05) | R38: Correct | T38: 1349
A39: EMP-D-04 | B39: D - Other business | C39: 1 | D39: Ram dumper wala aaj poore din trip pe raha | E39: राम डंपर वाला आज पूरे दिन ट्रिप पे रहा | F39: Ram the dumper driver was on trips all day today | G39: ENTRY | H39: Employee | I39: record_attendance | J39: employee_name=Ram; attendance=P; driving=P; date=T | K39: Sand/gravel business: 'trip' = driving | L39: attendance(attendance=P, driving=absent, employee_name=Ram; 2026-10-04) | M39: Silent wrong | N39: Driving not marked (attendance P, driving absent) | O39: Correct | P39: Missed | Q39: attendance(employee_name=Ram, attendance=P, driving=P, note=trip pe raha, date=2026-10-05) | R39: Correct | T39: 1349
A40: EMP-D-05 | B40: D - Other business | C40: 1 | D40: Sohan cook ki aaj off thi | E40: सोहन कुक की आज ऑफ थी | F40: Sohan the cook had the day off today | G40: ENTRY | H40: Employee | I40: record_attendance | J40: employee_name=Sohan; attendance=absent; date=T | K40: Dhaba wording: 'off thi' = absent | L40: attendance(attendance=absent, driving=absent, employee_name=Sohan; 2026-10-04) | M40: Correct | O40: Silent wrong | P40: Missed | Q40: attendance(employee_name=Sohan, attendance=absent, driving=absent, note=cook ki aaj off thi, date=2026-10-05) | R40: Correct | T40: 1349
A41: EMP-D-06 | B41: D - Other business | C41: 1 | D41: Beldar Sohan ko hafte ka 3600 bhugtaan kar diya | E41: बेलदार सोहन को हफ्ते का 3600 भुगतान कर दिया | F41: Paid labourer Sohan 3600 for the week | G41: ENTRY | H41: Employee | I41: record_employee_transaction | J41: employee_name=Sohan; transaction_type=payment; amount=3600; date=T | K41: Construction: 'beldar', formal 'bhugtaan' | L41: expense_payment(amount=3600.0, description=hafte ka; 2026-10-04) | M41: Silent wrong | N41: Recorded as expense payment | O41: Correct | P41: Correct | Q41: employee_transaction(employee_name=Sohan, transaction_type=payment, amount=3600, note=hafte ka bhugtaan, date=2026-10-05) | R41: Correct | T41: 1349
A42: EMP-D-07 | B42: D - Other business | C42: 1 | D42: Ram ne aaj godown mein maal ki packing ki, 400 banta hai | E42: राम ने आज गोदाम में माल की पैकिंग की, 400 बनता है | F42: Ram packed goods in the godown today, 400 is due | G42: ENTRY | H42: Employee | I42: record_employee_transaction | J42: employee_name=Ram; transaction_type=work; amount=400; date=T | K42: Hardware: 'banta hai' = amount owed for work | L42: asked amount (employee_transaction) | M42: Safe ask | N42: Asked amount though 400 was stated (correct tool) | O42: Safe ask | P42: Silent wrong | R42: Missed | S42: record_employee_transaction: no entry, no question (route=accounting) | T42: 1349
A43: EMP-D-07 | B43: D - Other business | C43: extra 1 | D43: Ram ne aaj godown mein maal ki packing ki, 400 banta hai | E43: राम ने आज गोदाम में माल की पैकिंग की, 400 बनता है | F43: Ram packed goods in the godown today, 400 is due | G43: ENTRY | I43: (extra entry) | K43: Hardware: 'banta hai' = amount owed for work | R43: Silent wrong | S43: EXTRA entry: record_work_log | T43: 1349
A44: EMP-D-08 | B44: D - Other business | C44: 1 | D44: Kitanu ko UPI se 2500 bhej diye overtime ke | E44: कितनू को UPI से 2500 भेज दिए ओवरटाइम के | F44: Sent Kitanu 2500 via UPI for overtime | G44: ENTRY | H44: Employee | I44: record_employee_transaction | J44: employee_name=Kitanu; transaction_type=payment; amount=2500; payment_method=upi; date=T | K44: Mobile shop: UPI + overtime | L44: employee_transaction(transaction_type=payment, amount=2500.0, payment_method=UPI, employee_name=Kitanu; 2026-10-04) | M44: Correct | O44: Missed | P44: Missed | Q44: employee_transaction(employee_name=Kitanu, transaction_type=payment, amount=2500, payment_method=UPI, note=overtime ke, date=2026-10-05) | R44: Correct | T44: 1349
A45: EMP-D-09 | B45: D - Other business | C45: 1 | D45: Sohan kaarigar ne 2 almari banayi, 3000 ka kaam | E45: सोहन कारीगर ने 2 अलमारी बनाई, 3000 का काम | F45: Sohan the carpenter built 2 cupboards, work worth 3000 | G45: ENTRY | H45: Employee | I45: record_employee_transaction | J45: employee_name=Sohan; transaction_type=work; amount=3000; date=T | K45: Furniture: '2 almari' is not the amount | L45: employee_transaction(transaction_type=work, amount=3000.0, employee_name=Sohan kaarigar; 2026-10-04) | M45: Silent wrong | N45: Name taken with title ('Sohan kaarigar') → new employee | O45: Silent wrong | P45: Correct | Q45: employee_transaction(employee_name=Sohan, transaction_type=work, amount=3000, note=2 almari banayi, date=2026-10-05) | R45: Correct | T45: 1349
A46: EMP-D-10 | B46: D - Other business | C46: 1 | D46: Ram aaj sirf subah ki shift karke gaya | E46: राम आज सिर्फ सुबह की शिफ्ट करके गया | F46: Ram did only the morning shift today and left | G46: ENTRY | H46: Employee | I46: record_attendance | J46: employee_name=Ram; attendance=half; date=T | K46: Shop shifts: one shift = half day | L46: attendance(attendance=P, driving=absent, employee_name=Ram; 2026-10-04) | M46: Silent wrong | N46: Marked full day (expected half) | O46: Silent wrong | P46: Missed | Q46: attendance(employee_name=Ram, attendance=half, driving=absent, note=sirf subah ki shift karke gaya, date=2026-10-05) | R46: Correct | T46: 1349
A47: EMP-E-01 | B47: E - Mixed | C47: 1 | D47: Sohan ne 600 ka kaam kiya aur Sharma ji ne 4000 jama karaye | E47: सोहन ने 600 का काम किया और शर्मा जी ने 4000 जमा कराए | F47: Sohan did work worth 600 and Sharma ji deposited 4000 | G47: ENTRY | H47: Employee | I47: record_employee_transaction | J47: employee_name=Sohan; transaction_type=work; amount=600; date=T | K47: Employee + customer payment | L47: employee_transaction(transaction_type=work, amount=600.0, employee_name=Sohan; 2026-10-04) | M47: Correct | O47: Correct | P47: Correct | Q47: employee_transaction(employee_name=Sohan, transaction_type=work, amount=600, date=2026-10-05) | R47: Correct | T47: 1349
A48: EMP-E-01 | B48: E - Mixed | C48: 2 | D48: Sohan ne 600 ka kaam kiya aur Sharma ji ne 4000 jama karaye | E48: सोहन ने 600 का काम किया और शर्मा जी ने 4000 जमा कराए | F48: Sohan did work worth 600 and Sharma ji deposited 4000 | G48: ENTRY | H48: Customer | I48: record_sale_payment | J48: customer_name=Sharma ji; amount=4000; date=T | K48: Employee + customer payment | L48: sale_payment(amount=4000.0, customer_name=Sharma ji; 2026-10-04) | M48: Correct | O48: Correct | P48: Correct | Q48: sale_payment(customer_name=Sharma ji, amount=4000, date=2026-10-05) | R48: Correct | T48: 1349
A49: EMP-E-02 | B49: E - Mixed | C49: 1 | D49: SBI bhatte se 3000 eent gudam mein aayi, Kitanu gaadi lekar gaya tha, use 300 diye | E49: एसबीआई भट्टे से 3000 ईंट गोदाम में आई, कितनू गाड़ी लेकर गया था, उसे 300 दिए | F49: 3000 bricks came from SBI Bhatta to the warehouse, Kitanu drove, paid him 300 | G49: ENTRY | H49: Supplier | I49: record_supplier_transaction | J49: supplier_name=SBI Bhatta; item_name=eent; quantity=3000; driver_name=Kitanu; date=T | K49: Same name as driver and as payee | L49: supplier_transaction(supplier_name=SBI bhata, item_name=eent, quantity=3000.0; 2026-10-04) | M49: Silent wrong | N49: Supplier saved as new 'SBI bhata' (not SBI Bhatta); driver not saved | O49: Missed | P49: Missed | Q49: supplier_transaction(supplier_name=SBI Bhatta, item_name=eent, quantity=3000, driver_name=Kitanu, date=2026-10-05) | R49: Correct | T49: 1349
A50: EMP-E-02 | B50: E - Mixed | C50: 2 | D50: SBI bhatte se 3000 eent gudam mein aayi, Kitanu gaadi lekar gaya tha, use 300 diye | E50: एसबीआई भट्टे से 3000 ईंट गोदाम में आई, कितनू गाड़ी लेकर गया था, उसे 300 दिए | F50: 3000 bricks came from SBI Bhatta to the warehouse, Kitanu drove, paid him 300 | G50: ENTRY | H50: Employee | I50: record_employee_transaction | J50: employee_name=Kitanu; transaction_type=payment; amount=300; date=T | K50: Same name as driver and as payee | L50: employee_transaction(transaction_type=payment, amount=300.0, employee_name=Kitanu; 2026-10-04) | M50: Correct | O50: Missed | P50: Missed | Q50: employee_transaction(employee_name=Kitanu, transaction_type=payment, amount=300, date=2026-10-05) | R50: Correct | T50: 1349
A51: EMP-E-03 | B51: E - Mixed | C51: 1 | D51: Ram aaj nahi aaya, aur Papa ne ghar ke liye 2000 nikale | E51: राम आज नहीं आया, और पापा ने घर के लिए 2000 निकाले | F51: Ram didn't come today, and Papa took 2000 for the house | G51: ENTRY | H51: Employee | I51: record_attendance | J51: employee_name=Ram; attendance=absent; date=T | K51: Employee attendance + family kharcha | L51: attendance(attendance=absent, driving=absent, employee_name=Ram; 2026-10-04) | M51: Correct | O51: Correct | P51: Correct | Q51: attendance(employee_name=Ram, attendance=absent, driving=absent, date=2026-10-05) | R51: Correct | T51: 1349
A52: EMP-E-03 | B52: E - Mixed | C52: 2 | D52: Ram aaj nahi aaya, aur Papa ne ghar ke liye 2000 nikale | E52: राम आज नहीं आया, और पापा ने घर के लिए 2000 निकाले | F52: Ram didn't come today, and Papa took 2000 for the house | G52: ENTRY | H52: Family Member | I52: record_family_transaction | J52: member_name=Papa; transaction_type=kharcha; amount=2000; date=T | K52: Employee attendance + family kharcha | L52: family_transaction(transaction_type=kharcha, amount=2000.0, member_name=Papa; 2026-10-04) | M52: Correct | O52: Correct | P52: Correct | Q52: family_transaction(member_name=Papa, transaction_type=kharcha, amount=2000, date=2026-10-05) | R52: Correct | T52: 1349
A53: EMP-E-04 | B53: E - Mixed | C53: 1 | D53: Diesel mein 1500 lage aur Kitanu ko aaj ki mazdoori 500 di | E53: डीज़ल में 1500 लगे और कितनू को आज की मज़दूरी 500 दी | F53: 1500 went on diesel and paid Kitanu 500 for today's wages | G53: ENTRY | I53: record_expense | J53: amount=1500; category=transport; date=T | K53: Expense (no payment words) + employee payment | L53: expense(amount=1500.0, category=fuel, description=diesel; 2026-10-04) | M53: Correct | O53: Correct | P53: Correct | Q53: expense(amount=1500, category=fuel, date=2026-10-05) | R53: Correct | T53: 1349
A54: EMP-E-04 | B54: E - Mixed | C54: 2 | D54: Diesel mein 1500 lage aur Kitanu ko aaj ki mazdoori 500 di | E54: डीज़ल में 1500 लगे और कितनू को आज की मज़दूरी 500 दी | F54: 1500 went on diesel and paid Kitanu 500 for today's wages | G54: ENTRY | H54: Employee | I54: record_employee_transaction | J54: employee_name=Kitanu; transaction_type=payment; amount=500; date=T | K54: Expense (no payment words) + employee payment | L54: employee_transaction(transaction_type=payment, amount=500.0, employee_name=Kitanu; 2026-10-04) | M54: Correct | O54: Correct | P54: Correct | Q54: employee_transaction(employee_name=Kitanu, transaction_type=payment, amount=500, note=aaj ki mazdoori, date=2026-10-05) | R54: Correct | T54: 1349
A55: EMP-E-05 | B55: E - Mixed | C55: 1 | D55: Suresh Traders ko 2000 eent 16000 mein bheji, Ram ne load karwayi, uska 400 ka kaam | E55: सुरेश ट्रेडर्स को 2000 ईंट 16000 में भेजी, राम ने लोड करवाई, उसका 400 का काम | F55: Sent 2000 bricks to Suresh Traders for 16000, Ram did the loading, his work is 400 | G55: ENTRY | H55: Customer | I55: record_sale_transaction | J55: customer_name=Suresh Traders; item_name=eent; quantity=2000; amount=16000; date=T | K55: Sale + employee work | L55: asked location type (UNKNOWN) | M55: Missed | N55: Sale grouped as movement with source 'UNKNOWN'; location question blocked all | O55: Missed | P55: Missed | Q55: sale_transaction(customer_name=Suresh Traders, item_name=eent, quantity=2000, amount=16000, date=2026-10-05) | R55: Correct | T55: 1349
A56: EMP-E-05 | B56: E - Mixed | C56: 2 | D56: Suresh Traders ko 2000 eent 16000 mein bheji, Ram ne load karwayi, uska 400 ka kaam | E56: सुरेश ट्रेडर्स को 2000 ईंट 16000 में भेजी, राम ने लोड करवाई, उसका 400 का काम | F56: Sent 2000 bricks to Suresh Traders for 16000, Ram did the loading, his work is 400 | G56: ENTRY | H56: Employee | I56: record_employee_transaction | J56: employee_name=Ram; transaction_type=work; amount=400; date=T | K56: Sale + employee work | L56: asked location type (UNKNOWN) | M56: Missed | N56: Sale grouped as movement with source 'UNKNOWN'; location question blocked all | O56: Missed | P56: Missed | Q56: employee_transaction(employee_name=Ram, transaction_type=work, amount=400, note=load karwayi, date=2026-10-05) | R56: Correct | T56: 1349
A57: EMP-E-06 | B57: E - Mixed | C57: 1 | D57: Sohan aur Kitanu dono aaj poora din aaye, Sharma ji se 5000 aaye | E57: सोहन और कितनू दोनों आज पूरा दिन आए, शर्मा जी से 5000 आए | F57: Sohan and Kitanu both came full day today, received 5000 from Sharma ji | G57: ENTRY | H57: Employee | I57: record_attendance | J57: employee_name=Sohan; attendance=P; date=T | K57: Two employees + customer payment | L57: asked location type (UNKNOWN) | M57: Missed | N57: Blocked by location-type question 'UNKNOWN' | O57: Missed | P57: Correct | Q57: attendance(employee_name=Sohan, attendance=P, driving=absent, date=2026-10-05) | R57: Correct | T57: 1349
A58: EMP-E-06 | B58: E - Mixed | C58: 2 | D58: Sohan aur Kitanu dono aaj poora din aaye, Sharma ji se 5000 aaye | E58: सोहन और कितनू दोनों आज पूरा दिन आए, शर्मा जी से 5000 आए | F58: Sohan and Kitanu both came full day today, received 5000 from Sharma ji | G58: ENTRY | H58: Employee | I58: record_attendance | J58: employee_name=Kitanu; attendance=P; date=T | K58: Two employees + customer payment | L58: asked location type (UNKNOWN) | M58: Missed | N58: Blocked by location-type question 'UNKNOWN' | O58: Missed | P58: Correct | Q58: attendance(employee_name=Kitanu, attendance=P, driving=absent, date=2026-10-05) | R58: Correct | T58: 1349
A59: EMP-E-06 | B59: E - Mixed | C59: 3 | D59: Sohan aur Kitanu dono aaj poora din aaye, Sharma ji se 5000 aaye | E59: सोहन और कितनू दोनों आज पूरा दिन आए, शर्मा जी से 5000 आए | F59: Sohan and Kitanu both came full day today, received 5000 from Sharma ji | G59: ENTRY | H59: Customer | I59: record_sale_payment | J59: customer_name=Sharma ji; amount=5000; date=T | K59: Two employees + customer payment | L59: asked location type (UNKNOWN) | M59: Missed | N59: Blocked by location-type question 'UNKNOWN' | O59: Missed | P59: Missed | Q59: sale_payment(customer_name=Sharma ji, amount=5000, date=2026-10-05) | R59: Correct | T59: 1349
A60: EMP-E-06 | B60: E - Mixed | C60: extra 1 | D60: Sohan aur Kitanu dono aaj poora din aaye, Sharma ji se 5000 aaye | E60: सोहन और कितनू दोनों आज पूरा दिन आए, शर्मा जी से 5000 आए | F60: Sohan and Kitanu both came full day today, received 5000 from Sharma ji | G60: ENTRY | I60: (extra entry) | K60: Two employees + customer payment | P60: Silent wrong
A61: EMP-E-06 | B61: E - Mixed | C61: extra 2 | D61: Sohan aur Kitanu dono aaj poora din aaye, Sharma ji se 5000 aaye | E61: सोहन और कितनू दोनों आज पूरा दिन आए, शर्मा जी से 5000 आए | F61: Sohan and Kitanu both came full day today, received 5000 from Sharma ji | G61: ENTRY | I61: (extra entry) | K61: Two employees + customer payment | P61: Silent wrong
A62: EMP-E-07 | B62: E - Mixed | C62: 1 | D62: SBI bhatte ko 10000 diye, Ram ko 1000 advance diya aur bijli ka bill 1200 bhara | E62: एसबीआई भट्टे को 10000 दिए, राम को 1000 एडवांस दिया और बिजली का बिल 1200 भरा | F62: Paid SBI Bhatta 10000, gave Ram 1000 advance and paid the electricity bill of 1200 | G62: ENTRY | H62: Supplier | I62: record_supplier_payment | J62: supplier_name=SBI Bhatta; amount=10000; date=T | K62: Supplier payment + employee advance + expense with payment (4 entries) | L62: (nothing recorded) | M62: Silent wrong | N62: Supplier payment recorded as expense payment | O62: Correct | P62: Silent wrong | Q62: supplier_payment(supplier_name=SBI Bhatta, amount=10000, date=2026-10-05) | R62: Correct | T62: 1349
A63: EMP-E-07 | B63: E - Mixed | C63: 2 | D63: SBI bhatte ko 10000 diye, Ram ko 1000 advance diya aur bijli ka bill 1200 bhara | E63: एसबीआई भट्टे को 10000 दिए, राम को 1000 एडवांस दिया और बिजली का बिल 1200 भरा | F63: Paid SBI Bhatta 10000, gave Ram 1000 advance and paid the electricity bill of 1200 | G63: ENTRY | H63: Employee | I63: record_employee_transaction | J63: employee_name=Ram; transaction_type=payment; amount=1000; date=T | K63: Supplier payment + employee advance + expense with payment (4 entries) | L63: employee_transaction(transaction_type=payment, amount=1000.0, employee_name=Ram; 2026-10-04) | M63: Correct | O63: Correct | P63: Correct | Q63: employee_transaction(employee_name=Ram, transaction_type=payment, amount=1000, note=advance, date=2026-10-05) | R63: Correct | T63: 1349
A64: EMP-E-07 | B64: E - Mixed | C64: 3 | D64: SBI bhatte ko 10000 diye, Ram ko 1000 advance diya aur bijli ka bill 1200 bhara | E64: एसबीआई भट्टे को 10000 दिए, राम को 1000 एडवांस दिया और बिजली का बिल 1200 भरा | F64: Paid SBI Bhatta 10000, gave Ram 1000 advance and paid the electricity bill of 1200 | G64: ENTRY | I64: record_expense | J64: amount=1200; category=utility; date=T | K64: Supplier payment + employee advance + expense with payment (4 entries) | L64: expense(amount=1200.0, category=misc, description=bijli bill; 2026-10-04) | M64: Correct | O64: Correct | P64: Correct | Q64: expense(amount=1200, category=misc, date=2026-10-05) | R64: Correct | T64: 1349
A65: EMP-E-07 | B65: E - Mixed | C65: 4 | D65: SBI bhatte ko 10000 diye, Ram ko 1000 advance diya aur bijli ka bill 1200 bhara | E65: एसबीआई भट्टे को 10000 दिए, राम को 1000 एडवांस दिया और बिजली का बिल 1200 भरा | F65: Paid SBI Bhatta 10000, gave Ram 1000 advance and paid the electricity bill of 1200 | G65: ENTRY | I65: record_expense_payment | J65: amount=1200; date=T | K65: Supplier payment + employee advance + expense with payment (4 entries) | L65: expense_payment(amount=10000.0, description=SBI bhatte ko 10000 diye; 2026-10-04) | M65: Correct | O65: Correct | P65: Correct | Q65: expense_payment(amount=1200, date=2026-10-05) | R65: Correct | T65: 1349
A66: EMP-E-08 | B66: E - Mixed | C66: 1 | D66: Purane bazaar wali site pe aaj chhat todi, Sohan ne wahan 700 ka kaam kiya | E66: पुराने बाज़ार वाली साइट पे आज छत तोड़ी, सोहन ने वहाँ 700 का काम किया | F66: Broke a roof at the old market site today, Sohan did 700 worth of work there | G66: ENTRY | I66: record_work_log | J66: location_type=site; description=chhat todi; date=T | K66: Business work log + employee work at the same site | L66: work_log(location_type=site, description=chhat todi; 2026-10-04) | M66: Correct | O66: Missed | P66: Correct | Q66: work_log() | R66: Correct | T66: 1349
A67: EMP-E-08 | B67: E - Mixed | C67: 2 | D67: Purane bazaar wali site pe aaj chhat todi, Sohan ne wahan 700 ka kaam kiya | E67: पुराने बाज़ार वाली साइट पे आज छत तोड़ी, सोहन ने वहाँ 700 का काम किया | F67: Broke a roof at the old market site today, Sohan did 700 worth of work there | G67: ENTRY | H67: Employee | I67: record_employee_transaction | J67: employee_name=Sohan; transaction_type=work; amount=700; date=T | K67: Business work log + employee work at the same site | L67: employee_transaction(transaction_type=work, amount=700.0, employee_name=Sohan; 2026-10-04) | M67: Correct | O67: Missed | P67: Correct | Q67: employee_transaction(employee_name=Sohan, transaction_type=work, amount=700, note=wahan kaam kiya, date=2026-10-05) | R67: Correct | T67: 1349
A68: EMP-E-09 | B68: E - Mixed | C68: 1 | D68: Kitanu gudam se 50 khidkiyan shop pe le gaya, aaj uski haaziri poori | E68: कितनू गोदाम से 50 खिड़कियाँ दुकान पे ले गया, आज उसकी हाज़िरी पूरी | F68: Kitanu took 50 windows from the warehouse to the shop, full attendance for him today | G68: ENTRY | I68: record_material_movement | J68: item_name=khidki; quantity=50; source_name=gudam; destination_name=shop; date=T | K68: Material movement + attendance of the driver | L68: CRASH: AttributeError | M68: Missed | N68: Crash: AttributeError in tool_argument_extraction (material movement source_type) | O68: Missed | P68: Missed | Q68: material_movement(item_name=khidkiyan, quantity=50, date=2026-10-05) | R68: Correct | T68: 1349
A69: EMP-E-09 | B69: E - Mixed | C69: 2 | D69: Kitanu gudam se 50 khidkiyan shop pe le gaya, aaj uski haaziri poori | E69: कितनू गोदाम से 50 खिड़कियाँ दुकान पे ले गया, आज उसकी हाज़िरी पूरी | F69: Kitanu took 50 windows from the warehouse to the shop, full attendance for him today | G69: ENTRY | H69: Employee | I69: record_attendance | J69: employee_name=Kitanu; attendance=P; date=T | K69: Material movement + attendance of the driver | L69: CRASH: AttributeError | M69: Missed | N69: Crash: AttributeError in tool_argument_extraction (material movement source_type) | O69: Missed | P69: Missed | Q69: attendance(employee_name=Kitanu, attendance=P, driving=absent, date=2026-10-05) | R69: Correct | T69: 1349
A70: EMP-E-10 | B70: E - Mixed | C70: 1 | D70: Kal Ram ne 500 ka kaam kiya tha, aaj Suresh Traders ko 1000 eent 9000 mein di aur 4000 haath ke haath le liye | E70: कल राम ने 500 का काम किया था, आज सुरेश ट्रेडर्स को 1000 ईंट 9000 में दी और 4000 हाथ के हाथ ले लिए | F70: Yesterday Ram did 500 worth of work; today sold 1000 bricks to Suresh Traders for 9000 and took 4000 on the spot | G70: ENTRY | H70: Employee | I70: record_employee_transaction | J70: employee_name=Ram; transaction_type=work; amount=500; date=T-1 | K70: Two dates in one message; 'le liye' here = money received from customer | L70: asked location type (UNKNOWN) | M70: Missed | N70: Sale grouped as movement with source 'UNKNOWN'; location question blocked all | O70: Missed | P70: Missed | Q70: employee_transaction(employee_name=Ram, transaction_type=work, amount=500, date=2026-10-04) | R70: Correct | T70: 1349
A71: EMP-E-10 | B71: E - Mixed | C71: 2 | D71: Kal Ram ne 500 ka kaam kiya tha, aaj Suresh Traders ko 1000 eent 9000 mein di aur 4000 haath ke haath le liye | E71: कल राम ने 500 का काम किया था, आज सुरेश ट्रेडर्स को 1000 ईंट 9000 में दी और 4000 हाथ के हाथ ले लिए | F71: Yesterday Ram did 500 worth of work; today sold 1000 bricks to Suresh Traders for 9000 and took 4000 on the spot | G71: ENTRY | H71: Customer | I71: record_sale_transaction | J71: customer_name=Suresh Traders; item_name=eent; quantity=1000; amount=9000; date=T | K71: Two dates in one message; 'le liye' here = money received from customer | L71: asked location type (UNKNOWN) | M71: Missed | N71: Sale grouped as movement with source 'UNKNOWN'; location question blocked all | O71: Missed | P71: Missed | Q71: sale_transaction(customer_name=Suresh Traders, item_name=eent, quantity=1000, amount=9000, note=4000 haath ke haath le liye, date=2026-10-05) | R71: Correct | T71: 1349
A72: EMP-E-10 | B72: E - Mixed | C72: 3 | D72: Kal Ram ne 500 ka kaam kiya tha, aaj Suresh Traders ko 1000 eent 9000 mein di aur 4000 haath ke haath le liye | E72: कल राम ने 500 का काम किया था, आज सुरेश ट्रेडर्स को 1000 ईंट 9000 में दी और 4000 हाथ के हाथ ले लिए | F72: Yesterday Ram did 500 worth of work; today sold 1000 bricks to Suresh Traders for 9000 and took 4000 on the spot | G72: ENTRY | H72: Customer | I72: record_sale_payment | J72: customer_name=Suresh Traders; amount=4000; date=T | K72: Two dates in one message; 'le liye' here = money received from customer | L72: asked location type (UNKNOWN) | M72: Missed | N72: Sale grouped as movement with source 'UNKNOWN'; location question blocked all | O72: Missed | P72: Missed | Q72: sale_payment(customer_name=Suresh Traders, amount=4000, date=2026-10-05) | R72: Correct | T72: 1349

Sheet Customer
A1: Customer bundle — test cases and results (before vs after fixes)
A2: Yellow = written and locked before the first run · Green = from the runs. Before = v1 code (2026-10-05 17:57, Hinglish) · After = the last FULL run of the bundle after the fixes (Hinglish; every test in one run; run id in the After - Run column).
A3: After = full 50-test run 2026-10-05 22:14, Hinglish.
A4: Test ID | B4: Category | C4: Event # | D4: Statement (Hinglish) | E4: Statement (Hindi) | F4: Statement (English) | G4: Expected Outcome | H4: Expected Role | I4: Expected Tool | J4: Expected Arguments | K4: Why this test | L4: Before — Actual (Hinglish) | M4: Before — Result (Hinglish) | N4: Before — Remark | O4: After — Actual (Hinglish) | P4: After — Result (Hinglish) | Q4: After — Remark | R4: After — Run
A5: CUS-A-01 | B5: A - Daily | C5: 1 | D5: Sharma ji ko 500 eent 4000 mein bechi | E5: शर्मा जी को 500 ईंट 4000 में बेची | F5: Sold 500 bricks to Sharma ji for 4000 | G5: ENTRY | H5: Customer | I5: record_sale_transaction | J5: customer_name=Sharma ji; item_name=eent; quantity=500; amount=4000; date=T | K5: Most common daily sale | L5: sale_transaction(customer_name=Sharma ji, item_name=eent, quantity=500, amount=4000, date=2026-10-05) | M5: Correct | O5: sale_transaction(customer_name=Sharma ji, item_name=eent, quantity=500, amount=4000, date=2026-10-05) | P5: Correct | R5: 2214
A6: CUS-A-02 | B6: A - Daily | C6: 1 | D6: Suresh Traders se aaj 3000 aaye | E6: सुरेश ट्रेडर्स से आज 3000 आए | F6: Received 3000 from Suresh Traders today | G6: ENTRY | H6: Customer | I6: record_sale_payment | J6: customer_name=Suresh Traders; amount=3000; date=T | K6: Most common daily payment received | L6: sale_payment(customer_name=Suresh Traders, amount=3000, date=2026-10-05) | M6: Correct | O6: sale_payment(customer_name=Suresh Traders, amount=3000, date=2026-10-05) | P6: Correct | R6: 2214
A7: CUS-A-03 | B7: A - Daily | C7: 1 | D7: Sharma ji ko 2 darwaze 1800 mein diye, paise baad mein denge | E7: शर्मा जी को 2 दरवाज़े 1800 में दिए, पैसे बाद में देंगे | F7: Gave Sharma ji 2 doors for 1800, he will pay later | G7: ENTRY | H7: Customer | I7: record_sale_transaction | J7: customer_name=Sharma ji; item_name=darwaza; quantity=2; amount=1800; date=T | K7: Credit sale — 'will pay later' must NOT create a payment | L7: sale_transaction(customer_name=Sharma ji, item_name=darwaze, quantity=2, amount=1800, date=2026-10-05) | M7: Correct | O7: sale_transaction(customer_name=Sharma ji, item_name=darwaze, quantity=2, amount=1800, note=paise baad mein denge, date=2026-10-05) | P7: Correct | R7: 2214
A8: CUS-A-04 | B8: A - Daily | C8: 1 | D8: Suresh Traders ko gudam se 1000 eent bheji, 8 rupaye eent ke hisab se | E8: सुरेश ट्रेडर्स को गोदाम से 1000 ईंट भेजी, 8 रुपये ईंट के हिसाब से | F8: Sent 1000 bricks from the warehouse to Suresh Traders at 8 rupees per brick | G8: ENTRY | H8: Customer | I8: record_sale_transaction | J8: customer_name=Suresh Traders; item_name=eent; quantity=1000; rate=8; amount=8000; source=gudam; date=T | K8: Rate × quantity; source location | L8: sale_transaction(customer_name=Suresh Traders, item_name=eent, quantity=1000, rate=8, source=Gudam, date=2026-10-05) | M8: Silent wrong | N8: record_sale_transaction: amount 0.0≠8000 | O8: sale_transaction(customer_name=Suresh Traders, item_name=eent, quantity=1000, rate=8, amount=8000, source=Gudam, date=2026-10-05) | P8: Correct | R8: 2214
A9: CUS-A-05 | B9: A - Daily | C9: 1 | D9: Sharma ji ne pichla 2000 de diya | E9: शर्मा जी ने पिछला 2000 दे दिया | F9: Sharma ji paid the previous 2000 | G9: ENTRY | H9: Customer | I9: record_sale_payment | J9: customer_name=Sharma ji; amount=2000; date=T | K9: Money received TODAY for old dues — payment, not an opening balance | L9: sale_payment(customer_name=Sharma ji, amount=2000, note=pichla, date=2026-10-05) | M9: Correct | O9: sale_payment(customer_name=Sharma ji, amount=2000, note=pichla, date=2026-10-05) | P9: Correct | R9: 2214
A10: CUS-A-06 | B10: A - Daily | C10: 1 | D10: Kal Sharma ji ko 4 khidkiyan 2400 mein bechi aur poore paise mil gaye | E10: कल शर्मा जी को 4 खिड़कियाँ 2400 में बेचीं और पूरे पैसे मिल गए | F10: Yesterday sold 4 windows to Sharma ji for 2400 and got the full payment | G10: ENTRY | H10: Customer | I10: record_sale_transaction | J10: customer_name=Sharma ji; item_name=khidki; quantity=4; amount=2400; date=T-1 | K10: Sale + full payment, both yesterday | L10: sale_transaction(customer_name=Sharma ji, item_name=khidkiyan, quantity=4, amount=2400, date=2026-10-04) | M10: Correct | O10: sale_transaction(customer_name=Sharma ji, item_name=khidkiyan, quantity=4, amount=2400, date=2026-10-04) | P10: Correct | R10: 2214
A11: CUS-A-06 | B11: A - Daily | C11: 2 | D11: Kal Sharma ji ko 4 khidkiyan 2400 mein bechi aur poore paise mil gaye | E11: कल शर्मा जी को 4 खिड़कियाँ 2400 में बेचीं और पूरे पैसे मिल गए | F11: Yesterday sold 4 windows to Sharma ji for 2400 and got the full payment | G11: ENTRY | H11: Customer | I11: record_sale_payment | J11: customer_name=Sharma ji; amount=2400; date=T-1 | K11: Sale + full payment, both yesterday | L11: asked location (source) → Pata nahi | M11: Missed | O11: sale_payment(customer_name=Sharma ji, amount=2400, note=Poore paise mil gaye, date=2026-10-04) | P11: Correct | R11: 2214
A12: CUS-A-07 | B12: A - Daily | C12: 1 | D12: Suresh Traders ko 3 chaukhat 1500 ki di, 1000 nakad mile | E12: सुरेश ट्रेडर्स को 3 चौखट 1500 की दी, 1000 नकद मिले | F12: Gave Suresh Traders 3 door frames worth 1500, received 1000 in cash | G12: ENTRY | H12: Customer | I12: record_sale_transaction | J12: customer_name=Suresh Traders; item_name=chaukhat; quantity=3; amount=1500; date=T | K12: Sale + partial cash payment | L12: sale_transaction(customer_name=Suresh Traders, item_name=chaukhat, quantity=3, unit=piece, amount=1500, date=2026-10-05) | M12: Correct | O12: sale_transaction(customer_name=Suresh Traders, item_name=chaukhat, quantity=3, unit=piece, amount=1500, date=2026-10-05) | P12: Correct | R12: 2214
A13: CUS-A-07 | B13: A - Daily | C13: 2 | D13: Suresh Traders ko 3 chaukhat 1500 ki di, 1000 nakad mile | E13: सुरेश ट्रेडर्स को 3 चौखट 1500 की दी, 1000 नकद मिले | F13: Gave Suresh Traders 3 door frames worth 1500, received 1000 in cash | G13: ENTRY | H13: Customer | I13: record_sale_payment | J13: customer_name=Suresh Traders; amount=1000; date=T | K13: Sale + partial cash payment | L13: sale_payment(customer_name=Suresh Traders, amount=1000, date=2026-10-05) | M13: Correct | O13: sale_payment(customer_name=Suresh Traders, amount=1000, note=3 chaukhat 1500 ki di, date=2026-10-05) | P13: Correct | R13: 2214
A14: CUS-A-08 | B14: A - Daily | C14: 1 | D14: Sharma ji ne PhonePe pe 1200 bheje | E14: शर्मा जी ने फोनपे पे 1200 भेजे | F14: Sharma ji sent 1200 on PhonePe | G14: ENTRY | H14: Customer | I14: record_sale_payment | J14: customer_name=Sharma ji; amount=1200; date=T | K14: UPI payment received | L14: sale_payment(customer_name=Sharma ji, amount=1200, date=2026-10-05) | M14: Correct | O14: sale_payment(customer_name=Sharma ji, amount=1200, date=2026-10-05) | P14: Correct | R14: 2214
